Workbook

Sheet Monthly Summary
A1: Month | B1: Period | C1: Canada | D1: Total | E1: Strong matches | F1: Global North | G1: Global South
A2: 2024-01 | B2: Pre-withdrawal | C2: =COUNTIFS('All Articles'!$A:$A,$A2,'All Articles'!$D:$D,C$1) | D2: =SUM(C2:C2) | E2: =COUNTIFS('All Articles'!$A:$A,$A2,'All Articles'!$M:$M,"Yes") | F2: =COUNTIFS('All Articles'!$A:$A,$A2,'All Articles'!$E:$E,"Global North") | G2: =COUNTIFS('All Articles'!$A:$A,$A2,'All Articles'!$E:$E,"Global South")
A3: 2024-02 | B3: Pre-withdrawal | C3: =COUNTIFS('All Articles'!$A:$A,$A3,'All Articles'!$D:$D,C$1) | D3: =SUM(C3:C3) | E3: =COUNTIFS('All Articles'!$A:$A,$A3,'All Articles'!$M:$M,"Yes") | F3: =COUNTIFS('All Articles'!$A:$A,$A3,'All Articles'!$E:$E,"Global North") | G3: =COUNTIFS('All Articles'!$A:$A,$A3,'All Articles'!$E:$E,"Global South")
A4: 2024-03 | B4: Pre-withdrawal | C4: =COUNTIFS('All Articles'!$A:$A,$A4,'All Articles'!$D:$D,C$1) | D4: =SUM(C4:C4) | E4: =COUNTIFS('All Articles'!$A:$A,$A4,'All Articles'!$M:$M,"Yes") | F4: =COUNTIFS('All Articles'!$A:$A,$A4,'All Articles'!$E:$E,"Global North") | G4: =COUNTIFS('All Articles'!$A:$A,$A4,'All Articles'!$E:$E,"Global South")
A5: 2024-04 | B5: Pre-withdrawal | C5: =COUNTIFS('All Articles'!$A:$A,$A5,'All Articles'!$D:$D,C$1) | D5: =SUM(C5:C5) | E5: =COUNTIFS('All Articles'!$A:$A,$A5,'All Articles'!$M:$M,"Yes") | F5: =COUNTIFS('All Articles'!$A:$A,$A5,'All Articles'!$E:$E,"Global North") | G5: =COUNTIFS('All Articles'!$A:$A,$A5,'All Articles'!$E:$E,"Global South")
A6: 2024-05 | B6: Pre-withdrawal | C6: =COUNTIFS('All Articles'!$A:$A,$A6,'All Articles'!$D:$D,C$1) | D6: =SUM(C6:C6) | E6: =COUNTIFS('All Articles'!$A:$A,$A6,'All Articles'!$M:$M,"Yes") | F6: =COUNTIFS('All Articles'!$A:$A,$A6,'All Articles'!$E:$E,"Global North") | G6: =COUNTIFS('All Articles'!$A:$A,$A6,'All Articles'!$E:$E,"Global South")
A7: 2024-06 | B7: Pre-withdrawal | C7: =COUNTIFS('All Articles'!$A:$A,$A7,'All Articles'!$D:$D,C$1) | D7: =SUM(C7:C7) | E7: =COUNTIFS('All Articles'!$A:$A,$A7,'All Articles'!$M:$M,"Yes") | F7: =COUNTIFS('All Articles'!$A:$A,$A7,'All Articles'!$E:$E,"Global North") | G7: =COUNTIFS('All Articles'!$A:$A,$A7,'All Articles'!$E:$E,"Global South")
A8: 2024-07 | B8: Pre-withdrawal | C8: =COUNTIFS('All Articles'!$A:$A,$A8,'All Articles'!$D:$D,C$1) | D8: =SUM(C8:C8) | E8: =COUNTIFS('All Articles'!$A:$A,$A8,'All Articles'!$M:$M,"Yes") | F8: =COUNTIFS('All Articles'!$A:$A,$A8,'All Articles'!$E:$E,"Global North") | G8: =COUNTIFS('All Articles'!$A:$A,$A8,'All Articles'!$E:$E,"Global South")
A9: 2024-08 | B9: Pre-withdrawal | C9: =COUNTIFS('All Articles'!$A:$A,$A9,'All Articles'!$D:$D,C$1) | D9: =SUM(C9:C9) | E9: =COUNTIFS('All Articles'!$A:$A,$A9,'All Articles'!$M:$M,"Yes") | F9: =COUNTIFS('All Articles'!$A:$A,$A9,'All Articles'!$E:$E,"Global North") | G9: =COUNTIFS('All Articles'!$A:$A,$A9,'All Articles'!$E:$E,"Global South")
A10: 2024-09 | B10: Pre-withdrawal | C10: =COUNTIFS('All Articles'!$A:$A,$A10,'All Articles'!$D:$D,C$1) | D10: =SUM(C10:C10) | E10: =COUNTIFS('All Articles'!$A:$A,$A10,'All Articles'!$M:$M,"Yes") | F10: =COUNTIFS('All Articles'!$A:$A,$A10,'All Articles'!$E:$E,"Global North") | G10: =COUNTIFS('All Articles'!$A:$A,$A10,'All Articles'!$E:$E,"Global South")
A11: 2024-10 | B11: Pre-withdrawal | C11: =COUNTIFS('All Articles'!$A:$A,$A11,'All Articles'!$D:$D,C$1) | D11: =SUM(C11:C11) | E11: =COUNTIFS('All Articles'!$A:$A,$A11,'All Articles'!$M:$M,"Yes") | F11: =COUNTIFS('All Articles'!$A:$A,$A11,'All Articles'!$E:$E,"Global North") | G11: =COUNTIFS('All Articles'!$A:$A,$A11,'All Articles'!$E:$E,"Global South")
A12: 2024-11 | B12: Pre-withdrawal | C12: =COUNTIFS('All Articles'!$A:$A,$A12,'All Articles'!$D:$D,C$1) | D12: =SUM(C12:C12) | E12: =COUNTIFS('All Articles'!$A:$A,$A12,'All Articles'!$M:$M,"Yes") | F12: =COUNTIFS('All Articles'!$A:$A,$A12,'All Articles'!$E:$E,"Global North") | G12: =COUNTIFS('All Articles'!$A:$A,$A12,'All Articles'!$E:$E,"Global South")
A13: 2024-12 | B13: Pre-withdrawal | C13: =COUNTIFS('All Articles'!$A:$A,$A13,'All Articles'!$D:$D,C$1) | D13: =SUM(C13:C13) | E13: =COUNTIFS('All Articles'!$A:$A,$A13,'All Articles'!$M:$M,"Yes") | F13: =COUNTIFS('All Articles'!$A:$A,$A13,'All Articles'!$E:$E,"Global North") | G13: =COUNTIFS('All Articles'!$A:$A,$A13,'All Articles'!$E:$E,"Global South")
... A30: 2026-05 | B30: Post-withdrawal | C30: =COUNTIFS('All Articles'!$A:$A,$A30,'All Articles'!$D:$D,C$1) | D30: =SUM(C30:C30) | E30: =COUNTIFS('All Articles'!$A:$A,$A30,'All Articles'!$M:$M,"Yes") | F30: =COUNTIFS('All Articles'!$A:$A,$A30,'All Articles'!$E:$E,"Global North") | G30: =COUNTIFS('All Articles'!$A:$A,$A30,'All Articles'!$E:$E,"Global South")
A31: Total | C31: =SUM(C2:C30) | D31: =SUM(D2:D30) | E31: =SUM(E2:E30) | F31: =SUM(F2:F30) | G31: =SUM(G2:G30)
A33: Undated articles | C33: =COUNTIFS('All Articles'!$A:$A,"Undated")
A35: Period | C35: Canada | D35: Total
A36: Pre-withdrawal | C36: =COUNTIFS('All Articles'!$C:$C,$A36,'All Articles'!$D:$D,C$35) | D36: =SUM(C36:C36)
A37: Transition | C37: =COUNTIFS('All Articles'!$C:$C,$A37,'All Articles'!$D:$D,C$35) | D37: =SUM(C37:C37)
A38: Post-withdrawal | C38: =COUNTIFS('All Articles'!$C:$C,$A38,'All Articles'!$D:$D,C$35) | D38: =SUM(C38:C38)
A40: Shaded cells = no articles collected for that country in that month (a coverage gap).

Sheet All Articles
A1: Month | B1: Date | C1: Period | D1: Country | E1: North/South | F1: Continent | G1: Source Type | H1: Document Type | I1: Site | J1: Title | K1: URL | L1: Matched Keywords | M1: Strong Match | N1: Keyword Count | O1: Minister/Person Country | P1: Date Source | Q1: Fetched Via | R1: Word Count | S1: Event/Person hits | T1: Adjective Indicators hits | U1: Organizations/Alliances hits | V1: Regulatory Bodies hits
A2: 2024-01 | B2: 45293 | C2: Pre-withdrawal | D2: Canada | E2: Global North | F2: North America | G2: Ministry of Environment | H2: Press release | I2: canada.ca | J2: The Government of Canada is seeking feedback on developing a federal plastics registry to help tackle plastic pollution | K2: https://www.canada.ca/en/environment-climate-change/news/2024/01/the-government-of-canada-is-seeking-feedback-on-developing-a-federal-plastics-registry-to-help-tackle-plastic-pollution.html | L2: Circular; Circular Economy; Climate; Climate Change; Environment; Steven Guilbeault; transition | M2: Yes | N2: 7 | O2: Canada | P2: page metadata | Q2: live | R2: 733 | S2: Steven Guilbeault | T2: Circular; Circular Economy; Climate; Climate Change; Environment; transition
A3: 2024-01 | B3: 45302 | C3: Pre-withdrawal | D3: Canada | E3: Global North | F3: North America | G3: Ministry of Environment | H3: Press release | I3: canada.ca | J3: Environment and Climate Change Canada to hold a technical briefing and media availability related to a winter storm affecting Ontario and Quebec this weekend | K3: https://www.canada.ca/en/environment-climate-change/news/2024/01/environment-and-climate-change-canada-to-hold-a-technical-briefing-and-media-availability-related-to-a-winter-storm-affecting-ontario-and-quebec-th.html | L3: Climate; Climate Change; Environment | M3: No | N3: 3 | P3: page metadata | Q3: live | R3: 223 | T3: Climate; Climate Change; Environment
A4: 2024-01 | B4: 45303 | C4: Pre-withdrawal | D4: Canada | E4: Global North | F4: North America | G4: Ministry of Environment | H4: Press release | I4: canada.ca | J4: Eligible Canadian residents to receive their first pollution pricing rebate of the year | K4: https://www.canada.ca/en/environment-climate-change/news/2024/01/eligible-canadian-residents-to-receive-their-first-pollution-pricing-rebate-of-the-year.html | L4: Climate; Climate Change; Environment; Steven Guilbeault; carbon; emissions; energy; net zero emissions | M4: Yes | N4: 8 | O4: Canada | P4: page metadata | Q4: live | R4: 880 | S4: Steven Guilbeault | T4: Climate; Climate Change; Environment; carbon; emissions; energy; net zero emissions
A5: 2024-01 | B5: 45303 | C5: Pre-withdrawal | D5: Canada | E5: Global North | F5: North America | G5: Ministry of Environment | H5: Press release | I5: canada.ca | J5: Minister Guilbeault to make an announcement to support the Université de Sherbrooke’s work on environmental research | K5: https://www.canada.ca/en/environment-climate-change/news/2024/01/minister-guilbeault-to-make-an-announcement-to-support-the-universite-de-sherbrookes-work-on-environmental-research.html | L5: Climate; Climate Change; Environment; Steven Guilbeault | M5: Yes | N5: 4 | O5: Canada | P5: page metadata | Q5: live | R5: 196 | S5: Steven Guilbeault | T5: Climate; Climate Change; Environment
A6: 2024-01 | B6: 45306 | C6: Pre-withdrawal | D6: Canada | E6: Global North | F6: North America | G6: Ministry of Environment | H6: Press release | I6: canada.ca | J6: Government of Canada announces new investments in environmental research for the Université de Sherbrooke | K6: https://www.canada.ca/en/environment-climate-change/news/2024/01/government-of-canada-announces-new-investments-in-environmental-research-for-the-universite-de-sherbrooke.html | L6: Climate; Climate Change; Environment; Environmental Policy; Steven Guilbeault; carbon; emissions; greenhouse gas | M6: Yes | N6: 8 | O6: Canada | P6: page metadata | Q6: live | R6: 1074 | S6: Steven Guilbeault | T6: Climate; Climate Change; Environment; Environmental Policy; carbon; emissions; greenhouse gas
A7: 2024-01 | B7: 45310 | C7: Pre-withdrawal | D7: Canada | E7: Global North | F7: North America | G7: Ministry of Environment | H7: Press release | I7: canada.ca | J7: Government of Canada to make an announcement on funding for freshwater ecosystem initiatives | K7: https://www.canada.ca/en/environment-climate-change/news/2024/01/government-of-canada-to-make-an-announcement-on-funding-for-freshwater-ecosystem-initiatives.html | L7: Climate; Climate Change; Environment; Steven Guilbeault | M7: Yes | N7: 4 | O7: Canada | P7: page metadata | Q7: live | R7: 159 | S7: Steven Guilbeault | T7: Climate; Climate Change; Environment
A8: 2024-01 | B8: 45313 | C8: Pre-withdrawal | D8: Canada | E8: Global North | F8: North America | G8: Ministry of Environment | H8: Press release | I8: canada.ca | J8: Federal Government opens the door to projects that help keep Canadian fresh water clean and healthy | K8: https://www.canada.ca/en/environment-climate-change/news/2024/01/federal-government-opens-the-door-to-projects-that-help-keep-canadian-fresh-water-clean-and-healthy.html | L8: Climate; Climate Change; Environment; Steven Guilbeault | M8: Yes | N8: 4 | O8: Canada | P8: page metadata | Q8: live | R8: 1070 | S8: Steven Guilbeault | T8: Climate; Climate Change; Environment
A9: 2024-01 | B9: 45313 | C9: Pre-withdrawal | D9: Canada | E9: Global North | F9: North America | G9: Ministry of Environment | H9: Press release | I9: canada.ca | J9: Operation Northern Fur leads to $20,000 in fines and a prohibition order for a Manitoba resident who illegally imported, exported, and transported wildlife | K9: https://www.canada.ca/en/environment-climate-change/news/2024/01/operation-northern-fur-leads-to-20000-in-fines-and-a-prohibition-order-for-a-manitoba-resident-who-illegally-imported-exported-and-transported-wild.html | L9: Climate; Climate Change; Environment | M9: No | N9: 3 | P9: page metadata | Q9: live | R9: 619 | T9: Climate; Climate Change; Environment
A10: 2024-01 | B10: 45317 | C10: Pre-withdrawal | D10: Canada | E10: Global North | F10: North America | G10: Ministry of Environment | H10: Press release | I10: canada.ca | J10: Canada boosts conservation and restoration efforts with investments in 27 new Indigenous-Led Natural Climate Solutions | K10: https://www.canada.ca/en/environment-climate-change/news/2024/01/canada-boosts-conservation-and-restoration-efforts-with-investments-in-27-new-indigenous-led-natural-climate-solutions.html | L10: Climate; Climate Change; Environment; Steven Guilbeault; Sustainability; carbon; emissions; greenhouse gas | M10: Yes | N10: 8 | O10: Canada | P10: page metadata | Q10: live | R10: 1021 | S10: Steven Guilbeault | T10: Climate; Climate Change; Environment; Sustainability; carbon; emissions; greenhouse gas
A11: 2024-01 | B11: 45317 | C11: Pre-withdrawal | D11: Canada | E11: Global North | F11: North America | G11: Ministry of Environment | H11: Press release | I11: canada.ca | J11: List of 27 Indigenous-Led Natural Climate Solutions projects 2023–2024 | K11: https://www.canada.ca/en/environment-climate-change/news/2024/01/list-of-27-indigenous-led-natural-climate-solutions-projects-20232024.html | L11: Climate; Climate Change; Climate change mitigation; carbon; emissions; greenhouse gas | M11: Yes | N11: 6 | P11: page metadata | Q11: live | R11: 1927 | T11: Climate; Climate Change; Climate change mitigation; carbon; emissions; greenhouse gas
A12: 2024-01 | B12: 45317 | C12: Pre-withdrawal | D12: Canada | E12: Global North | F12: North America | G12: Ministry of Environment | H12: Policy / regulatory | I12: canada.ca | J12: North West Redwater Partnership paid $280,428 to the Environmental Damages Fund as part of an environmental protection alternative measures agreement under the Canadian Environmental Protection Act, 1999 | K12: https://www.canada.ca/en/environment-climate-change/news/2024/01/north-west-redwater-partnership-paid-280428-to-the-environmental-damages-fund-as-part-of-an-environmental-protection-alternative-measures-agreement.html | L12: Climate; Climate Change; Environment | M12: No | N12: 3 | P12: page metadata | Q12: live | R12: 691 | T12: Climate; Climate Change; Environment
A13: 2024-01 | B13: 45321 | C13: Pre-withdrawal | D13: Canada | E13: Global North | F13: North America | G13: Ministry of Environment | H13: Press release | I13: canada.ca | J13: Environment and Climate Change Canada Study of Winter Air Pollution in Toronto begins | K13: https://www.canada.ca/en/environment-climate-change/news/2024/01/environment-and-climate-change-canada-study-of-winter-air-pollution-in-toronto-begins.html | L13: Climate; Climate Change; Environment; carbon | M13: Yes | N13: 4 | P13: page metadata | Q13: live | R13: 570 | T13: Climate; Climate Change; Environment; carbon
A14: 2024-01 | B14: 45321 | C14: Pre-withdrawal | D14: Canada | E14: Global North | F14: North America | G14: Ministry of Environment | H14: Press release | I14: canada.ca | J14: Two Quebecers convicted of violating the Migratory Birds Regulations by destroying the nests of endangered Bank Swallows | K14: https://www.canada.ca/en/environment-climate-change/news/2024/01/two-quebecers-convicted-of-violating-the-migratory-birds-regulations-by-destroying-the-nests-of-endangered-bank-swallows.html | L14: Climate; Climate Change; Environment | M14: No | N14: 3 | P14: page metadata | Q14: live | R14: 485 | T14: Climate; Climate Change; Environment
A15: 2024-01 | B15: 45322 | C15: Pre-withdrawal | D15: Canada | E15: Global North | F15: North America | G15: Ministry of Environment | H15: Press release | I15: canada.ca | J15: Forty-two Indigenous-led conservation projects across Canada receive federal funding to protect more nature | K15: https://www.canada.ca/en/environment-climate-change/news/2024/01/forty-two-indigenous-led-conservation-projects-across-canada-receive-federal-funding-to-protect-more-nature.html | L15: Climate; Climate Change; Environment; Steven Guilbeault; Sustainability | M15: Yes | N15: 5 | O15: Canada | P15: page metadata | Q15: live | R15: 1284 | S15: Steven Guilbeault | T15: Climate; Climate Change; Environment; Sustainability
A16: 2024-02 | B16: 45324 | C16: Pre-withdrawal | D16: Canada | E16: Global North | F16: North America | G16: Ministry of Environment | H16: Press release | I16: canada.ca | J16: Government of Canada launches public engagement on the 2035 greenhouse gas emissions reduction target | K16: https://www.canada.ca/en/environment-climate-change/news/2024/02/government-of-canada-launches-public-engagement-on-the-2035-greenhouse-gas-emissions-reduction-target.html | L16: Climate; Climate Change; Environment; Paris Agreement; Steven Guilbeault; climate goals; emissions; energy; greenhouse gas; net zero emissions | M16: Yes | N16: 10 | O16: Canada | P16: page metadata | Q16: live | R16: 782 | S16: Steven Guilbeault | T16: Climate; Climate Change; Environment; climate goals; emissions; energy; greenhouse gas; net zero emissions | U16: Paris Agreement
A17: 2024-02 | B17: 45330 | C17: Pre-withdrawal | D17: Canada | E17: Global North | F17: North America | G17: Ministry of Environment | H17: Press release | I17: canada.ca | J17: Canada taking next steps on the right to a healthy environment and environmental justice and racism | K17: https://www.canada.ca/en/environment-climate-change/news/2024/02/canada-taking-next-steps-on-the-right-to-a-healthy-environment-and-environmental-justice-and-racism.html | L17: Climate; Climate Change; Environment | M17: No | N17: 3 | P17: page metadata | Q17: live | R17: 485 | T17: Climate; Climate Change; Environment
A18: 2024-02 | B18: 45330 | C18: Pre-withdrawal | D18: Canada | E18: Global North | F18: North America | G18: Ministry of Environment | H18: Policy / regulatory | I18: canada.ca | J18: Creating a healthy, clean, and sustainable environment for all: Canada consulting on the right to a healthy environment in federal legislation and engaging on environmental justice and racism | K18: https://www.canada.ca/en/environment-climate-change/news/2024/02/creating-a-healthy-clean-and-sustainable-environment-for-all-canada-consulting-on-the-right-to-a-healthy-environment-in-federal-legislation-and-eng.html | L18: Climate; Climate Change; Environment; Steven Guilbeault | M18: Yes | N18: 4 | O18: Canada | P18: page metadata | Q18: live | R18: 776 | S18: Steven Guilbeault | T18: Climate; Climate Change; Environment
A19: 2024-02 | B19: 45335 | C19: Pre-withdrawal | D19: Canada | E19: Global North | F19: North America | G19: Ministry of Environment | H19: Press release | I19: canada.ca | J19: Minister Guilbeault to make an announcement to support citizen science and protect nature | K19: https://www.canada.ca/en/environment-climate-change/news/2024/02/minister-guilbeault-to-make-an-announcement-to-support-citizen-science-and-protect-nature.html | L19: Climate; Climate Change; Environment; Steven Guilbeault | M19: Yes | N19: 4 | O19: Canada | P19: page metadata | Q19: live | R19: 167 | S19: Steven Guilbeault | T19: Climate; Climate Change; Environment
A20: 2024-02 | B20: 45336 | C20: Pre-withdrawal | D20: Canada | E20: Global North | F20: North America | G20: Ministry of Environment | H20: Press release | I20: canada.ca | J20: Government of Canada invests $3 million in citizen science and open data for birds and biodiversity | K20: https://www.canada.ca/en/environment-climate-change/news/2024/02/government-of-canada-invests-3-million-in-citizen-science-and-open-data-for-birds-and-biodiversity.html | L20: Climate; Climate Change; Environment; Steven Guilbeault | M20: Yes | N20: 4 | O20: Canada | P20: page metadata | Q20: live | R20: 670 | S20: Steven Guilbeault | T20: Climate; Climate Change; Environment
A21: 2024-02 | B21: 45338 | C21: Pre-withdrawal | D21: Canada | E21: Global North | F21: North America | G21: Ministry of Environment | H21: Press release | I21: canada.ca | J21: Minister Guilbeault provides update with new design options for the Clean Electricity Regulations | K21: https://www.canada.ca/en/environment-climate-change/news/2024/02/minister-guilbeault-provides-update-with-new-design-options-for-the-clean-electricity-regulations.html | L21: Climate; Climate Change; Environment; Steven Guilbeault; carbon; emissions; energy; fossil fuel; net zero emissions; transition | M21: Yes | N21: 10 | O21: Canada | P21: page metadata | Q21: live | R21: 890 | S21: Steven Guilbeault | T21: Climate; Climate Change; Environment; carbon; emissions; energy; fossil fuel; net zero emissions; transition
A22: 2024-02 | B22: 45338 | C22: Pre-withdrawal | D22: Canada | E22: Global North | F22: North America | G22: Ministry of Environment | H22: Policy / regulatory | I22: canada.ca | J22: Town of Trenton fined $100,000 for violating the Fisheries Act in Nova Scotia | K22: https://www.canada.ca/en/environment-climate-change/news/2024/02/town-of-trenton-fined-100000-for-violating-the-fisheries-act-in-nova-scotia.html | L22: Climate; Climate Change; Environment | M22: No | N22: 3 | P22: page metadata | Q22: live | R22: 657 | T22: Climate; Climate Change; Environment
A23: 2024-02 | B23: 45342 | C23: Pre-withdrawal | D23: Canada | E23: Global North | F23: North America | G23: Ministry of Environment | H23: Press release | I23: canada.ca | J23: Minister Guilbeault to make a funding announcement supporting affordable home energy retrofits for the City of Peterborough | K23: https://www.canada.ca/en/environment-climate-change/news/2024/02/minister-guilbeault-to-make-a-funding-announcement-to-support-affordable-heating-for-the-city-of-peterborough.html | L23: Climate; Climate Change; Environment; Steven Guilbeault; energy | M23: Yes | N23: 5 | O23: Canada | P23: page metadata | Q23: live | R23: 178 | S23: Steven Guilbeault | T23: Climate; Climate Change; Environment; energy
A24: 2024-02 | B24: 45343 | C24: Pre-withdrawal | D24: Canada | E24: Global North | F24: North America | G24: Ministry of Environment | H24: Press release | I24: canada.ca | J24: Government of Canada to announce a federal investment to support household energy-saving climate action in Newfoundland and Labrador | K24: https://www.canada.ca/en/environment-climate-change/news/2024/02/government-of-canada-to-announce-a-federal-investment-to-support-household-energy-saving-climate-action-in-newfoundland-and-labrador.html | L24: Climate; Climate Change; Environment; Steven Guilbeault; energy | M24: Yes | N24: 5 | O24: Canada | P24: page metadata | Q24: live | R24: 201 | S24: Steven Guilbeault | T24: Climate; Climate Change; Environment; energy
A25: 2024-02 | B25: 45345 | C25: Pre-withdrawal | D25: Canada | E25: Global North | F25: North America | G25: Ministry of Environment | H25: Press release | I25: canada.ca | J25: Federal-provincial agreement allows Newfoundlanders and Labradorians to switch from heating homes with oil to heat pumps and other electric home heating systems | K25: https://www.canada.ca/en/environment-climate-change/news/2024/02/federal-provincial-agreement-allows-newfoundlanders-and-labradorians-to-switch-from-heating-homes-with-oil-to-heat-pumps-and-other-electric-home-he.html | L25: Climate; Climate Change; Environment; Steven Guilbeault; carbon; emissions; energy; greenhouse gas; net zero emissions; transition | M25: Yes | N25: 10 | O25: Canada | P25: page metadata | Q25: live | R25: 1142 | S25: Steven Guilbeault | T25: Climate; Climate Change; Environment; carbon; emissions; energy; greenhouse gas; net zero emissions; transition
A26: 2024-02 | B26: 45345 | C26: Pre-withdrawal | D26: Canada | E26: Global North | F26: North America | G26: Ministry of Environment | H26: Press release | I26: canada.ca | J26: Government of Canada announces draft rules to cut pollutants that cause smog in communities across Canada | K26: https://www.canada.ca/en/environment-climate-change/news/2024/02/government-of-canada-announces-draft-rules-to-cut-pollutants-that-cause-smog-in-communities-across-canada.html | L26: Climate; Climate Change; Environment; Steven Guilbeault; emissions | M26: Yes | N26: 5 | O26: Canada | P26: page metadata | Q26: live | R26: 996 | S26: Steven Guilbeault | T26: Climate; Climate Change; Environment; emissions
A27: 2024-02 | B27: 45345 | C27: Pre-withdrawal | D27: Canada | E27: Global North | F27: North America | G27: Ministry of Environment | H27: Press release | I27: canada.ca | J27: Reduction in the Release of Volatile Organic Compounds (Storage and Loading of Volatile Petroleum Liquids) draft Regulations | K27: https://www.canada.ca/en/environment-climate-change/news/2024/02/reduction-in-the-release-of-volatile-organic-compounds-storage-and-loading-of-volatile-petroleum-liquids-draft-regulations.html | L27: Climate; Climate Change; Environment; carbon; emissions; energy | M27: Yes | N27: 6 | P27: page metadata | Q27: live | R27: 1449 | T27: Climate; Climate Change; Environment; carbon; emissions; energy
A28: 2024-03 | B28: 45352 | C28: Pre-withdrawal | D28: Canada | E28: Global North | F28: North America | G28: Ministry of Environment | H28: Press release | I28: canada.ca | J28: Minister Guilbeault calls for an ambitious plastics treaty at the United Nations Environment Assembly in Kenya | K28: https://www.canada.ca/en/environment-climate-change/news/2024/03/minister-guilbeault-calls-for-an-ambitious-plastics-treaty-at-the-united-nations-environment-assembly-in-kenya.html | L28: COP; Climate; Climate Change; Environment; Steven Guilbeault | M28: Yes | N28: 5 | O28: Canada | P28: page metadata | Q28: live | R28: 785 | S28: Steven Guilbeault | T28: Climate; Climate Change; Environment | U28: COP
A29: 2024-03 | B29: 45352 | C29: Pre-withdrawal | D29: Canada | E29: Global North | F29: North America | G29: Ministry of Environment | H29: Press release | I29: canada.ca | J29: Minister Guilbeault to make a funding announcement to support species at risk and their habitats | K29: https://www.canada.ca/en/environment-climate-change/news/2024/03/minister-guilbeault-to-make-a-funding-announcement-to-support-species-at-risk-and-their-habitats.html | L29: Climate; Climate Change; Environment; Steven Guilbeault | M29: Yes | N29: 4 | O29: Canada | P29: page metadata | Q29: live | R29: 186 | S29: Steven Guilbeault | T29: Climate; Climate Change; Environment
A30: 2024-03 | B30: 45355 | C30: Pre-withdrawal | D30: Canada | E30: Global North | F30: North America | G30: Ministry of Environment | H30: Press release | I30: canada.ca | J30: Empowering key regional environmental groups to protect habitats and species at risk in Quebec and across Canada | K30: https://www.canada.ca/en/environment-climate-change/news/2024/03/empowering-key-regional-environmental-groups-to-protect-habitats-and-species-at-risk-in-quebec-and-across-canada.html | L30: Climate; Climate Change; Environment; Steven Guilbeault | M30: Yes | N30: 4 | O30: Canada | P30: page metadata | Q30: live | R30: 916 | S30: Steven Guilbeault | T30: Climate; Climate Change; Environment
A31: 2024-03 | B31: 45355 | C31: Pre-withdrawal | D31: Canada | E31: Global North | F31: North America | G31: Ministry of Environment | H31: Press release | I31: canada.ca | J31: List of 56 Habitat Stewardship Program for Species at Risk projects 2023–2024 | K31: https://www.canada.ca/en/environment-climate-change/news/2024/03/list-of-56-habitat-stewardship-program-for-species-at-risk-projects-20232024.html | L31: Environment | M31: No | N31: 1 | P31: page metadata | Q31: live | R31: 2647 | T31: Environment
A32: 2024-03 | B32: 45359 | C32: Pre-withdrawal | D32: Canada | E32: Global North | F32: North America | G32: Ministry of Environment | H32: Press release | I32: canada.ca | J32: Governments of Canada and Ontario join together to announce funding and collaboration for conservation areas in Ontario | K32: https://www.canada.ca/en/environment-climate-change/news/2024/03/governments-of-canada-and-ontario-join-together-to-announce-funding-and-collaboration-for-conservation-areas-in-ontario.html | L32: Climate; Climate Change; Environment; Steven Guilbeault | M32: Yes | N32: 4 | O32: Canada | P32: page metadata | Q32: live | R32: 220 | S32: Steven Guilbeault | T32: Climate; Climate Change; Environment
A33: 2024-03 | B33: 45359 | C33: Pre-withdrawal | D33: Canada | E33: Global North | F33: North America | G33: Ministry of Environment | H33: Press release | I33: canada.ca | J33: UPDATE: Minister Guilbeault to travel to New Brunswick to make a funding announcement for a clean electricity project through the Future Electricity Fund | K33: https://www.canada.ca/en/environment-climate-change/news/2024/03/minister-guilbeault-to-travel-to-new-brunswick-to-participate-in-a-ribbon-cutting-ceremony-and-make-a-funding-announcement-for-a-clean-electricity-.html | L33: Climate; Climate Change; Environment; Steven Guilbeault; energy | M33: Yes | N33: 5 | O33: Canada | P33: page metadata | Q33: live | R33: 234 | S33: Steven Guilbeault | T33: Climate; Climate Change; Environment; energy
A34: 2024-03 | B34: 45362 | C34: Pre-withdrawal | D34: Canada | E34: Global North | F34: North America | G34: Ministry of Environment | H34: Press release | I34: canada.ca | J34: Canada and Ontario commit to significant collaboration on shared nature conservation goals | K34: https://www.canada.ca/en/environment-climate-change/news/2024/03/canada-and-ontario-commit-to-significant-collaboration-on-shared-nature-conservation-goals.html | L34: Climate; Climate Change; Environment; Steven Guilbeault; carbon; commitments | M34: Yes | N34: 6 | O34: Canada | P34: page metadata | Q34: live | R34: 1196 | S34: Steven Guilbeault | T34: Climate; Climate Change; Environment; carbon; commitments
A35: 2024-03 | B35: 45362 | C35: Pre-withdrawal | D35: Canada | E35: Global North | F35: North America | G35: Ministry of Environment | H35: Press release | I35: canada.ca | J35: Cutting the ribbon on the largest battery energy storage system in New Brunswick | K35: https://www.canada.ca/en/environment-climate-change/news/2024/03/cutting-the-ribbon-on-the-largest-battery-energy-storage-system-in-new-brunswick.html | L35: Climate; Climate Change; Environment; Steven Guilbeault; emissions; energy; fossil fuel; green; greenhouse gas; renewable energy; transition | M35: Yes | N35: 11 | O35: Canada | P35: page metadata | Q35: live | R35: 942 | S35: Steven Guilbeault | T35: Climate; Climate Change; Environment; emissions; energy; fossil fuel; green; greenhouse gas; renewable energy; transition
A36: 2024-03 | B36: 45362 | C36: Pre-withdrawal | D36: Canada | E36: Global North | F36: North America | G36: Ministry of Environment | H36: Press release | I36: canada.ca | J36: Helping New Brunswickers reduce energy costs, cut pollution | K36: https://www.canada.ca/en/environment-climate-change/news/2024/03/helping-new-brunswickers-reduce-energy-costs-cut-pollution.html | L36: Climate; Climate Change; Environment; Steven Guilbeault; Sustainability; carbon; climate goals; emissions; energy; greenhouse gas; net zero emissions; sustainable energy; transition | M36: Yes | N36: 13 | O36: Canada | P36: page metadata | Q36: live | R36: 1058 | S36: Steven Guilbeault | T36: Climate; Climate Change; Environment; Sustainability; carbon; climate goals; emissions; energy; greenhouse gas; net zero emissions; sustainable energy; transition
A37: 2024-03 | B37: 45362 | C37: Pre-withdrawal | D37: Canada | E37: Global North | F37: North America | G37: Ministry of Environment | H37: Press release | I37: canada.ca | J37: Minister Guilbeault to travel to Nova Scotia to make an announcement regarding a clean energy investment and hold media availabilities | K37: https://www.canada.ca/en/environment-climate-change/news/2024/03/minister-guilbeault-to-travel-to-nova-scotia-to-make-an-announcement-regarding-a-clean-energy-investment-and-hold-media-availabilities.html | L37: Climate; Climate Change; Environment; Steven Guilbeault; energy | M37: Yes | N37: 5 | O37: Canada | P37: page metadata | Q37: live | R37: 213 | S37: Steven Guilbeault | T37: Climate; Climate Change; Environment; energy
A38: 2024-03 | B38: 45363 | C38: Pre-withdrawal | D38: Canada | E38: Global North | F38: North America | G38: Ministry of Environment | H38: Press release | I38: canada.ca | J38: Government of Canada supports Indigenous climate action with new funding stream under the Indigenous Leadership Fund | K38: https://www.canada.ca/en/environment-climate-change/news/2024/03/government-of-canada-supports-indigenous-climate-action-with-new-funding-stream-under-the-indigenous-leadership-fund.html | L38: Climate; Climate Change; Environment; Steven Guilbeault; carbon; emissions; energy; green; greenhouse gas; net zero emissions; renewable energy | M38: Yes | N38: 11 | O38: Canada | P38: page metadata | Q38: live | R38: 662 | S38: Steven Guilbeault | T38: Climate; Climate Change; Environment; carbon; emissions; energy; green; greenhouse gas; net zero emissions; renewable energy
A39: 2024-03 | B39: 45364 | C39: Pre-withdrawal | D39: Canada | E39: Global North | F39: North America | G39: Ministry of Environment | H39: Press release | I39: canada.ca | J39: Government of Canada to deliver final step of major radar modernization project, followed by a site tour | K39: https://www.canada.ca/en/environment-climate-change/news/2024/03/government-of-canada-to-deliver-final-step-of-major-radar-modernization-project-followed-by-a-site-tour.html | L39: Climate; Climate Change; Environment; Steven Guilbeault | M39: Yes | N39: 4 | O39: Canada | P39: page metadata | Q39: live | R39: 263 | S39: Steven Guilbeault | T39: Climate; Climate Change; Environment
A40: 2024-03 | B40: 45365 | C40: Pre-withdrawal | D40: Canada | E40: Global North | F40: North America | G40: Ministry of Environment | H40: Press release | I40: canada.ca | J40: Call for applications for the next Environment and Climate Change Youth Council: A chance to help shape our environmental future | K40: https://www.canada.ca/en/environment-climate-change/news/2024/03/call-for-applications-for-the-next-environment-and-climate-change-youth-council-a-chance-to-help-shape-our-environmental-future.html | L40: Climate; Climate Change; Environment; Steven Guilbeault | M40: Yes | N40: 4 | O40: Canada | P40: page metadata | Q40: live | R40: 697 | S40: Steven Guilbeault | T40: Climate; Climate Change; Environment
A41: 2024-03 | B41: 45365 | C41: Pre-withdrawal | D41: Canada | E41: Global North | F41: North America | G41: Ministry of Environment | H41: Policy / regulatory | I41: canada.ca | J41: Minister Guilbeault meets with historically impacted Black community in advance of environmental justice and racism bill | K41: https://www.canada.ca/en/environment-climate-change/news/2024/03/minister-guilbeault-meets-with-historically-impacted-black-community-in-advance-of-environmental-justice-and-racism-bill.html | L41: Climate; Climate Change; Environment; Steven Guilbeault | M41: Yes | N41: 4 | O41: Canada | P41: page metadata | Q41: live | R41: 938 | S41: Steven Guilbeault | T41: Climate; Climate Change; Environment
A42: 2024-03 | B42: 45366 | C42: Pre-withdrawal | D42: Canada | E42: Global North | F42: North America | G42: Ministry of Environment | H42: Press release | I42: canada.ca | J42: Canada’s modernized radar network | K42: https://www.canada.ca/en/environment-climate-change/news/2024/03/canadas-modernized-radar-network.html | L42: Climate; Climate Change; Environment | M42: No | N42: 3 | P42: page metadata | Q42: live | R42: 708 | T42: Climate; Climate Change; Environment
A43: 2024-03 | B43: 45366 | C43: Pre-withdrawal | D43: Canada | E43: Global North | F43: North America | G43: Ministry of Environment | H43: Press release | I43: canada.ca | J43: Keeping Canadians safe and tracking severe weather: Government of Canada completes 33 state-of-the-art radar modernization projects across Canada | K43: https://www.canada.ca/en/environment-climate-change/news/2024/03/keeping-canadians-safe-and-tracking-severe-weather-government-of-canada-completes-33-state-of-the-art-radar-modernization-projects-across-canada.html | L43: Climate; Climate Change; Environment; Steven Guilbeault | M43: Yes | N43: 4 | O43: Canada | P43: page metadata | Q43: live | R43: 1116 | S43: Steven Guilbeault | T43: Climate; Climate Change; Environment
A44: 2024-03 | B44: 45370 | C44: Pre-withdrawal | D44: Canada | E44: Global North | F44: North America | G44: Ministry of Environment | H44: Policy / regulatory | I44: canada.ca | J44: Groupe Marcelle inc. was fined $500,000 for violating the Canadian Environmental Protection Act, 1999 | K44: https://www.canada.ca/en/environment-climate-change/news/2024/03/groupe-marcelle-inc-was-fined-500000-for-violating-the-canadian-environmental-protection-act-1999.html | L44: Climate; Climate Change; Environment | M44: No | N44: 3 | P44: page metadata | Q44: live | R44: 605 | T44: Climate; Climate Change; Environment
A45: 2024-03 | B45: 45370 | C45: Pre-withdrawal | D45: Canada | E45: Global North | F45: North America | G45: Ministry of Environment | H45: Press release | I45: canada.ca | J45: Keep the cash, care for climate: Canada Carbon Rebates being paid next month | K45: https://www.canada.ca/en/environment-climate-change/news/2024/03/keep-the-cash-care-for-climate-canada-carbon-rebates-being-paid-next-month.html | L45: Climate; Climate Change; Environment; Steven Guilbeault; carbon; emissions; energy; net zero emissions | M45: Yes | N45: 8 | O45: Canada | P45: page metadata | Q45: live | R45: 1155 | S45: Steven Guilbeault | T45: Climate; Climate Change; Environment; carbon; emissions; energy; net zero emissions
A46: 2024-03 | B46: 45372 | C46: Pre-withdrawal | D46: Canada | E46: Global North | F46: North America | G46: Ministry of Environment | H46: Press release | I46: canada.ca | J46: Minister Guilbeault to make an announcement to support the conservation and improvement of the St. Lawrence ecosystem | K46: https://www.canada.ca/en/environment-climate-change/news/2024/03/minister-guilbeault-to-make-an-announcement-to-support-the-conservation-and-improvement-of-the-st-lawrence-ecosystem.html | L46: Climate; Climate Change; Environment; Steven Guilbeault | M46: Yes | N46: 4 | O46: Canada | P46: page metadata | Q46: live | R46: 200 | S46: Steven Guilbeault | T46: Climate; Climate Change; Environment
A47: 2024-03 | B47: 45373 | C47: Pre-withdrawal | D47: Canada | E47: Global North | F47: North America | G47: Ministry of Environment | H47: Press release | I47: canada.ca | J47: On World Water Day, the Government of Canada announces funding for new community projects to protect fresh water | K47: https://www.canada.ca/en/environment-climate-change/news/2024/03/on-world-water-day-the-government-of-canada-announces-funding-for-new-community-projects-to-protect-fresh-water.html | L47: Climate; Climate Change; Environment; Steven Guilbeault; Sustainability | M47: Yes | N47: 5 | O47: Canada | P47: page metadata | Q47: live | R47: 969 | S47: Steven Guilbeault | T47: Climate; Climate Change; Environment; Sustainability
A48: 2024-03 | B48: 45373 | C48: Pre-withdrawal | D48: Canada | E48: Global North | F48: North America | G48: Ministry of Environment | H48: Press release | I48: canada.ca | J48: Regional parks in British Columbia’s Central Okanagan join Canada’s national conservation network, conserving nature and combatting climate change | K48: https://www.canada.ca/en/environment-climate-change/news/2024/03/regional-parks-in-british-columbias-central-okanagan-join-canadas-national-conservation-network-conserving-nature-and-combatting-climate-change.html | L48: Climate; Climate Change; Environment; Steven Guilbeault; carbon | M48: Yes | N48: 5 | O48: Canada | P48: page metadata | Q48: live | R48: 827 | S48: Steven Guilbeault | T48: Climate; Climate Change; Environment; carbon
A49: 2024-03 | B49: 45377 | C49: Pre-withdrawal | D49: Canada | E49: Global North | F49: North America | G49: Ministry of Environment | H49: Press release | I49: canada.ca | J49: Ministers Guilbeault and Rodriguez to make an announcement on housing and affordability | K49: https://www.canada.ca/en/environment-climate-change/news/2024/03/ministers-guilbeault-and-rodriguez-to-make-an-announcement-on-housing-and-affordability.html | L49: Climate; Climate Change; Environment; Steven Guilbeault | M49: Yes | N49: 4 | O49: Canada | P49: page metadata | Q49: live | R49: 145 | S49: Steven Guilbeault | T49: Climate; Climate Change; Environment
A50: 2024-04 | B50: 45392 | C50: Pre-withdrawal | D50: Canada | E50: Global North | F50: North America | G50: Ministry of Environment | H50: Press release | I50: canada.ca | J50: New Canada Carbon Rebate estimator tells you how much you may get back in payments starting April 15 | K50: https://www.canada.ca/en/environment-climate-change/news/2024/04/new-canada-carbon-rebate-estimator-tells-you-how-much-you-may-get-back-in-payments-starting-april-15.html | L50: Climate; Climate Change; Environment; Steven Guilbeault; carbon; climate goals; emissions; energy; greenhouse gas | M50: Yes | N50: 9 | O50: Canada | P50: page metadata | Q50: live | R50: 875 | S50: Steven Guilbeault | T50: Climate; Climate Change; Environment; carbon; climate goals; emissions; energy; greenhouse gas
A51: 2024-04 | B51: 45399 | C51: Pre-withdrawal | D51: Canada | E51: Global North | F51: North America | G51: Ministry of Environment | H51: Press release | I51: canada.ca | J51: Government of Canada to hold a technical briefing on Canada’s priorities and objectives for the fourth session of the Intergovernmental Negotiating Committee on Plastic Pollution (INC-4) | K51: https://www.canada.ca/en/environment-climate-change/news/2024/04/government-of-canada-to-hold-a-technical-briefing-on-canadas-priorities-and-objectives-for-the-fourth-session-of-the-intergovernmental-negotiating-.html | L51: Climate; Climate Change; Environment | M51: No | N51: 3 | P51: page metadata | Q51: live | R51: 203 | T51: Climate; Climate Change; Environment
A52: 2024-04 | B52: 45400 | C52: Pre-withdrawal | D52: Canada | E52: Global North | F52: North America | G52: Ministry of Environment | H52: Press release | I52: canada.ca | J52: Canada brings the world together in pursuit of an ambitious global deal to end plastic pollution | K52: https://www.canada.ca/en/environment-climate-change/news/2024/04/canada-brings-the-world-together-in-pursuit-of-an-ambitious-global-deal-to-end-plastic-pollution.html | L52: Circular; Circular Economy; Climate; Climate Change; Environment; Steven Guilbeault; United Nations Environment Programme | M52: Yes | N52: 7 | O52: Canada | P52: page metadata | Q52: live | R52: 1097 | S52: Steven Guilbeault | T52: Circular; Circular Economy; Climate; Climate Change; Environment | U52: United Nations Environment Programme
A53: 2024-04 | B53: 45400 | C53: Pre-withdrawal | D53: Canada | E53: Global North | F53: North America | G53: Ministry of Environment | H53: Press release | I53: canada.ca | J53: UPDATE - Itinerary: Minister Guilbeault to attend the fourth session of the Intergovernmental Negotiating Committee (INC-4) | K53: https://www.canada.ca/en/environment-climate-change/news/2024/04/itinerary-minister-guilbeault-to-attend-the-fourth-session-of-the-intergovernmental-negotiating-committee-inc-4.html | L53: Climate; Climate Change; Environment; Steven Guilbeault; United Nations Environment Programme | M53: Yes | N53: 5 | O53: Canada | P53: page metadata | Q53: live | R53: 404 | S53: Steven Guilbeault | T53: Climate; Climate Change; Environment | U53: United Nations Environment Programme
A54: 2024-04 | B54: 45404 | C54: Pre-withdrawal | D54: Canada | E54: Global North | F54: North America | G54: Ministry of Environment | H54: Press release | I54: canada.ca | J54: Alberta resident sentenced to $35,000 fine and prohibition order for illegally importing and possessing protected turtles and turtle eggs | K54: https://www.canada.ca/en/environment-climate-change/news/2024/04/alberta-resident-sentenced-to-35000-fine-and-prohibition-order-for-illegally-importing-and-possessing-protected-turtles-and-turtle-eggs.html | L54: Climate; Climate Change; Environment | M54: No | N54: 3 | P54: page metadata | Q54: live | R54: 577 | T54: Climate; Climate Change; Environment
A55: 2024-04 | B55: 45404 | C55: Pre-withdrawal | D55: Canada | E55: Global North | F55: North America | G55: Ministry of Environment | H55: Press release | I55: canada.ca | J55: Minister Guilbeault to make an announcement to help promote a circular economy and reduce plastic pollution in Canada | K55: https://www.canada.ca/en/environment-climate-change/news/2024/04/minister-guilbeault-to-make-an-announcement-to-help-promote-a-circular-economy-and-reduce-plastic-pollution-in-canada.html | L55: Circular; Circular Economy; Climate; Climate Change; Environment; Julie Dabrusin; Steven Guilbeault | M55: Yes | N55: 7 | O55: Canada | P55: page metadata | Q55: live | R55: 200 | S55: Julie Dabrusin; Steven Guilbeault | T55: Circular; Circular Economy; Climate; Climate Change; Environment
A56: 2024-04 | B56: 45404 | C56: Pre-withdrawal | D56: Canada | E56: Global North | F56: North America | G56: Ministry of Environment | H56: Press release | I56: canada.ca | J56: The Government of Canada requires producers to take more responsibility for the plastic they put on the market | K56: https://www.canada.ca/en/environment-climate-change/news/2024/04/the-government-of-canada-requires-producers-to-take-more-responsibility-for-the-plastic-they-put-on-the-market.html | L56: Circular; Circular Economy; Environment | M56: No | N56: 3 | P56: page metadata | Q56: live | R56: 1189 | T56: Circular; Circular Economy; Environment
A57: 2024-04 | B57: 45404 | C57: Pre-withdrawal | D57: Canada | E57: Global North | F57: North America | G57: Ministry of Environment | H57: Press release | I57: canada.ca | J57: The Government of Canada requires producers to take more responsibility for the plastic they put on the market | K57: https://www.canada.ca/en/environment-climate-change/news/2024/04/the-government-of-canada-requires-producers-to-take-more-responsibility-for-the-plastic-they-put-on-the-market0.html | L57: Circular; Circular Economy; Climate; Climate Change; Environment; Steven Guilbeault; Transparency; green | M57: Yes | N57: 8 | O57: Canada | P57: page metadata | Q57: live | R57: 777 | S57: Steven Guilbeault | T57: Circular; Circular Economy; Climate; Climate Change; Environment; Transparency; green
A58: 2024-04 | B58: 45405 | C58: Pre-withdrawal | D58: Canada | E58: Global North | F58: North America | G58: Ministry of Environment | H58: Press release | I58: canada.ca | J58: Canadian Plastics Innovation Challenges— Environment and Climate Change Canada Phase 1 recipients | K58: https://www.canada.ca/en/environment-climate-change/news/2024/04/canadian-plastics-innovation-challenges-environment-and-climate-change-canada-phase-1-recipients.html | L58: Circular; Circular Economy; Climate; Climate Change; Environment; energy | M58: Yes | N58: 6 | P58: page metadata | Q58: live | R58: 712 | T58: Circular; Circular Economy; Climate; Climate Change; Environment; energy
A59: 2024-04 | B59: 45405 | C59: Pre-withdrawal | D59: Canada | E59: Global North | F59: North America | G59: Ministry of Environment | H59: Press release | I59: canada.ca | J59: Government of Canada invests to support Canadian innovators to find ways to reduce plastic pollution | K59: https://www.canada.ca/en/environment-climate-change/news/2024/04/government-of-canada-invests-to-support-canadian-innovators-to-find-ways-to-reduce-plastic-pollution.html | L59: Circular; Circular Economy; Climate; Climate Change; Environment; Julie Dabrusin; Steven Guilbeault; Sustainable Economy; energy | M59: Yes | N59: 9 | O59: Canada | P59: page metadata | Q59: live | R59: 904 | S59: Julie Dabrusin; Steven Guilbeault | T59: Circular; Circular Economy; Climate; Climate Change; Environment; Sustainable Economy; energy
A60: 2024-04 | B60: 45405 | C60: Pre-withdrawal | D60: Canada | E60: Global North | F60: North America | G60: Ministry of Environment | H60: Joint / ministerial statement | I60: canada.ca | J60: Minister Guilbeault issues statement on high-level meeting as INC-4 begins | K60: https://www.canada.ca/en/environment-climate-change/news/2024/04/minister-guilbeault-issues-statement-on-high-level-meeting-as-inc-4-begins.html | L60: Climate; Climate Change; Environment; Steven Guilbeault | M60: Yes | N60: 4 | O60: Canada | P60: page metadata | Q60: live | R60: 463 | S60: Steven Guilbeault | T60: Climate; Climate Change; Environment
A61: 2024-04 | B61: 45405 | C61: Pre-withdrawal | D61: Canada | E61: Global North | F61: North America | G61: Ministry of Environment | H61: Press release | I61: canada.ca | J61: Ministers Guilbeault, Champagne and Bibeau to make an announcement on housing and affordability | K61: https://www.canada.ca/en/environment-climate-change/news/2024/04/ministers-guilbeault-champagne-and-bibeau-to-make-an-announcement-on-housing-and-affordability.html | L61: Climate; Climate Change; Environment; Steven Guilbeault | M61: Yes | N61: 4 | O61: Canada | P61: page metadata | Q61: live | R61: 208 | S61: Steven Guilbeault | T61: Climate; Climate Change; Environment
A62: 2024-04 | B62: 45405 | C62: Pre-withdrawal | D62: Canada | E62: Global North | F62: North America | G62: Ministry of Environment | H62: Press release | I62: canada.ca | J62: Recipients of the grants and contributions funding for advancing a circular economy for plastics in Canada | K62: https://www.canada.ca/en/environment-climate-change/news/2024/04/recipients-of-the-grants-and-contributions-funding-for-advancing-a-circular-economy-for-plastics-in-canada.html | L62: Circular; Circular Economy; Climate; Climate Change; Environment; carbon; emissions; energy | M62: Yes | N62: 8 | P62: page metadata | Q62: live | R62: 905 | T62: Circular; Circular Economy; Climate; Climate Change; Environment; carbon; emissions; energy
A63: 2024-04 | B63: 45406 | C63: Pre-withdrawal | D63: Canada | E63: Global North | F63: North America | G63: Ministry of Environment | H63: Press release | I63: canada.ca | J63: Ministers Champagne, Bibeau, and Guilbeault highlight budget investments to support housing creation | K63: https://www.canada.ca/en/environment-climate-change/news/2024/04/ministers-champagne-bibeau-and-guilbeault-highlight-budget-investments-to-support-housing-creation.html | L63: Climate; Climate Change; Environment; Steven Guilbeault | M63: Yes | N63: 4 | O63: Canada | P63: page metadata | Q63: live | R63: 1220 | S63: Steven Guilbeault | T63: Climate; Climate Change; Environment
A64: 2024-04 | B64: 45408 | C64: Pre-withdrawal | D64: Canada | E64: Global North | F64: North America | G64: Ministry of Environment | H64: Policy / regulatory | I64: canada.ca | J64: Husky Oil Operations Limited fined $2.5 million for three offences under federal legislation related to crude oil release in Newfoundland and Labrador offshore | K64: https://www.canada.ca/en/environment-climate-change/news/2024/04/husky-oil-operations-limited-fined-25-million-for-three-offences-under-federal-legislation-related-to-crude-oil-release-in-newfoundland-and-labrado.html | L64: Climate; Climate Change; Environment | M64: No | N64: 3 | P64: page metadata | Q64: live | R64: 748 | T64: Climate; Climate Change; Environment
A65: 2024-04 | B65: 45411 | C65: Pre-withdrawal | D65: Canada | E65: Global North | F65: North America | G65: Ministry of Environment | H65: Press release | I65: canada.ca | J65: Minister Guilbeault to hold a media availability from the G7 Ministers’ Meeting on Climate, Energy and Environment in Turin, Italy | K65: https://www.canada.ca/en/environment-climate-change/news/2024/04/minister-guilbeault-to-hold-a-media-availability-from-the-g7-ministers-meeting-on-climate-energy-and-environment-in-turin-italy.html | L65: Climate; Climate Change; Environment; Steven Guilbeault; energy | M65: Yes | N65: 5 | O65: Canada | P65: page metadata | Q65: live | R65: 184 | S65: Steven Guilbeault | T65: Climate; Climate Change; Environment; energy
A66: 2024-04 | B66: 45412 | C66: Pre-withdrawal | D66: Canada | E66: Global North | F66: North America | G66: Ministry of Environment | H66: Policy / regulatory | I66: canada.ca | J66: Canada helps chart roadmap toward an ambitious global deal to end plastic pollution | K66: https://www.canada.ca/en/environment-climate-change/news/2024/04/canada-helps-chart-roadmap-toward-an-ambitious-global-deal-to-end-plastic-pollution.html | L66: Circular; Circular Economy; Climate; Climate Change; Environment; Julie Dabrusin; Paris Agreement; Steven Guilbeault; Sustainable Economic Development; United Nations Environment Programme | M66: Yes | N66: 10 | O66: Canada | P66: page metadata | Q66: live | R66: 1024 | S66: Julie Dabrusin; Steven Guilbeault | T66: Circular; Circular Economy; Climate; Climate Change; Environment; Sustainable Economic Development | U66: Paris Agreement; United Nations Environment Programme
A67: 2024-04 | B67: 45412 | C67: Pre-withdrawal | D67: Canada | E67: Global North | F67: North America | G67: Ministry of Environment | H67: Policy / regulatory | I67: canada.ca | J67: Federal government concerned about further delays in release of Quebec government’s caribou strategy | K67: https://www.canada.ca/en/environment-climate-change/news/2024/04/federal-government-concerned-about-further-delays-in-release-of-quebec-governments-caribou-strategy.html | L67: Climate; Climate Change; Environment; Steven Guilbeault | M67: Yes | N67: 4 | O67: Canada | P67: page metadata | Q67: live | R67: 337 | S67: Steven Guilbeault | T67: Climate; Climate Change; Environment
A68: 2024-04 | B68: 45412 | C68: Pre-withdrawal | D68: Canada | E68: Global North | F68: North America | G68: Ministry of Environment | H68: Press release | I68: canada.ca | J68: Government of Canada to hold a media availability to respond to the tabling of the Commissioner of the Environment and Sustainable Development 2024 spring reports | K68: https://www.canada.ca/en/environment-climate-change/news/2024/04/government-of-canada-to-hold-a-media-availability-to-respond-to-the-tabling-of-the-commissioner-of-the-environment-and-sustainable-development-2024.html | L68: Climate; Climate Change; Environment; Julie Dabrusin; Steven Guilbeault | M68: Yes | N68: 5 | O68: Canada | P68: page metadata | Q68: live | R68: 188 | S68: Julie Dabrusin; Steven Guilbeault | T68: Climate; Climate Change; Environment
A69: 2024-04 | B69: 45412 | C69: Pre-withdrawal | D69: Canada | E69: Global North | F69: North America | G69: Ministry of Environment | H69: Press release | I69: canada.ca | J69: Government of Canada welcomes reports from the Commissioner of the Environment and Sustainable Development | K69: https://www.canada.ca/en/environment-climate-change/news/2024/04/government-of-canada-welcomes-reports-from-the-commissioner-of-the-environment-and-sustainable-development.html | L69: Circular; Climate; Climate Change; Climate change mitigation; Environment; Steven Guilbeault; Sustainability; Transparency; carbon; carbon emissions; climate goals; commitments; emissions; greenhouse gas; transition | M69: Yes | N69: 15 | O69: Canada | P69: page metadata | Q69: live | R69: 1652 | S69: Steven Guilbeault | T69: Circular; Climate; Climate Change; Climate change mitigation; Environment; Sustainability; Transparency; carbon; carbon emissions; climate goals; commitments; emissions; greenhouse gas; transition
A70: 2024-05 | B70: 45413 | C70: Pre-withdrawal | D70: Canada | E70: Global North | F70: North America | G70: Ministry of Environment | H70: Press release | I70: canada.ca | J70: Minister Guilbeault concludes G7 Ministers’ Meeting with strong outcomes on clean energy, clean air, and a nature-positive future | K70: https://www.canada.ca/en/environment-climate-change/news/2024/05/minister-guilbeault-concludes-g7-ministers-meeting-with-strong-outcomes-on-clean-energy-clean-air-and-a-nature-positive-future.html | L70: COP; Climate; Climate Change; Environment; Steven Guilbeault; Transparency; carbon; commitments; emissions; energy; fossil fuel; sustainable energy; transition | M70: Yes | N70: 13 | O70: Canada | P70: page metadata | Q70: live | R70: 1605 | S70: Steven Guilbeault | T70: Climate; Climate Change; Environment; Transparency; carbon; commitments; emissions; energy; fossil fuel; sustainable energy; transition | U70: COP
A71: 2024-05 | B71: 45413 | C71: Pre-withdrawal | D71: Canada | E71: Global North | F71: North America | G71: Ministry of Environment | H71: Press release | I71: canada.ca | J71: Minister Guilbeault to make an announcement on Canada’s progress to lower greenhouse gas emissions and grow the economy | K71: https://www.canada.ca/en/environment-climate-change/news/2024/05/minister-guilbeault-to-make-an-announcement-on-canadas-progress-to-lower-greenhouse-gas-emissions-and-grow-the-economy.html | L71: Climate; Climate Change; Environment; Steven Guilbeault; emissions; greenhouse gas | M71: Yes | N71: 6 | O71: Canada | P71: page metadata | Q71: live | R71: 200 | S71: Steven Guilbeault | T71: Climate; Climate Change; Environment; emissions; greenhouse gas
A72: 2024-05 | B72: 45414 | C72: Pre-withdrawal | D72: Canada | E72: Global North | F72: North America | G72: Ministry of Environment | H72: Press release | I72: canada.ca | J72: Canada’s 2024 National Inventory Report shows Canada is successfully reducing emissions | K72: https://www.canada.ca/en/environment-climate-change/news/2024/05/canadas-2024-national-inventory-report-shows-canada-is-successfully-reducing-emissions.html | L72: Climate; Climate Change; Environment; Paris Agreement; Steven Guilbeault; carbon; emissions; energy; greenhouse gas | M72: Yes | N72: 9 | O72: Canada | P72: page metadata | Q72: live | R72: 954 | S72: Steven Guilbeault | T72: Climate; Climate Change; Environment; carbon; emissions; energy; greenhouse gas | U72: Paris Agreement
A73: 2024-05 | B73: 45414 | C73: Pre-withdrawal | D73: Canada | E73: Global North | F73: North America | G73: Ministry of Environment | H73: Press release | I73: canada.ca | J73: Where Canada’s greenhouse gas emissions come from: 2024 National Greenhouse Gas Inventory | K73: https://www.canada.ca/en/environment-climate-change/news/2024/05/where-canadas-greenhouse-gas-emissions-come-from-2024-national-greenhouse-gas-inventory.html | L73: Climate; Climate Change; Environment; Paris Agreement; carbon; emissions; energy; green; greenhouse gas; net zero emissions; transition | M73: Yes | N73: 11 | P73: page metadata | Q73: live | R73: 3411 | T73: Climate; Climate Change; Environment; carbon; emissions; energy; green; greenhouse gas; net zero emissions; transition | U73: Paris Agreement
A74: 2024-05 | B74: 45418 | C74: Pre-withdrawal | D74: Canada | E74: Global North | F74: North America | G74: Ministry of Environment | H74: Press release | I74: canada.ca | J74: Canada cultivates climate solutions with financial incentive for sustainable forest management | K74: https://www.canada.ca/en/environment-climate-change/news/2024/05/canada-cultivates-climate-solutions-with-financial-incentive-for-sustainable-forest-management.html | L74: Climate; Climate Change; Environment; Steven Guilbeault; carbon; emissions; energy; greenhouse gas | M74: Yes | N74: 8 | O74: Canada | P74: page metadata | Q74: live | R74: 1200 | S74: Steven Guilbeault | T74: Climate; Climate Change; Environment; carbon; emissions; energy; greenhouse gas
A75: 2024-05 | B75: 45420 | C75: Pre-withdrawal | D75: Canada | E75: Global North | F75: North America | G75: Ministry of Environment | H75: Press release | I75: canada.ca | J75: Environment and Climate Change Canada hosts Blainville radar media tour and media availability with Minister Guilbeault | K75: https://www.canada.ca/en/environment-climate-change/news/2024/05/environment-and-climate-change-canada-hosts-blainville-radar-media-tour-and-media-availability-with-minister-guilbeault.html | L75: Climate; Climate Change; Environment; Steven Guilbeault | M75: Yes | N75: 4 | O75: Canada | P75: page metadata | Q75: live | R75: 321 | S75: Steven Guilbeault | T75: Climate; Climate Change; Environment
A76: 2024-05 | B76: 45420 | C76: Pre-withdrawal | D76: Canada | E76: Global North | F76: North America | G76: Ministry of Environment | H76: Press release | I76: canada.ca | J76: Government of Canada to make an announcement on investments to help lower greenhouse gas emissions in Ontario | K76: https://www.canada.ca/en/environment-climate-change/news/2024/05/government-of-canada-to-make-an-announcement-on-investments-to-help-lower-greenhouse-gas-emissions-in-ontario.html | L76: Climate; Climate Change; Environment; Steven Guilbeault; emissions; greenhouse gas | M76: Yes | N76: 6 | O76: Canada | P76: page metadata | Q76: live | R76: 200 | S76: Steven Guilbeault | T76: Climate; Climate Change; Environment; emissions; greenhouse gas
A77: 2024-05 | B77: 45421 | C77: Pre-withdrawal | D77: Canada | E77: Global North | F77: North America | G77: Ministry of Environment | H77: Press release | I77: canada.ca | J77: Major upgrades to Children’s Hospital of Eastern Ontario for cleaner, healthier air and energy savings | K77: https://www.canada.ca/en/environment-climate-change/news/2024/05/major-upgrades-to-childrens-hospital-of-eastern-ontario-for-cleaner-healthier-air-and-energy-savings.html | L77: Climate; Climate Change; Environment; Steven Guilbeault; carbon; carbon emissions; emissions; energy; greenhouse gas; net zero emissions | M77: Yes | N77: 10 | O77: Canada | P77: page metadata | Q77: live | R77: 794 | S77: Steven Guilbeault | T77: Climate; Climate Change; Environment; carbon; carbon emissions; emissions; energy; greenhouse gas; net zero emissions
A78: 2024-05 | B78: 45422 | C78: Pre-withdrawal | D78: Canada | E78: Global North | F78: North America | G78: Ministry of Environment | H78: Press release | I78: canada.ca | J78: Canada cuts carbon pollution with funding for Glencore Canada Corporation project | K78: https://www.canada.ca/en/environment-climate-change/news/2024/05/canada-cuts-carbon-pollution-with-funding-for-glencore-canada-corporation-project.html | L78: Climate; Climate Change; Environment; Steven Guilbeault; carbon; carbon emissions; emissions; energy; green; greenhouse gas; renewable energy; transition | M78: Yes | N78: 12 | O78: Canada | P78: page metadata | Q78: live | R78: 1035 | S78: Steven Guilbeault | T78: Climate; Climate Change; Environment; carbon; carbon emissions; emissions; energy; green; greenhouse gas; renewable energy; transition
A79: 2024-05 | B79: 45422 | C79: Pre-withdrawal | D79: Canada | E79: Global North | F79: North America | G79: Ministry of Environment | H79: Press release | I79: canada.ca | J79: Ensuring the safety of Canadians and monitoring severe weather: new state-of-the-art weather radar in Quebec | K79: https://www.canada.ca/en/environment-climate-change/news/2024/05/ensuring-the-safety-of-canadians-and-monitoring-severe-weather-new-state-of-the-art-weather-radar-in-quebec.html | L79: Climate; Climate Change; Environment; Steven Guilbeault | M79: Yes | N79: 4 | O79: Canada | P79: page metadata | Q79: live | R79: 744 | S79: Steven Guilbeault | T79: Climate; Climate Change; Environment
A80: 2024-05 | B80: 45422 | C80: Pre-withdrawal | D80: Canada | E80: Global North | F80: North America | G80: Ministry of Environment | H80: Press release | I80: canada.ca | J80: Government of Canada releases report on national efforts toward Boreal Caribou recovery | K80: https://www.canada.ca/en/environment-climate-change/news/2024/05/government-of-canada-releases-report-on-national-efforts-toward-boreal-caribou-recovery.html | L80: Climate; Climate Change; Environment; Steven Guilbeault | M80: Yes | N80: 4 | O80: Canada | P80: page metadata | Q80: live | R80: 738 | S80: Steven Guilbeault | T80: Climate; Climate Change; Environment
A81: 2024-05 | B81: 45422 | C81: Pre-withdrawal | D81: Canada | E81: Global North | F81: North America | G81: Ministry of Environment | H81: Press release | I81: canada.ca | J81: Governments of Canada and British Columbia to make a key announcement to lower home heating and cooling bills across the province | K81: https://www.canada.ca/en/environment-climate-change/news/2024/05/governments-of-canada-and-british-columbia-to-make-a-key-announcement-to-lower-home-heating-and-cooling-bills-across-the-province.html | L81: Climate; Climate Change; Environment; Steven Guilbeault; carbon; energy | M81: Yes | N81: 6 | O81: Canada | P81: page metadata | Q81: live | R81: 243 | S81: Steven Guilbeault | T81: Climate; Climate Change; Environment; carbon; energy
A82: 2024-05 | B82: 45422 | C82: Pre-withdrawal | D82: Canada | E82: Global North | F82: North America | G82: Ministry of Environment | H82: Joint / ministerial statement | I82: canada.ca | J82: Minister Guilbeault’s statement on World Migratory Bird Day | K82: https://www.canada.ca/en/environment-climate-change/news/2024/05/minister-guilbeaults-statement-on-world-migratory-bird-day.html | L82: Climate; Climate Change; Environment; Steven Guilbeault | M82: Yes | N82: 4 | O82: Canada | P82: page metadata | Q82: live | R82: 474 | S82: Steven Guilbeault | T82: Climate; Climate Change; Environment
A83: 2024-05 | B83: 45425 | C83: Pre-withdrawal | D83: Canada | E83: Global North | F83: North America | G83: Ministry of Environment | H83: Press release | I83: canada.ca | J83: Expanded heat pump program helps British Columbians save on home energy costs | K83: https://www.canada.ca/en/environment-climate-change/news/2024/05/expanded-heat-pump-program-helps-british-columbians-save-on-home-energy-costs.html | L83: Climate; Climate Change; Environment; Steven Guilbeault; carbon; carbon emissions; emissions; energy; fossil fuel; green; greenhouse gas; net zero emissions; transition | M83: Yes | N83: 13 | O83: Canada | P83: page metadata | Q83: live | R83: 1393 | S83: Steven Guilbeault | T83: Climate; Climate Change; Environment; carbon; carbon emissions; emissions; energy; fossil fuel; green; greenhouse gas; net zero emissions; transition
A84: 2024-05 | B84: 45428 | C84: Pre-withdrawal | D84: Canada | E84: Global North | F84: North America | G84: Ministry of Environment | H84: Press release | I84: canada.ca | J84: Federal and Ontario governments agree to significant collaboration on caribou conservation | K84: https://www.canada.ca/en/environment-climate-change/news/2024/05/federal-and-ontario-governments-agree-to-significant-collaboration-on-caribou-conservation.html | L84: Climate; Climate Change; Environment; Steven Guilbeault | M84: Yes | N84: 4 | O84: Canada | P84: page metadata | Q84: live | R84: 1025 | S84: Steven Guilbeault | T84: Climate; Climate Change; Environment
A85: 2024-05 | B85: 45429 | C85: Pre-withdrawal | D85: Canada | E85: Global North | F85: North America | G85: Ministry of Environment | H85: Press release | I85: canada.ca | J85: Minister Guilbeault imposes strict benzene pollution controls in the pursuit of environmental justice for Aamjiwnaang First Nation and Sarnia, Ontario | K85: https://www.canada.ca/en/environment-climate-change/news/2024/05/minister-guilbeault-imposes-strict-benzene-pollution-controls-in-the-pursuit-of-environmental-justice-for-aamjiwnaang-first-nation-and-sarnia-ontario.html | L85: Climate; Climate Change; Environment; Steven Guilbeault; commitments; emissions | M85: Yes | N85: 6 | O85: Canada | P85: page metadata | Q85: live | R85: 1275 | S85: Steven Guilbeault | T85: Climate; Climate Change; Environment; commitments; emissions
A86: 2024-05 | B86: 45433 | C86: Pre-withdrawal | D86: Canada | E86: Global North | F86: North America | G86: Ministry of Environment | H86: Press release | I86: canada.ca | J86: Environment and Climate Change Canada presents the 2024 hurricane season outlook | K86: https://www.canada.ca/en/environment-climate-change/news/2024/05/environment-and-climate-change-canada-presents-the-2024-hurricane-season-outlook.html | L86: Climate; Climate Change; Environment | M86: No | N86: 3 | P86: page metadata | Q86: live | R86: 197 | T86: Climate; Climate Change; Environment
A87: 2024-05 | B87: 45434 | C87: Pre-withdrawal | D87: Canada | E87: Global North | F87: North America | G87: Ministry of Environment | H87: Joint / ministerial statement | I87: canada.ca | J87: International Day for Biological Diversity 2024: Statement from the Honourable Steven Guilbeault, Minister of Environment and Climate Change | K87: https://www.canada.ca/en/environment-climate-change/news/2024/05/international-day-for-biological-diversity-2024-statement-from-the-honourable-steven-guilbeault-minister-of-environment-and-climate-change.html | L87: COP; Climate; Climate Change; Environment; Steven Guilbeault; Transparency; commitments | M87: Yes | N87: 7 | O87: Canada | P87: page metadata | Q87: live | R87: 501 | S87: Steven Guilbeault | T87: Climate; Climate Change; Environment; Transparency; commitments | U87: COP
A88: 2024-05 | B88: 45435 | C88: Pre-withdrawal | D88: Canada | E88: Global North | F88: North America | G88: Ministry of Environment | H88: Press release | I88: canada.ca | J88: Environment and Climate Change Canada’s Canadian Hurricane Centre expects a very active hurricane season | K88: https://www.canada.ca/en/environment-climate-change/news/2024/05/environment-and-climate-change-canadas-canadian-hurricane-centre-expects-a-very-active-hurricane-season.html | L88: Climate; Climate Change; Environment; Steven Guilbeault; Temperature; emissions | M88: Yes | N88: 6 | O88: Canada | P88: page metadata | Q88: live | R88: 1384 | S88: Steven Guilbeault | T88: Climate; Climate Change; Environment; Temperature; emissions
A89: 2024-05 | B89: 45440 | C89: Pre-withdrawal | D89: Canada | E89: Global North | F89: North America | G89: Ministry of Environment | H89: Press release | I89: canada.ca | J89: Protections for the Aamjiwnaang First Nation and Sarnia from benzene emissions officially extended for two years | K89: https://www.canada.ca/en/environment-climate-change/news/2024/05/protections-for-the-aamjiwnaang-first-nation-and-sarnia-from-benzene-emissions-officially-extended-for-two-years.html | L89: Climate; Climate Change; Environment; emissions | M89: Yes | N89: 4 | P89: page metadata | Q89: live | R89: 358 | T89: Climate; Climate Change; Environment; emissions
A90: 2024-05 | B90: 45442 | C90: Pre-withdrawal | D90: Canada | E90: Global North | F90: North America | G90: Ministry of Environment | H90: Press release | I90: canada.ca | J90: Canada releases the Climate Science 2050: National Priorities for Climate Change Science and Knowledge Report | K90: https://www.canada.ca/en/environment-climate-change/news/2024/05/canada-releases-the-climate-science-2050-national-priorities-for-climate-change-science-and-knowledge-report.html | L90: Climate; Climate Change; Climate change mitigation; Environment; Green Economy; Steven Guilbeault; carbon; carbon emissions; emissions; green; net zero emissions | M90: Yes | N90: 11 | O90: Canada | P90: page metadata | Q90: live | R90: 632 | S90: Steven Guilbeault | T90: Climate; Climate Change; Climate change mitigation; Environment; Green Economy; carbon; carbon emissions; emissions; green; net zero emissions
A91: 2024-05 | B91: 45442 | C91: Pre-withdrawal | D91: Canada | E91: Global North | F91: North America | G91: Ministry of Environment | H91: Press release | I91: canada.ca | J91: Minister Guilbeault to make an announcement on wildlife habitat protection and restoration | K91: https://www.canada.ca/en/environment-climate-change/news/2024/05/minister-guilbeault-to-make-an-announcement-on-wildlife-habitat-protection-and-restoration.html | L91: Climate; Climate Change; Environment; Steven Guilbeault | M91: Yes | N91: 4 | O91: Canada | P91: page metadata | Q91: live | R91: 195 | S91: Steven Guilbeault | T91: Climate; Climate Change; Environment
A92: 2024-05 | B92: 45442 | C92: Pre-withdrawal | D92: Canada | E92: Global North | F92: North America | G92: Ministry of Environment | H92: Press release | I92: canada.ca | J92: Ministers Guilbeault and Miller to make a major health science funding announcement in Montreal | K92: https://www.canada.ca/en/environment-climate-change/news/2024/05/ministers-guilbeault-and-miller-to-make-a-major-health-science-funding-announcement-in-montreal.html | L92: Climate; Climate Change; Environment; Steven Guilbeault | M92: Yes | N92: 4 | O92: Canada | P92: page metadata | Q92: live | R92: 232 | S92: Steven Guilbeault | T92: Climate; Climate Change; Environment
A93: 2024-05 | B93: 45443 | C93: Pre-withdrawal | D93: Canada | E93: Global North | F93: North America | G93: Ministry of Environment | H93: Press release | I93: canada.ca | J93: Government of Canada Supports Brain Canada’s Research Programs to Improve Brain Health $80 million over four years would support the advancement of brain research in Canada | K93: https://www.canada.ca/en/environment-climate-change/news/2024/05/government-of-canada-supports-brain-canadas-research-programs-to-improve-brain-health-80-million-over-four-years-would-support-the-advancement-of-b.html | L93: Climate; Climate Change; Environment; Steven Guilbeault | M93: Yes | N93: 4 | O93: Canada | P93: page metadata | Q93: live | R93: 974 | S93: Steven Guilbeault | T93: Climate; Climate Change; Environment
A94: 2024-05 | B94: 45443 | C94: Pre-withdrawal | D94: Canada | E94: Global North | F94: North America | G94: Ministry of Environment | H94: Press release | I94: canada.ca | J94: Protecting a threatened species, the Western Chorus Frog, in Quebec | K94: https://www.canada.ca/en/environment-climate-change/news/2024/05/protecting-a-threatened-species-the-western-chorus-frog-in-quebec.html | L94: Climate; Climate Change; Environment; Steven Guilbeault; carbon | M94: Yes | N94: 5 | O94: Canada | P94: page metadata | Q94: live | R94: 888 | S94: Steven Guilbeault | T94: Climate; Climate Change; Environment; carbon
A95: 2024-05 | B95: 45443 | C95: Pre-withdrawal | D95: Canada | E95: Global North | F95: North America | G95: Ministry of Environment | H95: Press release | I95: canada.ca | J95: The Government of Canada to make an announcement on significant investments to help build Canada’s climate resiliency | K95: https://www.canada.ca/en/environment-climate-change/news/2024/05/the-government-of-canada-to-make-an-announcement-on-significant-investments-to-help-build-canadas-climate-resiliency.html | L95: Climate; Climate Change; Environment; Steven Guilbeault | M95: Yes | N95: 4 | O95: Canada | P95: page metadata | Q95: live | R95: 227 | S95: Steven Guilbeault | T95: Climate; Climate Change; Environment
A96: 2024-05 | B96: 45443 | C96: Pre-withdrawal | D96: Canada | E96: Global North | F96: North America | G96: Ministry of Environment | H96: Policy / regulatory | I96: canada.ca | J96: Twin Rivers Paper Company Inc. fined $250,000 for Fisheries Act offence in New Brunswick | K96: https://www.canada.ca/en/environment-climate-change/news/2024/05/twin-rivers-paper-company-inc-fined-250000-for-fisheries-act-offence-in-new-brunswick.html | L96: Climate; Climate Change; Environment | M96: No | N96: 3 | P96: page metadata | Q96: live | R96: 481 | T96: Climate; Climate Change; Environment
A97: 2024-06 | B97: 45446 | C97: Pre-withdrawal | D97: Canada | E97: Global North | F97: North America | G97: Ministry of Environment | H97: Press release | I97: canada.ca | J97: Backgrounder: Update on Federal Climate Change Adaptation Actions | K97: https://www.canada.ca/en/environment-climate-change/news/2024/06/backgrounder-update-on-federal-climate-change-adaptation-actions.html | L97: Climate; Climate Change; Environment; Steven Guilbeault; green | M97: Yes | N97: 5 | O97: Canada | P97: page metadata | Q97: live | R97: 581 | S97: Steven Guilbeault | T97: Climate; Climate Change; Environment; green
A98: 2024-06 | B98: 45446 | C98: Pre-withdrawal | D98: Canada | E98: Global North | F98: North America | G98: Ministry of Environment | H98: Press release | I98: canada.ca | J98: Building stronger, more climate-resilient communities | K98: https://www.canada.ca/en/environment-climate-change/news/2024/06/building-stronger-more-climate-resilient-communities-the-government-of-canada-provides-530-million-to-municipalities-through-the-green-municipal-fu.html | L98: Climate; Climate Change; Environment; Steven Guilbeault; Sustainability; commitments; green | M98: Yes | N98: 7 | O98: Canada | P98: page metadata | Q98: live | R98: 1177 | S98: Steven Guilbeault | T98: Climate; Climate Change; Environment; Sustainability; commitments; green
A99: 2024-06 | B99: 45447 | C99: Pre-withdrawal | D99: Canada | E99: Global North | F99: North America | G99: Ministry of Environment | H99: Press release | I99: canada.ca | J99: Government of Canada extends pilot to support innovative funding opportunities for biodiversity conservation | K99: https://www.canada.ca/en/environment-climate-change/news/2024/06/government-of-canada-extends-pilot-to-support-innovative-funding-opportunities-for-biodiversity-conservation.html | L99: Climate; Climate Change; Environment; Steven Guilbeault; Sustainability; commitments; energy | M99: Yes | N99: 7 | O99: Canada | P99: page metadata | Q99: live | R99: 1248 | S99: Steven Guilbeault | T99: Climate; Climate Change; Environment; Sustainability; commitments; energy
A100: 2024-06 | B100: 45448 | C100: Pre-withdrawal | D100: Canada | E100: Global North | F100: North America | G100: Ministry of Environment | H100: Press release | I100: canada.ca | J100: New public alert makes it easier to understand air quality conditions during wildfire events and year-round | K100: https://www.canada.ca/en/environment-climate-change/news/2024/06/new-public-alert-makes-it-easier-to-understand-air-quality-conditions-during-wildfire-events-and-year-round.html | L100: Climate; Climate Change; Environment; Steven Guilbeault; energy | M100: Yes | N100: 5 | O100: Canada | P100: page metadata | Q100: live | R100: 993 | S100: Steven Guilbeault | T100: Climate; Climate Change; Environment; energy
...

Sheet 2024-01
A1: Month | B1: Date | C1: Period | D1: Country | E1: North/South | F1: Continent | G1: Source Type | H1: Document Type | I1: Site | J1: Title | K1: URL | L1: Matched Keywords | M1: Strong Match | N1: Keyword Count | O1: Minister/Person Country | P1: Date Source | Q1: Fetched Via | R1: Word Count | S1: Event/Person hits | T1: Adjective Indicators hits | U1: Organizations/Alliances hits | V1: Regulatory Bodies hits
A2: 2024-01 | B2: 45293 | C2: Pre-withdrawal | D2: Canada | E2: Global North | F2: North America | G2: Ministry of Environment | H2: Press release | I2: canada.ca | J2: The Government of Canada is seeking feedback on developing a federal plastics registry to help tackle plastic pollution | K2: https://www.canada.ca/en/environment-climate-change/news/2024/01/the-government-of-canada-is-seeking-feedback-on-developing-a-federal-plastics-registry-to-help-tackle-plastic-pollution.html | L2: Circular; Circular Economy; Climate; Climate Change; Environment; Steven Guilbeault; transition | M2: Yes | N2: 7 | O2: Canada | P2: page metadata | Q2: live | R2: 733 | S2: Steven Guilbeault | T2: Circular; Circular Economy; Climate; Climate Change; Environment; transition
A3: 2024-01 | B3: 45302 | C3: Pre-withdrawal | D3: Canada | E3: Global North | F3: North America | G3: Ministry of Environment | H3: Press release | I3: canada.ca | J3: Environment and Climate Change Canada to hold a technical briefing and media availability related to a winter storm affecting Ontario and Quebec this weekend | K3: https://www.canada.ca/en/environment-climate-change/news/2024/01/environment-and-climate-change-canada-to-hold-a-technical-briefing-and-media-availability-related-to-a-winter-storm-affecting-ontario-and-quebec-th.html | L3: Climate; Climate Change; Environment | M3: No | N3: 3 | P3: page metadata | Q3: live | R3: 223 | T3: Climate; Climate Change; Environment
A4: 2024-01 | B4: 45303 | C4: Pre-withdrawal | D4: Canada | E4: Global North | F4: North America | G4: Ministry of Environment | H4: Press release | I4: canada.ca | J4: Eligible Canadian residents to receive their first pollution pricing rebate of the year | K4: https://www.canada.ca/en/environment-climate-change/news/2024/01/eligible-canadian-residents-to-receive-their-first-pollution-pricing-rebate-of-the-year.html | L4: Climate; Climate Change; Environment; Steven Guilbeault; carbon; emissions; energy; net zero emissions | M4: Yes | N4: 8 | O4: Canada | P4: page metadata | Q4: live | R4: 880 | S4: Steven Guilbeault | T4: Climate; Climate Change; Environment; carbon; emissions; energy; net zero emissions
A5: 2024-01 | B5: 45303 | C5: Pre-withdrawal | D5: Canada | E5: Global North | F5: North America | G5: Ministry of Environment | H5: Press release | I5: canada.ca | J5: Minister Guilbeault to make an announcement to support the Université de Sherbrooke’s work on environmental research | K5: https://www.canada.ca/en/environment-climate-change/news/2024/01/minister-guilbeault-to-make-an-announcement-to-support-the-universite-de-sherbrookes-work-on-environmental-research.html | L5: Climate; Climate Change; Environment; Steven Guilbeault | M5: Yes | N5: 4 | O5: Canada | P5: page metadata | Q5: live | R5: 196 | S5: Steven Guilbeault | T5: Climate; Climate Change; Environment
A6: 2024-01 | B6: 45306 | C6: Pre-withdrawal | D6: Canada | E6: Global North | F6: North America | G6: Ministry of Environment | H6: Press release | I6: canada.ca | J6: Government of Canada announces new investments in environmental research for the Université de Sherbrooke | K6: https://www.canada.ca/en/environment-climate-change/news/2024/01/government-of-canada-announces-new-investments-in-environmental-research-for-the-universite-de-sherbrooke.html | L6: Climate; Climate Change; Environment; Environmental Policy; Steven Guilbeault; carbon; emissions; greenhouse gas | M6: Yes | N6: 8 | O6: Canada | P6: page metadata | Q6: live | R6: 1074 | S6: Steven Guilbeault | T6: Climate; Climate Change; Environment; Environmental Policy; carbon; emissions; greenhouse gas
A7: 2024-01 | B7: 45310 | C7: Pre-withdrawal | D7: Canada | E7: Global North | F7: North America | G7: Ministry of Environment | H7: Press release | I7: canada.ca | J7: Government of Canada to make an announcement on funding for freshwater ecosystem initiatives | K7: https://www.canada.ca/en/environment-climate-change/news/2024/01/government-of-canada-to-make-an-announcement-on-funding-for-freshwater-ecosystem-initiatives.html | L7: Climate; Climate Change; Environment; Steven Guilbeault | M7: Yes | N7: 4 | O7: Canada | P7: page metadata | Q7: live | R7: 159 | S7: Steven Guilbeault | T7: Climate; Climate Change; Environment
A8: 2024-01 | B8: 45313 | C8: Pre-withdrawal | D8: Canada | E8: Global North | F8: North America | G8: Ministry of Environment | H8: Press release | I8: canada.ca | J8: Federal Government opens the door to projects that help keep Canadian fresh water clean and healthy | K8: https://www.canada.ca/en/environment-climate-change/news/2024/01/federal-government-opens-the-door-to-projects-that-help-keep-canadian-fresh-water-clean-and-healthy.html | L8: Climate; Climate Change; Environment; Steven Guilbeault | M8: Yes | N8: 4 | O8: Canada | P8: page metadata | Q8: live | R8: 1070 | S8: Steven Guilbeault | T8: Climate; Climate Change; Environment
A9: 2024-01 | B9: 45313 | C9: Pre-withdrawal | D9: Canada | E9: Global North | F9: North America | G9: Ministry of Environment | H9: Press release | I9: canada.ca | J9: Operation Northern Fur leads to $20,000 in fines and a prohibition order for a Manitoba resident who illegally imported, exported, and transported wildlife | K9: https://www.canada.ca/en/environment-climate-change/news/2024/01/operation-northern-fur-leads-to-20000-in-fines-and-a-prohibition-order-for-a-manitoba-resident-who-illegally-imported-exported-and-transported-wild.html | L9: Climate; Climate Change; Environment | M9: No | N9: 3 | P9: page metadata | Q9: live | R9: 619 | T9: Climate; Climate Change; Environment
A10: 2024-01 | B10: 45317 | C10: Pre-withdrawal | D10: Canada | E10: Global North | F10: North America | G10: Ministry of Environment | H10: Press release | I10: canada.ca | J10: Canada boosts conservation and restoration efforts with investments in 27 new Indigenous-Led Natural Climate Solutions | K10: https://www.canada.ca/en/environment-climate-change/news/2024/01/canada-boosts-conservation-and-restoration-efforts-with-investments-in-27-new-indigenous-led-natural-climate-solutions.html | L10: Climate; Climate Change; Environment; Steven Guilbeault; Sustainability; carbon; emissions; greenhouse gas | M10: Yes | N10: 8 | O10: Canada | P10: page metadata | Q10: live | R10: 1021 | S10: Steven Guilbeault | T10: Climate; Climate Change; Environment; Sustainability; carbon; emissions; greenhouse gas
A11: 2024-01 | B11: 45317 | C11: Pre-withdrawal | D11: Canada | E11: Global North | F11: North America | G11: Ministry of Environment | H11: Press release | I11: canada.ca | J11: List of 27 Indigenous-Led Natural Climate Solutions projects 2023–2024 | K11: https://www.canada.ca/en/environment-climate-change/news/2024/01/list-of-27-indigenous-led-natural-climate-solutions-projects-20232024.html | L11: Climate; Climate Change; Climate change mitigation; carbon; emissions; greenhouse gas | M11: Yes | N11: 6 | P11: page metadata | Q11: live | R11: 1927 | T11: Climate; Climate Change; Climate change mitigation; carbon; emissions; greenhouse gas
A12: 2024-01 | B12: 45317 | C12: Pre-withdrawal | D12: Canada | E12: Global North | F12: North America | G12: Ministry of Environment | H12: Policy / regulatory | I12: canada.ca | J12: North West Redwater Partnership paid $280,428 to the Environmental Damages Fund as part of an environmental protection alternative measures agreement under the Canadian Environmental Protection Act, 1999 | K12: https://www.canada.ca/en/environment-climate-change/news/2024/01/north-west-redwater-partnership-paid-280428-to-the-environmental-damages-fund-as-part-of-an-environmental-protection-alternative-measures-agreement.html | L12: Climate; Climate Change; Environment | M12: No | N12: 3 | P12: page metadata | Q12: live | R12: 691 | T12: Climate; Climate Change; Environment
A13: 2024-01 | B13: 45321 | C13: Pre-withdrawal | D13: Canada | E13: Global North | F13: North America | G13: Ministry of Environment | H13: Press release | I13: canada.ca | J13: Environment and Climate Change Canada Study of Winter Air Pollution in Toronto begins | K13: https://www.canada.ca/en/environment-climate-change/news/2024/01/environment-and-climate-change-canada-study-of-winter-air-pollution-in-toronto-begins.html | L13: Climate; Climate Change; Environment; carbon | M13: Yes | N13: 4 | P13: page metadata | Q13: live | R13: 570 | T13: Climate; Climate Change; Environment; carbon
A14: 2024-01 | B14: 45321 | C14: Pre-withdrawal | D14: Canada | E14: Global North | F14: North America | G14: Ministry of Environment | H14: Press release | I14: canada.ca | J14: Two Quebecers convicted of violating the Migratory Birds Regulations by destroying the nests of endangered Bank Swallows | K14: https://www.canada.ca/en/environment-climate-change/news/2024/01/two-quebecers-convicted-of-violating-the-migratory-birds-regulations-by-destroying-the-nests-of-endangered-bank-swallows.html | L14: Climate; Climate Change; Environment | M14: No | N14: 3 | P14: page metadata | Q14: live | R14: 485 | T14: Climate; Climate Change; Environment
A15: 2024-01 | B15: 45322 | C15: Pre-withdrawal | D15: Canada | E15: Global North | F15: North America | G15: Ministry of Environment | H15: Press release | I15: canada.ca | J15: Forty-two Indigenous-led conservation projects across Canada receive federal funding to protect more nature | K15: https://www.canada.ca/en/environment-climate-change/news/2024/01/forty-two-indigenous-led-conservation-projects-across-canada-receive-federal-funding-to-protect-more-nature.html | L15: Climate; Climate Change; Environment; Steven Guilbeault; Sustainability | M15: Yes | N15: 5 | O15: Canada | P15: page metadata | Q15: live | R15: 1284 | S15: Steven Guilbeault | T15: Climate; Climate Change; Environment; Sustainability

Sheet 2024-02
A1: Month | B1: Date | C1: Period | D1: Country | E1: North/South | F1: Continent | G1: Source Type | H1: Document Type | I1: Site | J1: Title | K1: URL | L1: Matched Keywords | M1: Strong Match | N1: Keyword Count | O1: Minister/Person Country | P1: Date Source | Q1: Fetched Via | R1: Word Count | S1: Event/Person hits | T1: Adjective Indicators hits | U1: Organizations/Alliances hits | V1: Regulatory Bodies hits
A2: 2024-02 | B2: 45324 | C2: Pre-withdrawal | D2: Canada | E2: Global North | F2: North America | G2: Ministry of Environment | H2: Press release | I2: canada.ca | J2: Government of Canada launches public engagement on the 2035 greenhouse gas emissions reduction target | K2: https://www.canada.ca/en/environment-climate-change/news/2024/02/government-of-canada-launches-public-engagement-on-the-2035-greenhouse-gas-emissions-reduction-target.html | L2: Climate; Climate Change; Environment; Paris Agreement; Steven Guilbeault; climate goals; emissions; energy; greenhouse gas; net zero emissions | M2: Yes | N2: 10 | O2: Canada | P2: page metadata | Q2: live | R2: 782 | S2: Steven Guilbeault | T2: Climate; Climate Change; Environment; climate goals; emissions; energy; greenhouse gas; net zero emissions | U2: Paris Agreement
A3: 2024-02 | B3: 45330 | C3: Pre-withdrawal | D3: Canada | E3: Global North | F3: North America | G3: Ministry of Environment | H3: Press release | I3: canada.ca | J3: Canada taking next steps on the right to a healthy environment and environmental justice and racism | K3: https://www.canada.ca/en/environment-climate-change/news/2024/02/canada-taking-next-steps-on-the-right-to-a-healthy-environment-and-environmental-justice-and-racism.html | L3: Climate; Climate Change; Environment | M3: No | N3: 3 | P3: page metadata | Q3: live | R3: 485 | T3: Climate; Climate Change; Environment
A4: 2024-02 | B4: 45330 | C4: Pre-withdrawal | D4: Canada | E4: Global North | F4: North America | G4: Ministry of Environment | H4: Policy / regulatory | I4: canada.ca | J4: Creating a healthy, clean, and sustainable environment for all: Canada consulting on the right to a healthy environment in federal legislation and engaging on environmental justice and racism | K4: https://www.canada.ca/en/environment-climate-change/news/2024/02/creating-a-healthy-clean-and-sustainable-environment-for-all-canada-consulting-on-the-right-to-a-healthy-environment-in-federal-legislation-and-eng.html | L4: Climate; Climate Change; Environment; Steven Guilbeault | M4: Yes | N4: 4 | O4: Canada | P4: page metadata | Q4: live | R4: 776 | S4: Steven Guilbeault | T4: Climate; Climate Change; Environment
A5: 2024-02 | B5: 45335 | C5: Pre-withdrawal | D5: Canada | E5: Global North | F5: North America | G5: Ministry of Environment | H5: Press release | I5: canada.ca | J5: Minister Guilbeault to make an announcement to support citizen science and protect nature | K5: https://www.canada.ca/en/environment-climate-change/news/2024/02/minister-guilbeault-to-make-an-announcement-to-support-citizen-science-and-protect-nature.html | L5: Climate; Climate Change; Environment; Steven Guilbeault | M5: Yes | N5: 4 | O5: Canada | P5: page metadata | Q5: live | R5: 167 | S5: Steven Guilbeault | T5: Climate; Climate Change; Environment
A6: 2024-02 | B6: 45336 | C6: Pre-withdrawal | D6: Canada | E6: Global North | F6: North America | G6: Ministry of Environment | H6: Press release | I6: canada.ca | J6: Government of Canada invests $3 million in citizen science and open data for birds and biodiversity | K6: https://www.canada.ca/en/environment-climate-change/news/2024/02/government-of-canada-invests-3-million-in-citizen-science-and-open-data-for-birds-and-biodiversity.html | L6: Climate; Climate Change; Environment; Steven Guilbeault | M6: Yes | N6: 4 | O6: Canada | P6: page metadata | Q6: live | R6: 670 | S6: Steven Guilbeault | T6: Climate; Climate Change; Environment
A7: 2024-02 | B7: 45338 | C7: Pre-withdrawal | D7: Canada | E7: Global North | F7: North America | G7: Ministry of Environment | H7: Press release | I7: canada.ca | J7: Minister Guilbeault provides update with new design options for the Clean Electricity Regulations | K7: https://www.canada.ca/en/environment-climate-change/news/2024/02/minister-guilbeault-provides-update-with-new-design-options-for-the-clean-electricity-regulations.html | L7: Climate; Climate Change; Environment; Steven Guilbeault; carbon; emissions; energy; fossil fuel; net zero emissions; transition | M7: Yes | N7: 10 | O7: Canada | P7: page metadata | Q7: live | R7: 890 | S7: Steven Guilbeault | T7: Climate; Climate Change; Environment; carbon; emissions; energy; fossil fuel; net zero emissions; transition
A8: 2024-02 | B8: 45338 | C8: Pre-withdrawal | D8: Canada | E8: Global North | F8: North America | G8: Ministry of Environment | H8: Policy / regulatory | I8: canada.ca | J8: Town of Trenton fined $100,000 for violating the Fisheries Act in Nova Scotia | K8: https://www.canada.ca/en/environment-climate-change/news/2024/02/town-of-trenton-fined-100000-for-violating-the-fisheries-act-in-nova-scotia.html | L8: Climate; Climate Change; Environment | M8: No | N8: 3 | P8: page metadata | Q8: live | R8: 657 | T8: Climate; Climate Change; Environment
A9: 2024-02 | B9: 45342 | C9: Pre-withdrawal | D9: Canada | E9: Global North | F9: North America | G9: Ministry of Environment | H9: Press release | I9: canada.ca | J9: Minister Guilbeault to make a funding announcement supporting affordable home energy retrofits for the City of Peterborough | K9: https://www.canada.ca/en/environment-climate-change/news/2024/02/minister-guilbeault-to-make-a-funding-announcement-to-support-affordable-heating-for-the-city-of-peterborough.html | L9: Climate; Climate Change; Environment; Steven Guilbeault; energy | M9: Yes | N9: 5 | O9: Canada | P9: page metadata | Q9: live | R9: 178 | S9: Steven Guilbeault | T9: Climate; Climate Change; Environment; energy
A10: 2024-02 | B10: 45343 | C10: Pre-withdrawal | D10: Canada | E10: Global North | F10: North America | G10: Ministry of Environment | H10: Press release | I10: canada.ca | J10: Government of Canada to announce a federal investment to support household energy-saving climate action in Newfoundland and Labrador | K10: https://www.canada.ca/en/environment-climate-change/news/2024/02/government-of-canada-to-announce-a-federal-investment-to-support-household-energy-saving-climate-action-in-newfoundland-and-labrador.html | L10: Climate; Climate Change; Environment; Steven Guilbeault; energy | M10: Yes | N10: 5 | O10: Canada | P10: page metadata | Q10: live | R10: 201 | S10: Steven Guilbeault | T10: Climate; Climate Change; Environment; energy
A11: 2024-02 | B11: 45345 | C11: Pre-withdrawal | D11: Canada | E11: Global North | F11: North America | G11: Ministry of Environment | H11: Press release | I11: canada.ca | J11: Federal-provincial agreement allows Newfoundlanders and Labradorians to switch from heating homes with oil to heat pumps and other electric home heating systems | K11: https://www.canada.ca/en/environment-climate-change/news/2024/02/federal-provincial-agreement-allows-newfoundlanders-and-labradorians-to-switch-from-heating-homes-with-oil-to-heat-pumps-and-other-electric-home-he.html | L11: Climate; Climate Change; Environment; Steven Guilbeault; carbon; emissions; energy; greenhouse gas; net zero emissions; transition | M11: Yes | N11: 10 | O11: Canada | P11: page metadata | Q11: live | R11: 1142 | S11: Steven Guilbeault | T11: Climate; Climate Change; Environment; carbon; emissions; energy; greenhouse gas; net zero emissions; transition
A12: 2024-02 | B12: 45345 | C12: Pre-withdrawal | D12: Canada | E12: Global North | F12: North America | G12: Ministry of Environment | H12: Press release | I12: canada.ca | J12: Government of Canada announces draft rules to cut pollutants that cause smog in communities across Canada | K12: https://www.canada.ca/en/environment-climate-change/news/2024/02/government-of-canada-announces-draft-rules-to-cut-pollutants-that-cause-smog-in-communities-across-canada.html | L12: Climate; Climate Change; Environment; Steven Guilbeault; emissions | M12: Yes | N12: 5 | O12: Canada | P12: page metadata | Q12: live | R12: 996 | S12: Steven Guilbeault | T12: Climate; Climate Change; Environment; emissions
A13: 2024-02 | B13: 45345 | C13: Pre-withdrawal | D13: Canada | E13: Global North | F13: North America | G13: Ministry of Environment | H13: Press release | I13: canada.ca | J13: Reduction in the Release of Volatile Organic Compounds (Storage and Loading of Volatile Petroleum Liquids) draft Regulations | K13: https://www.canada.ca/en/environment-climate-change/news/2024/02/reduction-in-the-release-of-volatile-organic-compounds-storage-and-loading-of-volatile-petroleum-liquids-draft-regulations.html | L13: Climate; Climate Change; Environment; carbon; emissions; energy | M13: Yes | N13: 6 | P13: page metadata | Q13: live | R13: 1449 | T13: Climate; Climate Change; Environment; carbon; emissions; energy

Sheet 2024-03
A1: Month | B1: Date | C1: Period | D1: Country | E1: North/South | F1: Continent | G1: Source Type | H1: Document Type | I1: Site | J1: Title | K1: URL | L1: Matched Keywords | M1: Strong Match | N1: Keyword Count | O1: Minister/Person Country | P1: Date Source | Q1: Fetched Via | R1: Word Count | S1: Event/Person hits | T1: Adjective Indicators hits | U1: Organizations/Alliances hits | V1: Regulatory Bodies hits
A2: 2024-03 | B2: 45352 | C2: Pre-withdrawal | D2: Canada | E2: Global North | F2: North America | G2: Ministry of Environment | H2: Press release | I2: canada.ca | J2: Minister Guilbeault calls for an ambitious plastics treaty at the United Nations Environment Assembly in Kenya | K2: https://www.canada.ca/en/environment-climate-change/news/2024/03/minister-guilbeault-calls-for-an-ambitious-plastics-treaty-at-the-united-nations-environment-assembly-in-kenya.html | L2: COP; Climate; Climate Change; Environment; Steven Guilbeault | M2: Yes | N2: 5 | O2: Canada | P2: page metadata | Q2: live | R2: 785 | S2: Steven Guilbeault | T2: Climate; Climate Change; Environment | U2: COP
A3: 2024-03 | B3: 45352 | C3: Pre-withdrawal | D3: Canada | E3: Global North | F3: North America | G3: Ministry of Environment | H3: Press release | I3: canada.ca | J3: Minister Guilbeault to make a funding announcement to support species at risk and their habitats | K3: https://www.canada.ca/en/environment-climate-change/news/2024/03/minister-guilbeault-to-make-a-funding-announcement-to-support-species-at-risk-and-their-habitats.html | L3: Climate; Climate Change; Environment; Steven Guilbeault | M3: Yes | N3: 4 | O3: Canada | P3: page metadata | Q3: live | R3: 186 | S3: Steven Guilbeault | T3: Climate; Climate Change; Environment
A4: 2024-03 | B4: 45355 | C4: Pre-withdrawal | D4: Canada | E4: Global North | F4: North America | G4: Ministry of Environment | H4: Press release | I4: canada.ca | J4: Empowering key regional environmental groups to protect habitats and species at risk in Quebec and across Canada | K4: https://www.canada.ca/en/environment-climate-change/news/2024/03/empowering-key-regional-environmental-groups-to-protect-habitats-and-species-at-risk-in-quebec-and-across-canada.html | L4: Climate; Climate Change; Environment; Steven Guilbeault | M4: Yes | N4: 4 | O4: Canada | P4: page metadata | Q4: live | R4: 916 | S4: Steven Guilbeault | T4: Climate; Climate Change; Environment
A5: 2024-03 | B5: 45355 | C5: Pre-withdrawal | D5: Canada | E5: Global North | F5: North America | G5: Ministry of Environment | H5: Press release | I5: canada.ca | J5: List of 56 Habitat Stewardship Program for Species at Risk projects 2023–2024 | K5: https://www.canada.ca/en/environment-climate-change/news/2024/03/list-of-56-habitat-stewardship-program-for-species-at-risk-projects-20232024.html | L5: Environment | M5: No | N5: 1 | P5: page metadata | Q5: live | R5: 2647 | T5: Environment
A6: 2024-03 | B6: 45359 | C6: Pre-withdrawal | D6: Canada | E6: Global North | F6: North America | G6: Ministry of Environment | H6: Press release | I6: canada.ca | J6: Governments of Canada and Ontario join together to announce funding and collaboration for conservation areas in Ontario | K6: https://www.canada.ca/en/environment-climate-change/news/2024/03/governments-of-canada-and-ontario-join-together-to-announce-funding-and-collaboration-for-conservation-areas-in-ontario.html | L6: Climate; Climate Change; Environment; Steven Guilbeault | M6: Yes | N6: 4 | O6: Canada | P6: page metadata | Q6: live | R6: 220 | S6: Steven Guilbeault | T6: Climate; Climate Change; Environment
A7: 2024-03 | B7: 45359 | C7: Pre-withdrawal | D7: Canada | E7: Global North | F7: North America | G7: Ministry of Environment | H7: Press release | I7: canada.ca | J7: UPDATE: Minister Guilbeault to travel to New Brunswick to make a funding announcement for a clean electricity project through the Future Electricity Fund | K7: https://www.canada.ca/en/environment-climate-change/news/2024/03/minister-guilbeault-to-travel-to-new-brunswick-to-participate-in-a-ribbon-cutting-ceremony-and-make-a-funding-announcement-for-a-clean-electricity-.html | L7: Climate; Climate Change; Environment; Steven Guilbeault; energy | M7: Yes | N7: 5 | O7: Canada | P7: page metadata | Q7: live | R7: 234 | S7: Steven Guilbeault | T7: Climate; Climate Change; Environment; energy
A8: 2024-03 | B8: 45362 | C8: Pre-withdrawal | D8: Canada | E8: Global North | F8: North America | G8: Ministry of Environment | H8: Press release | I8: canada.ca | J8: Canada and Ontario commit to significant collaboration on shared nature conservation goals | K8: https://www.canada.ca/en/environment-climate-change/news/2024/03/canada-and-ontario-commit-to-significant-collaboration-on-shared-nature-conservation-goals.html | L8: Climate; Climate Change; Environment; Steven Guilbeault; carbon; commitments | M8: Yes | N8: 6 | O8: Canada | P8: page metadata | Q8: live | R8: 1196 | S8: Steven Guilbeault | T8: Climate; Climate Change; Environment; carbon; commitments
A9: 2024-03 | B9: 45362 | C9: Pre-withdrawal | D9: Canada | E9: Global North | F9: North America | G9: Ministry of Environment | H9: Press release | I9: canada.ca | J9: Cutting the ribbon on the largest battery energy storage system in New Brunswick | K9: https://www.canada.ca/en/environment-climate-change/news/2024/03/cutting-the-ribbon-on-the-largest-battery-energy-storage-system-in-new-brunswick.html | L9: Climate; Climate Change; Environment; Steven Guilbeault; emissions; energy; fossil fuel; green; greenhouse gas; renewable energy; transition | M9: Yes | N9: 11 | O9: Canada | P9: page metadata | Q9: live | R9: 942 | S9: Steven Guilbeault | T9: Climate; Climate Change; Environment; emissions; energy; fossil fuel; green; greenhouse gas; renewable energy; transition
A10: 2024-03 | B10: 45362 | C10: Pre-withdrawal | D10: Canada | E10: Global North | F10: North America | G10: Ministry of Environment | H10: Press release | I10: canada.ca | J10: Helping New Brunswickers reduce energy costs, cut pollution | K10: https://www.canada.ca/en/environment-climate-change/news/2024/03/helping-new-brunswickers-reduce-energy-costs-cut-pollution.html | L10: Climate; Climate Change; Environment; Steven Guilbeault; Sustainability; carbon; climate goals; emissions; energy; greenhouse gas; net zero emissions; sustainable energy; transition | M10: Yes | N10: 13 | O10: Canada | P10: page metadata | Q10: live | R10: 1058 | S10: Steven Guilbeault | T10: Climate; Climate Change; Environment; Sustainability; carbon; climate goals; emissions; energy; greenhouse gas; net zero emissions; sustainable energy; transition
A11: 2024-03 | B11: 45362 | C11: Pre-withdrawal | D11: Canada | E11: Global North | F11: North America | G11: Ministry of Environment | H11: Press release | I11: canada.ca | J11: Minister Guilbeault to travel to Nova Scotia to make an announcement regarding a clean energy investment and hold media availabilities | K11: https://www.canada.ca/en/environment-climate-change/news/2024/03/minister-guilbeault-to-travel-to-nova-scotia-to-make-an-announcement-regarding-a-clean-energy-investment-and-hold-media-availabilities.html | L11: Climate; Climate Change; Environment; Steven Guilbeault; energy | M11: Yes | N11: 5 | O11: Canada | P11: page metadata | Q11: live | R11: 213 | S11: Steven Guilbeault | T11: Climate; Climate Change; Environment; energy
A12: 2024-03 | B12: 45363 | C12: Pre-withdrawal | D12: Canada | E12: Global North | F12: North America | G12: Ministry of Environment | H12: Press release | I12: canada.ca | J12: Government of Canada supports Indigenous climate action with new funding stream under the Indigenous Leadership Fund | K12: https://www.canada.ca/en/environment-climate-change/news/2024/03/government-of-canada-supports-indigenous-climate-action-with-new-funding-stream-under-the-indigenous-leadership-fund.html | L12: Climate; Climate Change; Environment; Steven Guilbeault; carbon; emissions; energy; green; greenhouse gas; net zero emissions; renewable energy | M12: Yes | N12: 11 | O12: Canada | P12: page metadata | Q12: live | R12: 662 | S12: Steven Guilbeault | T12: Climate; Climate Change; Environment; carbon; emissions; energy; green; greenhouse gas; net zero emissions; renewable energy
A13: 2024-03 | B13: 45364 | C13: Pre-withdrawal | D13: Canada | E13: Global North | F13: North America | G13: Ministry of Environment | H13: Press release | I13: canada.ca | J13: Government of Canada to deliver final step of major radar modernization project, followed by a site tour | K13: https://www.canada.ca/en/environment-climate-change/news/2024/03/government-of-canada-to-deliver-final-step-of-major-radar-modernization-project-followed-by-a-site-tour.html | L13: Climate; Climate Change; Environment; Steven Guilbeault | M13: Yes | N13: 4 | O13: Canada | P13: page metadata | Q13: live | R13: 263 | S13: Steven Guilbeault | T13: Climate; Climate Change; Environment
A14: 2024-03 | B14: 45365 | C14: Pre-withdrawal | D14: Canada | E14: Global North | F14: North America | G14: Ministry of Environment | H14: Press release | I14: canada.ca | J14: Call for applications for the next Environment and Climate Change Youth Council: A chance to help shape our environmental future | K14: https://www.canada.ca/en/environment-climate-change/news/2024/03/call-for-applications-for-the-next-environment-and-climate-change-youth-council-a-chance-to-help-shape-our-environmental-future.html | L14: Climate; Climate Change; Environment; Steven Guilbeault | M14: Yes | N14: 4 | O14: Canada | P14: page metadata | Q14: live | R14: 697 | S14: Steven Guilbeault | T14: Climate; Climate Change; Environment
A15: 2024-03 | B15: 45365 | C15: Pre-withdrawal | D15: Canada | E15: Global North | F15: North America | G15: Ministry of Environment | H15: Policy / regulatory | I15: canada.ca | J15: Minister Guilbeault meets with historically impacted Black community in advance of environmental justice and racism bill | K15: https://www.canada.ca/en/environment-climate-change/news/2024/03/minister-guilbeault-meets-with-historically-impacted-black-community-in-advance-of-environmental-justice-and-racism-bill.html | L15: Climate; Climate Change; Environment; Steven Guilbeault | M15: Yes | N15: 4 | O15: Canada | P15: page metadata | Q15: live | R15: 938 | S15: Steven Guilbeault | T15: Climate; Climate Change; Environment
A16: 2024-03 | B16: 45366 | C16: Pre-withdrawal | D16: Canada | E16: Global North | F16: North America | G16: Ministry of Environment | H16: Press release | I16: canada.ca | J16: Canada’s modernized radar network | K16: https://www.canada.ca/en/environment-climate-change/news/2024/03/canadas-modernized-radar-network.html | L16: Climate; Climate Change; Environment | M16: No | N16: 3 | P16: page metadata | Q16: live | R16: 708 | T16: Climate; Climate Change; Environment
A17: 2024-03 | B17: 45366 | C17: Pre-withdrawal | D17: Canada | E17: Global North | F17: North America | G17: Ministry of Environment | H17: Press release | I17: canada.ca | J17: Keeping Canadians safe and tracking severe weather: Government of Canada completes 33 state-of-the-art radar modernization projects across Canada | K17: https://www.canada.ca/en/environment-climate-change/news/2024/03/keeping-canadians-safe-and-tracking-severe-weather-government-of-canada-completes-33-state-of-the-art-radar-modernization-projects-across-canada.html | L17: Climate; Climate Change; Environment; Steven Guilbeault | M17: Yes | N17: 4 | O17: Canada | P17: page metadata | Q17: live | R17: 1116 | S17: Steven Guilbeault | T17: Climate; Climate Change; Environment
A18: 2024-03 | B18: 45370 | C18: Pre-withdrawal | D18: Canada | E18: Global North | F18: North America | G18: Ministry of Environment | H18: Policy / regulatory | I18: canada.ca | J18: Groupe Marcelle inc. was fined $500,000 for violating the Canadian Environmental Protection Act, 1999 | K18: https://www.canada.ca/en/environment-climate-change/news/2024/03/groupe-marcelle-inc-was-fined-500000-for-violating-the-canadian-environmental-protection-act-1999.html | L18: Climate; Climate Change; Environment | M18: No | N18: 3 | P18: page metadata | Q18: live | R18: 605 | T18: Climate; Climate Change; Environment
A19: 2024-03 | B19: 45370 | C19: Pre-withdrawal | D19: Canada | E19: Global North | F19: North America | G19: Ministry of Environment | H19: Press release | I19: canada.ca | J19: Keep the cash, care for climate: Canada Carbon Rebates being paid next month | K19: https://www.canada.ca/en/environment-climate-change/news/2024/03/keep-the-cash-care-for-climate-canada-carbon-rebates-being-paid-next-month.html | L19: Climate; Climate Change; Environment; Steven Guilbeault; carbon; emissions; energy; net zero emissions | M19: Yes | N19: 8 | O19: Canada | P19: page metadata | Q19: live | R19: 1155 | S19: Steven Guilbeault | T19: Climate; Climate Change; Environment; carbon; emissions; energy; net zero emissions
A20: 2024-03 | B20: 45372 | C20: Pre-withdrawal | D20: Canada | E20: Global North | F20: North America | G20: Ministry of Environment | H20: Press release | I20: canada.ca | J20: Minister Guilbeault to make an announcement to support the conservation and improvement of the St. Lawrence ecosystem | K20: https://www.canada.ca/en/environment-climate-change/news/2024/03/minister-guilbeault-to-make-an-announcement-to-support-the-conservation-and-improvement-of-the-st-lawrence-ecosystem.html | L20: Climate; Climate Change; Environment; Steven Guilbeault | M20: Yes | N20: 4 | O20: Canada | P20: page metadata | Q20: live | R20: 200 | S20: Steven Guilbeault | T20: Climate; Climate Change; Environment
A21: 2024-03 | B21: 45373 | C21: Pre-withdrawal | D21: Canada | E21: Global North | F21: North America | G21: Ministry of Environment | H21: Press release | I21: canada.ca | J21: On World Water Day, the Government of Canada announces funding for new community projects to protect fresh water | K21: https://www.canada.ca/en/environment-climate-change/news/2024/03/on-world-water-day-the-government-of-canada-announces-funding-for-new-community-projects-to-protect-fresh-water.html | L21: Climate; Climate Change; Environment; Steven Guilbeault; Sustainability | M21: Yes | N21: 5 | O21: Canada | P21: page metadata | Q21: live | R21: 969 | S21: Steven Guilbeault | T21: Climate; Climate Change; Environment; Sustainability
A22: 2024-03 | B22: 45373 | C22: Pre-withdrawal | D22: Canada | E22: Global North | F22: North America | G22: Ministry of Environment | H22: Press release | I22: canada.ca | J22: Regional parks in British Columbia’s Central Okanagan join Canada’s national conservation network, conserving nature and combatting climate change | K22: https://www.canada.ca/en/environment-climate-change/news/2024/03/regional-parks-in-british-columbias-central-okanagan-join-canadas-national-conservation-network-conserving-nature-and-combatting-climate-change.html | L22: Climate; Climate Change; Environment; Steven Guilbeault; carbon | M22: Yes | N22: 5 | O22: Canada | P22: page metadata | Q22: live | R22: 827 | S22: Steven Guilbeault | T22: Climate; Climate Change; Environment; carbon
A23: 2024-03 | B23: 45377 | C23: Pre-withdrawal | D23: Canada | E23: Global North | F23: North America | G23: Ministry of Environment | H23: Press release | I23: canada.ca | J23: Ministers Guilbeault and Rodriguez to make an announcement on housing and affordability | K23: https://www.canada.ca/en/environment-climate-change/news/2024/03/ministers-guilbeault-and-rodriguez-to-make-an-announcement-on-housing-and-affordability.html | L23: Climate; Climate Change; Environment; Steven Guilbeault | M23: Yes | N23: 4 | O23: Canada | P23: page metadata | Q23: live | R23: 145 | S23: Steven Guilbeault | T23: Climate; Climate Change; Environment

Sheet 2024-04
A1: Month | B1: Date | C1: Period | D1: Country | E1: North/South | F1: Continent | G1: Source Type | H1: Document Type | I1: Site | J1: Title | K1: URL | L1: Matched Keywords | M1: Strong Match | N1: Keyword Count | O1: Minister/Person Country | P1: Date Source | Q1: Fetched Via | R1: Word Count | S1: Event/Person hits | T1: Adjective Indicators hits | U1: Organizations/Alliances hits | V1: Regulatory Bodies hits
A2: 2024-04 | B2: 45392 | C2: Pre-withdrawal | D2: Canada | E2: Global North | F2: North America | G2: Ministry of Environment | H2: Press release | I2: canada.ca | J2: New Canada Carbon Rebate estimator tells you how much you may get back in payments starting April 15 | K2: https://www.canada.ca/en/environment-climate-change/news/2024/04/new-canada-carbon-rebate-estimator-tells-you-how-much-you-may-get-back-in-payments-starting-april-15.html | L2: Climate; Climate Change; Environment; Steven Guilbeault; carbon; climate goals; emissions; energy; greenhouse gas | M2: Yes | N2: 9 | O2: Canada | P2: page metadata | Q2: live | R2: 875 | S2: Steven Guilbeault | T2: Climate; Climate Change; Environment; carbon; climate goals; emissions; energy; greenhouse gas
A3: 2024-04 | B3: 45399 | C3: Pre-withdrawal | D3: Canada | E3: Global North | F3: North America | G3: Ministry of Environment | H3: Press release | I3: canada.ca | J3: Government of Canada to hold a technical briefing on Canada’s priorities and objectives for the fourth session of the Intergovernmental Negotiating Committee on Plastic Pollution (INC-4) | K3: https://www.canada.ca/en/environment-climate-change/news/2024/04/government-of-canada-to-hold-a-technical-briefing-on-canadas-priorities-and-objectives-for-the-fourth-session-of-the-intergovernmental-negotiating-.html | L3: Climate; Climate Change; Environment | M3: No | N3: 3 | P3: page metadata | Q3: live | R3: 203 | T3: Climate; Climate Change; Environment
A4: 2024-04 | B4: 45400 | C4: Pre-withdrawal | D4: Canada | E4: Global North | F4: North America | G4: Ministry of Environment | H4: Press release | I4: canada.ca | J4: Canada brings the world together in pursuit of an ambitious global deal to end plastic pollution | K4: https://www.canada.ca/en/environment-climate-change/news/2024/04/canada-brings-the-world-together-in-pursuit-of-an-ambitious-global-deal-to-end-plastic-pollution.html | L4: Circular; Circular Economy; Climate; Climate Change; Environment; Steven Guilbeault; United Nations Environment Programme | M4: Yes | N4: 7 | O4: Canada | P4: page metadata | Q4: live | R4: 1097 | S4: Steven Guilbeault | T4: Circular; Circular Economy; Climate; Climate Change; Environment | U4: United Nations Environment Programme
A5: 2024-04 | B5: 45400 | C5: Pre-withdrawal | D5: Canada | E5: Global North | F5: North America | G5: Ministry of Environment | H5: Press release | I5: canada.ca | J5: UPDATE - Itinerary: Minister Guilbeault to attend the fourth session of the Intergovernmental Negotiating Committee (INC-4) | K5: https://www.canada.ca/en/environment-climate-change/news/2024/04/itinerary-minister-guilbeault-to-attend-the-fourth-session-of-the-intergovernmental-negotiating-committee-inc-4.html | L5: Climate; Climate Change; Environment; Steven Guilbeault; United Nations Environment Programme | M5: Yes | N5: 5 | O5: Canada | P5: page metadata | Q5: live | R5: 404 | S5: Steven Guilbeault | T5: Climate; Climate Change; Environment | U5: United Nations Environment Programme
A6: 2024-04 | B6: 45404 | C6: Pre-withdrawal | D6: Canada | E6: Global North | F6: North America | G6: Ministry of Environment | H6: Press release | I6: canada.ca | J6: Alberta resident sentenced to $35,000 fine and prohibition order for illegally importing and possessing protected turtles and turtle eggs | K6: https://www.canada.ca/en/environment-climate-change/news/2024/04/alberta-resident-sentenced-to-35000-fine-and-prohibition-order-for-illegally-importing-and-possessing-protected-turtles-and-turtle-eggs.html | L6: Climate; Climate Change; Environment | M6: No | N6: 3 | P6: page metadata | Q6: live | R6: 577 | T6: Climate; Climate Change; Environment
A7: 2024-04 | B7: 45404 | C7: Pre-withdrawal | D7: Canada | E7: Global North | F7: North America | G7: Ministry of Environment | H7: Press release | I7: canada.ca | J7: Minister Guilbeault to make an announcement to help promote a circular economy and reduce plastic pollution in Canada | K7: https://www.canada.ca/en/environment-climate-change/news/2024/04/minister-guilbeault-to-make-an-announcement-to-help-promote-a-circular-economy-and-reduce-plastic-pollution-in-canada.html | L7: Circular; Circular Economy; Climate; Climate Change; Environment; Julie Dabrusin; Steven Guilbeault | M7: Yes | N7: 7 | O7: Canada | P7: page metadata | Q7: live | R7: 200 | S7: Julie Dabrusin; Steven Guilbeault | T7: Circular; Circular Economy; Climate; Climate Change; Environment
A8: 2024-04 | B8: 45404 | C8: Pre-withdrawal | D8: Canada | E8: Global North | F8: North America | G8: Ministry of Environment | H8: Press release | I8: canada.ca | J8: The Government of Canada requires producers to take more responsibility for the plastic they put on the market | K8: https://www.canada.ca/en/environment-climate-change/news/2024/04/the-government-of-canada-requires-producers-to-take-more-responsibility-for-the-plastic-they-put-on-the-market.html | L8: Circular; Circular Economy; Environment | M8: No | N8: 3 | P8: page metadata | Q8: live | R8: 1189 | T8: Circular; Circular Economy; Environment
A9: 2024-04 | B9: 45404 | C9: Pre-withdrawal | D9: Canada | E9: Global North | F9: North America | G9: Ministry of Environment | H9: Press release | I9: canada.ca | J9: The Government of Canada requires producers to take more responsibility for the plastic they put on the market | K9: https://www.canada.ca/en/environment-climate-change/news/2024/04/the-government-of-canada-requires-producers-to-take-more-responsibility-for-the-plastic-they-put-on-the-market0.html | L9: Circular; Circular Economy; Climate; Climate Change; Environment; Steven Guilbeault; Transparency; green | M9: Yes | N9: 8 | O9: Canada | P9: page metadata | Q9: live | R9: 777 | S9: Steven Guilbeault | T9: Circular; Circular Economy; Climate; Climate Change; Environment; Transparency; green
A10: 2024-04 | B10: 45405 | C10: Pre-withdrawal | D10: Canada | E10: Global North | F10: North America | G10: Ministry of Environment | H10: Press release | I10: canada.ca | J10: Canadian Plastics Innovation Challenges— Environment and Climate Change Canada Phase 1 recipients | K10: https://www.canada.ca/en/environment-climate-change/news/2024/04/canadian-plastics-innovation-challenges-environment-and-climate-change-canada-phase-1-recipients.html | L10: Circular; Circular Economy; Climate; Climate Change; Environment; energy | M10: Yes | N10: 6 | P10: page metadata | Q10: live | R10: 712 | T10: Circular; Circular Economy; Climate; Climate Change; Environment; energy
A11: 2024-04 | B11: 45405 | C11: Pre-withdrawal | D11: Canada | E11: Global North | F11: North America | G11: Ministry of Environment | H11: Press release | I11: canada.ca | J11: Government of Canada invests to support Canadian innovators to find ways to reduce plastic pollution | K11: https://www.canada.ca/en/environment-climate-change/news/2024/04/government-of-canada-invests-to-support-canadian-innovators-to-find-ways-to-reduce-plastic-pollution.html | L11: Circular; Circular Economy; Climate; Climate Change; Environment; Julie Dabrusin; Steven Guilbeault; Sustainable Economy; energy | M11: Yes | N11: 9 | O11: Canada | P11: page metadata | Q11: live | R11: 904 | S11: Julie Dabrusin; Steven Guilbeault | T11: Circular; Circular Economy; Climate; Climate Change; Environment; Sustainable Economy; energy
A12: 2024-04 | B12: 45405 | C12: Pre-withdrawal | D12: Canada | E12: Global North | F12: North America | G12: Ministry of Environment | H12: Joint / ministerial statement | I12: canada.ca | J12: Minister Guilbeault issues statement on high-level meeting as INC-4 begins | K12: https://www.canada.ca/en/environment-climate-change/news/2024/04/minister-guilbeault-issues-statement-on-high-level-meeting-as-inc-4-begins.html | L12: Climate; Climate Change; Environment; Steven Guilbeault | M12: Yes | N12: 4 | O12: Canada | P12: page metadata | Q12: live | R12: 463 | S12: Steven Guilbeault | T12: Climate; Climate Change; Environment
A13: 2024-04 | B13: 45405 | C13: Pre-withdrawal | D13: Canada | E13: Global North | F13: North America | G13: Ministry of Environment | H13: Press release | I13: canada.ca | J13: Ministers Guilbeault, Champagne and Bibeau to make an announcement on housing and affordability | K13: https://www.canada.ca/en/environment-climate-change/news/2024/04/ministers-guilbeault-champagne-and-bibeau-to-make-an-announcement-on-housing-and-affordability.html | L13: Climate; Climate Change; Environment; Steven Guilbeault | M13: Yes | N13: 4 | O13: Canada | P13: page metadata | Q13: live | R13: 208 | S13: Steven Guilbeault | T13: Climate; Climate Change; Environment
A14: 2024-04 | B14: 45405 | C14: Pre-withdrawal | D14: Canada | E14: Global North | F14: North America | G14: Ministry of Environment | H14: Press release | I14: canada.ca | J14: Recipients of the grants and contributions funding for advancing a circular economy for plastics in Canada | K14: https://www.canada.ca/en/environment-climate-change/news/2024/04/recipients-of-the-grants-and-contributions-funding-for-advancing-a-circular-economy-for-plastics-in-canada.html | L14: Circular; Circular Economy; Climate; Climate Change; Environment; carbon; emissions; energy | M14: Yes | N14: 8 | P14: page metadata | Q14: live | R14: 905 | T14: Circular; Circular Economy; Climate; Climate Change; Environment; carbon; emissions; energy
A15: 2024-04 | B15: 45406 | C15: Pre-withdrawal | D15: Canada | E15: Global North | F15: North America | G15: Ministry of Environment | H15: Press release | I15: canada.ca | J15: Ministers Champagne, Bibeau, and Guilbeault highlight budget investments to support housing creation | K15: https://www.canada.ca/en/environment-climate-change/news/2024/04/ministers-champagne-bibeau-and-guilbeault-highlight-budget-investments-to-support-housing-creation.html | L15: Climate; Climate Change; Environment; Steven Guilbeault | M15: Yes | N15: 4 | O15: Canada | P15: page metadata | Q15: live | R15: 1220 | S15: Steven Guilbeault | T15: Climate; Climate Change; Environment
A16: 2024-04 | B16: 45408 | C16: Pre-withdrawal | D16: Canada | E16: Global North | F16: North America | G16: Ministry of Environment | H16: Policy / regulatory | I16: canada.ca | J16: Husky Oil Operations Limited fined $2.5 million for three offences under federal legislation related to crude oil release in Newfoundland and Labrador offshore | K16: https://www.canada.ca/en/environment-climate-change/news/2024/04/husky-oil-operations-limited-fined-25-million-for-three-offences-under-federal-legislation-related-to-crude-oil-release-in-newfoundland-and-labrado.html | L16: Climate; Climate Change; Environment | M16: No | N16: 3 | P16: page metadata | Q16: live | R16: 748 | T16: Climate; Climate Change; Environment
A17: 2024-04 | B17: 45411 | C17: Pre-withdrawal | D17: Canada | E17: Global North | F17: North America | G17: Ministry of Environment | H17: Press release | I17: canada.ca | J17: Minister Guilbeault to hold a media availability from the G7 Ministers’ Meeting on Climate, Energy and Environment in Turin, Italy | K17: https://www.canada.ca/en/environment-climate-change/news/2024/04/minister-guilbeault-to-hold-a-media-availability-from-the-g7-ministers-meeting-on-climate-energy-and-environment-in-turin-italy.html | L17: Climate; Climate Change; Environment; Steven Guilbeault; energy | M17: Yes | N17: 5 | O17: Canada | P17: page metadata | Q17: live | R17: 184 | S17: Steven Guilbeault | T17: Climate; Climate Change; Environment; energy
A18: 2024-04 | B18: 45412 | C18: Pre-withdrawal | D18: Canada | E18: Global North | F18: North America | G18: Ministry of Environment | H18: Policy / regulatory | I18: canada.ca | J18: Canada helps chart roadmap toward an ambitious global deal to end plastic pollution | K18: https://www.canada.ca/en/environment-climate-change/news/2024/04/canada-helps-chart-roadmap-toward-an-ambitious-global-deal-to-end-plastic-pollution.html | L18: Circular; Circular Economy; Climate; Climate Change; Environment; Julie Dabrusin; Paris Agreement; Steven Guilbeault; Sustainable Economic Development; United Nations Environment Programme | M18: Yes | N18: 10 | O18: Canada | P18: page metadata | Q18: live | R18: 1024 | S18: Julie Dabrusin; Steven Guilbeault | T18: Circular; Circular Economy; Climate; Climate Change; Environment; Sustainable Economic Development | U18: Paris Agreement; United Nations Environment Programme
A19: 2024-04 | B19: 45412 | C19: Pre-withdrawal | D19: Canada | E19: Global North | F19: North America | G19: Ministry of Environment | H19: Policy / regulatory | I19: canada.ca | J19: Federal government concerned about further delays in release of Quebec government’s caribou strategy | K19: https://www.canada.ca/en/environment-climate-change/news/2024/04/federal-government-concerned-about-further-delays-in-release-of-quebec-governments-caribou-strategy.html | L19: Climate; Climate Change; Environment; Steven Guilbeault | M19: Yes | N19: 4 | O19: Canada | P19: page metadata | Q19: live | R19: 337 | S19: Steven Guilbeault | T19: Climate; Climate Change; Environment
A20: 2024-04 | B20: 45412 | C20: Pre-withdrawal | D20: Canada | E20: Global North | F20: North America | G20: Ministry of Environment | H20: Press release | I20: canada.ca | J20: Government of Canada to hold a media availability to respond to the tabling of the Commissioner of the Environment and Sustainable Development 2024 spring reports | K20: https://www.canada.ca/en/environment-climate-change/news/2024/04/government-of-canada-to-hold-a-media-availability-to-respond-to-the-tabling-of-the-commissioner-of-the-environment-and-sustainable-development-2024.html | L20: Climate; Climate Change; Environment; Julie Dabrusin; Steven Guilbeault | M20: Yes | N20: 5 | O20: Canada | P20: page metadata | Q20: live | R20: 188 | S20: Julie Dabrusin; Steven Guilbeault | T20: Climate; Climate Change; Environment
A21: 2024-04 | B21: 45412 | C21: Pre-withdrawal | D21: Canada | E21: Global North | F21: North America | G21: Ministry of Environment | H21: Press release | I21: canada.ca | J21: Government of Canada welcomes reports from the Commissioner of the Environment and Sustainable Development | K21: https://www.canada.ca/en/environment-climate-change/news/2024/04/government-of-canada-welcomes-reports-from-the-commissioner-of-the-environment-and-sustainable-development.html | L21: Circular; Climate; Climate Change; Climate change mitigation; Environment; Steven Guilbeault; Sustainability; Transparency; carbon; carbon emissions; climate goals; commitments; emissions; greenhouse gas; transition | M21: Yes | N21: 15 | O21: Canada | P21: page metadata | Q21: live | R21: 1652 | S21: Steven Guilbeault | T21: Circular; Climate; Climate Change; Climate change mitigation; Environment; Sustainability; Transparency; carbon; carbon emissions; climate goals; commitments; emissions; greenhouse gas; transition

Sheet 2024-05
A1: Month | B1: Date | C1: Period | D1: Country | E1: North/South | F1: Continent | G1: Source Type | H1: Document Type | I1: Site | J1: Title | K1: URL | L1: Matched Keywords | M1: Strong Match | N1: Keyword Count | O1: Minister/Person Country | P1: Date Source | Q1: Fetched Via | R1: Word Count | S1: Event/Person hits | T1: Adjective Indicators hits | U1: Organizations/Alliances hits | V1: Regulatory Bodies hits
A2: 2024-05 | B2: 45413 | C2: Pre-withdrawal | D2: Canada | E2: Global North | F2: North America | G2: Ministry of Environment | H2: Press release | I2: canada.ca | J2: Minister Guilbeault concludes G7 Ministers’ Meeting with strong outcomes on clean energy, clean air, and a nature-positive future | K2: https://www.canada.ca/en/environment-climate-change/news/2024/05/minister-guilbeault-concludes-g7-ministers-meeting-with-strong-outcomes-on-clean-energy-clean-air-and-a-nature-positive-future.html | L2: COP; Climate; Climate Change; Environment; Steven Guilbeault; Transparency; carbon; commitments; emissions; energy; fossil fuel; sustainable energy; transition | M2: Yes | N2: 13 | O2: Canada | P2: page metadata | Q2: live | R2: 1605 | S2: Steven Guilbeault | T2: Climate; Climate Change; Environment; Transparency; carbon; commitments; emissions; energy; fossil fuel; sustainable energy; transition | U2: COP
A3: 2024-05 | B3: 45413 | C3: Pre-withdrawal | D3: Canada | E3: Global North | F3: North America | G3: Ministry of Environment | H3: Press release | I3: canada.ca | J3: Minister Guilbeault to make an announcement on Canada’s progress to lower greenhouse gas emissions and grow the economy | K3: https://www.canada.ca/en/environment-climate-change/news/2024/05/minister-guilbeault-to-make-an-announcement-on-canadas-progress-to-lower-greenhouse-gas-emissions-and-grow-the-economy.html | L3: Climate; Climate Change; Environment; Steven Guilbeault; emissions; greenhouse gas | M3: Yes | N3: 6 | O3: Canada | P3: page metadata | Q3: live | R3: 200 | S3: Steven Guilbeault | T3: Climate; Climate Change; Environment; emissions; greenhouse gas
A4: 2024-05 | B4: 45414 | C4: Pre-withdrawal | D4: Canada | E4: Global North | F4: North America | G4: Ministry of Environment | H4: Press release | I4: canada.ca | J4: Canada’s 2024 National Inventory Report shows Canada is successfully reducing emissions | K4: https://www.canada.ca/en/environment-climate-change/news/2024/05/canadas-2024-national-inventory-report-shows-canada-is-successfully-reducing-emissions.html | L4: Climate; Climate Change; Environment; Paris Agreement; Steven Guilbeault; carbon; emissions; energy; greenhouse gas | M4: Yes | N4: 9 | O4: Canada | P4: page metadata | Q4: live | R4: 954 | S4: Steven Guilbeault | T4: Climate; Climate Change; Environment; carbon; emissions; energy; greenhouse gas | U4: Paris Agreement
A5: 2024-05 | B5: 45414 | C5: Pre-withdrawal | D5: Canada | E5: Global North | F5: North America | G5: Ministry of Environment | H5: Press release | I5: canada.ca | J5: Where Canada’s greenhouse gas emissions come from: 2024 National Greenhouse Gas Inventory | K5: https://www.canada.ca/en/environment-climate-change/news/2024/05/where-canadas-greenhouse-gas-emissions-come-from-2024-national-greenhouse-gas-inventory.html | L5: Climate; Climate Change; Environment; Paris Agreement; carbon; emissions; energy; green; greenhouse gas; net zero emissions; transition | M5: Yes | N5: 11 | P5: page metadata | Q5: live | R5: 3411 | T5: Climate; Climate Change; Environment; carbon; emissions; energy; green; greenhouse gas; net zero emissions; transition | U5: Paris Agreement
A6: 2024-05 | B6: 45418 | C6: Pre-withdrawal | D6: Canada | E6: Global North | F6: North America | G6: Ministry of Environment | H6: Press release | I6: canada.ca | J6: Canada cultivates climate solutions with financial incentive for sustainable forest management | K6: https://www.canada.ca/en/environment-climate-change/news/2024/05/canada-cultivates-climate-solutions-with-financial-incentive-for-sustainable-forest-management.html | L6: Climate; Climate Change; Environment; Steven Guilbeault; carbon; emissions; energy; greenhouse gas | M6: Yes | N6: 8 | O6: Canada | P6: page metadata | Q6: live | R6: 1200 | S6: Steven Guilbeault | T6: Climate; Climate Change; Environment; carbon; emissions; energy; greenhouse gas
A7: 2024-05 | B7: 45420 | C7: Pre-withdrawal | D7: Canada | E7: Global North | F7: North America | G7: Ministry of Environment | H7: Press release | I7: canada.ca | J7: Environment and Climate Change Canada hosts Blainville radar media tour and media availability with Minister Guilbeault | K7: https://www.canada.ca/en/environment-climate-change/news/2024/05/environment-and-climate-change-canada-hosts-blainville-radar-media-tour-and-media-availability-with-minister-guilbeault.html | L7: Climate; Climate Change; Environment; Steven Guilbeault | M7: Yes | N7: 4 | O7: Canada | P7: page metadata | Q7: live | R7: 321 | S7: Steven Guilbeault | T7: Climate; Climate Change; Environment
A8: 2024-05 | B8: 45420 | C8: Pre-withdrawal | D8: Canada | E8: Global North | F8: North America | G8: Ministry of Environment | H8: Press release | I8: canada.ca | J8: Government of Canada to make an announcement on investments to help lower greenhouse gas emissions in Ontario | K8: https://www.canada.ca/en/environment-climate-change/news/2024/05/government-of-canada-to-make-an-announcement-on-investments-to-help-lower-greenhouse-gas-emissions-in-ontario.html | L8: Climate; Climate Change; Environment; Steven Guilbeault; emissions; greenhouse gas | M8: Yes | N8: 6 | O8: Canada | P8: page metadata | Q8: live | R8: 200 | S8: Steven Guilbeault | T8: Climate; Climate Change; Environment; emissions; greenhouse gas
A9: 2024-05 | B9: 45421 | C9: Pre-withdrawal | D9: Canada | E9: Global North | F9: North America | G9: Ministry of Environment | H9: Press release | I9: canada.ca | J9: Major upgrades to Children’s Hospital of Eastern Ontario for cleaner, healthier air and energy savings | K9: https://www.canada.ca/en/environment-climate-change/news/2024/05/major-upgrades-to-childrens-hospital-of-eastern-ontario-for-cleaner-healthier-air-and-energy-savings.html | L9: Climate; Climate Change; Environment; Steven Guilbeault; carbon; carbon emissions; emissions; energy; greenhouse gas; net zero emissions | M9: Yes | N9: 10 | O9: Canada | P9: page metadata | Q9: live | R9: 794 | S9: Steven Guilbeault | T9: Climate; Climate Change; Environment; carbon; carbon emissions; emissions; energy; greenhouse gas; net zero emissions
A10: 2024-05 | B10: 45422 | C10: Pre-withdrawal | D10: Canada | E10: Global North | F10: North America | G10: Ministry of Environment | H10: Press release | I10: canada.ca | J10: Canada cuts carbon pollution with funding for Glencore Canada Corporation project | K10: https://www.canada.ca/en/environment-climate-change/news/2024/05/canada-cuts-carbon-pollution-with-funding-for-glencore-canada-corporation-project.html | L10: Climate; Climate Change; Environment; Steven Guilbeault; carbon; carbon emissions; emissions; energy; green; greenhouse gas; renewable energy; transition | M10: Yes | N10: 12 | O10: Canada | P10: page metadata | Q10: live | R10: 1035 | S10: Steven Guilbeault | T10: Climate; Climate Change; Environment; carbon; carbon emissions; emissions; energy; green; greenhouse gas; renewable energy; transition
A11: 2024-05 | B11: 45422 | C11: Pre-withdrawal | D11: Canada | E11: Global North | F11: North America | G11: Ministry of Environment | H11: Press release | I11: canada.ca | J11: Ensuring the safety of Canadians and monitoring severe weather: new state-of-the-art weather radar in Quebec | K11: https://www.canada.ca/en/environment-climate-change/news/2024/05/ensuring-the-safety-of-canadians-and-monitoring-severe-weather-new-state-of-the-art-weather-radar-in-quebec.html | L11: Climate; Climate Change; Environment; Steven Guilbeault | M11: Yes | N11: 4 | O11: Canada | P11: page metadata | Q11: live | R11: 744 | S11: Steven Guilbeault | T11: Climate; Climate Change; Environment
A12: 2024-05 | B12: 45422 | C12: Pre-withdrawal | D12: Canada | E12: Global North | F12: North America | G12: Ministry of Environment | H12: Press release | I12: canada.ca | J12: Government of Canada releases report on national efforts toward Boreal Caribou recovery | K12: https://www.canada.ca/en/environment-climate-change/news/2024/05/government-of-canada-releases-report-on-national-efforts-toward-boreal-caribou-recovery.html | L12: Climate; Climate Change; Environment; Steven Guilbeault | M12: Yes | N12: 4 | O12: Canada | P12: page metadata | Q12: live | R12: 738 | S12: Steven Guilbeault | T12: Climate; Climate Change; Environment
A13: 2024-05 | B13: 45422 | C13: Pre-withdrawal | D13: Canada | E13: Global North | F13: North America | G13: Ministry of Environment | H13: Press release | I13: canada.ca | J13: Governments of Canada and British Columbia to make a key announcement to lower home heating and cooling bills across the province | K13: https://www.canada.ca/en/environment-climate-change/news/2024/05/governments-of-canada-and-british-columbia-to-make-a-key-announcement-to-lower-home-heating-and-cooling-bills-across-the-province.html | L13: Climate; Climate Change; Environment; Steven Guilbeault; carbon; energy | M13: Yes | N13: 6 | O13: Canada | P13: page metadata | Q13: live | R13: 243 | S13: Steven Guilbeault | T13: Climate; Climate Change; Environment; carbon; energy
A14: 2024-05 | B14: 45422 | C14: Pre-withdrawal | D14: Canada | E14: Global North | F14: North America | G14: Ministry of Environment | H14: Joint / ministerial statement | I14: canada.ca | J14: Minister Guilbeault’s statement on World Migratory Bird Day | K14: https://www.canada.ca/en/environment-climate-change/news/2024/05/minister-guilbeaults-statement-on-world-migratory-bird-day.html | L14: Climate; Climate Change; Environment; Steven Guilbeault | M14: Yes | N14: 4 | O14: Canada | P14: page metadata | Q14: live | R14: 474 | S14: Steven Guilbeault | T14: Climate; Climate Change; Environment
A15: 2024-05 | B15: 45425 | C15: Pre-withdrawal | D15: Canada | E15: Global North | F15: North America | G15: Ministry of Environment | H15: Press release | I15: canada.ca | J15: Expanded heat pump program helps British Columbians save on home energy costs | K15: https://www.canada.ca/en/environment-climate-change/news/2024/05/expanded-heat-pump-program-helps-british-columbians-save-on-home-energy-costs.html | L15: Climate; Climate Change; Environment; Steven Guilbeault; carbon; carbon emissions; emissions; energy; fossil fuel; green; greenhouse gas; net zero emissions; transition | M15: Yes | N15: 13 | O15: Canada | P15: page metadata | Q15: live | R15: 1393 | S15: Steven Guilbeault | T15: Climate; Climate Change; Environment; carbon; carbon emissions; emissions; energy; fossil fuel; green; greenhouse gas; net zero emissions; transition
A16: 2024-05 | B16: 45428 | C16: Pre-withdrawal | D16: Canada | E16: Global North | F16: North America | G16: Ministry of Environment | H16: Press release | I16: canada.ca | J16: Federal and Ontario governments agree to significant collaboration on caribou conservation | K16: https://www.canada.ca/en/environment-climate-change/news/2024/05/federal-and-ontario-governments-agree-to-significant-collaboration-on-caribou-conservation.html | L16: Climate; Climate Change; Environment; Steven Guilbeault | M16: Yes | N16: 4 | O16: Canada | P16: page metadata | Q16: live | R16: 1025 | S16: Steven Guilbeault | T16: Climate; Climate Change; Environment
A17: 2024-05 | B17: 45429 | C17: Pre-withdrawal | D17: Canada | E17: Global North | F17: North America | G17: Ministry of Environment | H17: Press release | I17: canada.ca | J17: Minister Guilbeault imposes strict benzene pollution controls in the pursuit of environmental justice for Aamjiwnaang First Nation and Sarnia, Ontario | K17: https://www.canada.ca/en/environment-climate-change/news/2024/05/minister-guilbeault-imposes-strict-benzene-pollution-controls-in-the-pursuit-of-environmental-justice-for-aamjiwnaang-first-nation-and-sarnia-ontario.html | L17: Climate; Climate Change; Environment; Steven Guilbeault; commitments; emissions | M17: Yes | N17: 6 | O17: Canada | P17: page metadata | Q17: live | R17: 1275 | S17: Steven Guilbeault | T17: Climate; Climate Change; Environment; commitments; emissions
A18: 2024-05 | B18: 45433 | C18: Pre-withdrawal | D18: Canada | E18: Global North | F18: North America | G18: Ministry of Environment | H18: Press release | I18: canada.ca | J18: Environment and Climate Change Canada presents the 2024 hurricane season outlook | K18: https://www.canada.ca/en/environment-climate-change/news/2024/05/environment-and-climate-change-canada-presents-the-2024-hurricane-season-outlook.html | L18: Climate; Climate Change; Environment | M18: No | N18: 3 | P18: page metadata | Q18: live | R18: 197 | T18: Climate; Climate Change; Environment
A19: 2024-05 | B19: 45434 | C19: Pre-withdrawal | D19: Canada | E19: Global North | F19: North America | G19: Ministry of Environment | H19: Joint / ministerial statement | I19: canada.ca | J19: International Day for Biological Diversity 2024: Statement from the Honourable Steven Guilbeault, Minister of Environment and Climate Change | K19: https://www.canada.ca/en/environment-climate-change/news/2024/05/international-day-for-biological-diversity-2024-statement-from-the-honourable-steven-guilbeault-minister-of-environment-and-climate-change.html | L19: COP; Climate; Climate Change; Environment; Steven Guilbeault; Transparency; commitments | M19: Yes | N19: 7 | O19: Canada | P19: page metadata | Q19: live | R19: 501 | S19: Steven Guilbeault | T19: Climate; Climate Change; Environment; Transparency; commitments | U19: COP
A20: 2024-05 | B20: 45435 | C20: Pre-withdrawal | D20: Canada | E20: Global North | F20: North America | G20: Ministry of Environment | H20: Press release | I20: canada.ca | J20: Environment and Climate Change Canada’s Canadian Hurricane Centre expects a very active hurricane season | K20: https://www.canada.ca/en/environment-climate-change/news/2024/05/environment-and-climate-change-canadas-canadian-hurricane-centre-expects-a-very-active-hurricane-season.html | L20: Climate; Climate Change; Environment; Steven Guilbeault; Temperature; emissions | M20: Yes | N20: 6 | O20: Canada | P20: page metadata | Q20: live | R20: 1384 | S20: Steven Guilbeault | T20: Climate; Climate Change; Environment; Temperature; emissions
A21: 2024-05 | B21: 45440 | C21: Pre-withdrawal | D21: Canada | E21: Global North | F21: North America | G21: Ministry of Environment | H21: Press release | I21: canada.ca | J21: Protections for the Aamjiwnaang First Nation and Sarnia from benzene emissions officially extended for two years | K21: https://www.canada.ca/en/environment-climate-change/news/2024/05/protections-for-the-aamjiwnaang-first-nation-and-sarnia-from-benzene-emissions-officially-extended-for-two-years.html | L21: Climate; Climate Change; Environment; emissions | M21: Yes | N21: 4 | P21: page metadata | Q21: live | R21: 358 | T21: Climate; Climate Change; Environment; emissions
A22: 2024-05 | B22: 45442 | C22: Pre-withdrawal | D22: Canada | E22: Global North | F22: North America | G22: Ministry of Environment | H22: Press release | I22: canada.ca | J22: Canada releases the Climate Science 2050: National Priorities for Climate Change Science and Knowledge Report | K22: https://www.canada.ca/en/environment-climate-change/news/2024/05/canada-releases-the-climate-science-2050-national-priorities-for-climate-change-science-and-knowledge-report.html | L22: Climate; Climate Change; Climate change mitigation; Environment; Green Economy; Steven Guilbeault; carbon; carbon emissions; emissions; green; net zero emissions | M22: Yes | N22: 11 | O22: Canada | P22: page metadata | Q22: live | R22: 632 | S22: Steven Guilbeault | T22: Climate; Climate Change; Climate change mitigation; Environment; Green Economy; carbon; carbon emissions; emissions; green; net zero emissions
A23: 2024-05 | B23: 45442 | C23: Pre-withdrawal | D23: Canada | E23: Global North | F23: North America | G23: Ministry of Environment | H23: Press release | I23: canada.ca | J23: Minister Guilbeault to make an announcement on wildlife habitat protection and restoration | K23: https://www.canada.ca/en/environment-climate-change/news/2024/05/minister-guilbeault-to-make-an-announcement-on-wildlife-habitat-protection-and-restoration.html | L23: Climate; Climate Change; Environment; Steven Guilbeault | M23: Yes | N23: 4 | O23: Canada | P23: page metadata | Q23: live | R23: 195 | S23: Steven Guilbeault | T23: Climate; Climate Change; Environment
A24: 2024-05 | B24: 45442 | C24: Pre-withdrawal | D24: Canada | E24: Global North | F24: North America | G24: Ministry of Environment | H24: Press release | I24: canada.ca | J24: Ministers Guilbeault and Miller to make a major health science funding announcement in Montreal | K24: https://www.canada.ca/en/environment-climate-change/news/2024/05/ministers-guilbeault-and-miller-to-make-a-major-health-science-funding-announcement-in-montreal.html | L24: Climate; Climate Change; Environment; Steven Guilbeault | M24: Yes | N24: 4 | O24: Canada | P24: page metadata | Q24: live | R24: 232 | S24: Steven Guilbeault | T24: Climate; Climate Change; Environment
A25: 2024-05 | B25: 45443 | C25: Pre-withdrawal | D25: Canada | E25: Global North | F25: North America | G25: Ministry of Environment | H25: Press release | I25: canada.ca | J25: Government of Canada Supports Brain Canada’s Research Programs to Improve Brain Health $80 million over four years would support the advancement of brain research in Canada | K25: https://www.canada.ca/en/environment-climate-change/news/2024/05/government-of-canada-supports-brain-canadas-research-programs-to-improve-brain-health-80-million-over-four-years-would-support-the-advancement-of-b.html | L25: Climate; Climate Change; Environment; Steven Guilbeault | M25: Yes | N25: 4 | O25: Canada | P25: page metadata | Q25: live | R25: 974 | S25: Steven Guilbeault | T25: Climate; Climate Change; Environment
A26: 2024-05 | B26: 45443 | C26: Pre-withdrawal | D26: Canada | E26: Global North | F26: North America | G26: Ministry of Environment | H26: Press release | I26: canada.ca | J26: Protecting a threatened species, the Western Chorus Frog, in Quebec | K26: https://www.canada.ca/en/environment-climate-change/news/2024/05/protecting-a-threatened-species-the-western-chorus-frog-in-quebec.html | L26: Climate; Climate Change; Environment; Steven Guilbeault; carbon | M26: Yes | N26: 5 | O26: Canada | P26: page metadata | Q26: live | R26: 888 | S26: Steven Guilbeault | T26: Climate; Climate Change; Environment; carbon
A27: 2024-05 | B27: 45443 | C27: Pre-withdrawal | D27: Canada | E27: Global North | F27: North America | G27: Ministry of Environment | H27: Press release | I27: canada.ca | J27: The Government of Canada to make an announcement on significant investments to help build Canada’s climate resiliency | K27: https://www.canada.ca/en/environment-climate-change/news/2024/05/the-government-of-canada-to-make-an-announcement-on-significant-investments-to-help-build-canadas-climate-resiliency.html | L27: Climate; Climate Change; Environment; Steven Guilbeault | M27: Yes | N27: 4 | O27: Canada | P27: page metadata | Q27: live | R27: 227 | S27: Steven Guilbeault | T27: Climate; Climate Change; Environment
A28: 2024-05 | B28: 45443 | C28: Pre-withdrawal | D28: Canada | E28: Global North | F28: North America | G28: Ministry of Environment | H28: Policy / regulatory | I28: canada.ca | J28: Twin Rivers Paper Company Inc. fined $250,000 for Fisheries Act offence in New Brunswick | K28: https://www.canada.ca/en/environment-climate-change/news/2024/05/twin-rivers-paper-company-inc-fined-250000-for-fisheries-act-offence-in-new-brunswick.html | L28: Climate; Climate Change; Environment | M28: No | N28: 3 | P28: page metadata | Q28: live | R28: 481 | T28: Climate; Climate Change; Environment

Sheet 2024-06
A1: Month | B1: Date | C1: Period | D1: Country | E1: North/South | F1: Continent | G1: Source Type | H1: Document Type | I1: Site | J1: Title | K1: URL | L1: Matched Keywords | M1: Strong Match | N1: Keyword Count | O1: Minister/Person Country | P1: Date Source | Q1: Fetched Via | R1: Word Count | S1: Event/Person hits | T1: Adjective Indicators hits | U1: Organizations/Alliances hits | V1: Regulatory Bodies hits
A2: 2024-06 | B2: 45446 | C2: Pre-withdrawal | D2: Canada | E2: Global North | F2: North America | G2: Ministry of Environment | H2: Press release | I2: canada.ca | J2: Backgrounder: Update on Federal Climate Change Adaptation Actions | K2: https://www.canada.ca/en/environment-climate-change/news/2024/06/backgrounder-update-on-federal-climate-change-adaptation-actions.html | L2: Climate; Climate Change; Environment; Steven Guilbeault; green | M2: Yes | N2: 5 | O2: Canada | P2: page metadata | Q2: live | R2: 581 | S2: Steven Guilbeault | T2: Climate; Climate Change; Environment; green
A3: 2024-06 | B3: 45446 | C3: Pre-withdrawal | D3: Canada | E3: Global North | F3: North America | G3: Ministry of Environment | H3: Press release | I3: canada.ca | J3: Building stronger, more climate-resilient communities | K3: https://www.canada.ca/en/environment-climate-change/news/2024/06/building-stronger-more-climate-resilient-communities-the-government-of-canada-provides-530-million-to-municipalities-through-the-green-municipal-fu.html | L3: Climate; Climate Change; Environment; Steven Guilbeault; Sustainability; commitments; green | M3: Yes | N3: 7 | O3: Canada | P3: page metadata | Q3: live | R3: 1177 | S3: Steven Guilbeault | T3: Climate; Climate Change; Environment; Sustainability; commitments; green
A4: 2024-06 | B4: 45447 | C4: Pre-withdrawal | D4: Canada | E4: Global North | F4: North America | G4: Ministry of Environment | H4: Press release | I4: canada.ca | J4: Government of Canada extends pilot to support innovative funding opportunities for biodiversity conservation | K4: https://www.canada.ca/en/environment-climate-change/news/2024/06/government-of-canada-extends-pilot-to-support-innovative-funding-opportunities-for-biodiversity-conservation.html | L4: Climate; Climate Change; Environment; Steven Guilbeault; Sustainability; commitments; energy | M4: Yes | N4: 7 | O4: Canada | P4: page metadata | Q4: live | R4: 1248 | S4: Steven Guilbeault | T4: Climate; Climate Change; Environment; Sustainability; commitments; energy
A5: 2024-06 | B5: 45448 | C5: Pre-withdrawal | D5: Canada | E5: Global North | F5: North America | G5: Ministry of Environment | H5: Press release | I5: canada.ca | J5: New public alert makes it easier to understand air quality conditions during wildfire events and year-round | K5: https://www.canada.ca/en/environment-climate-change/news/2024/06/new-public-alert-makes-it-easier-to-understand-air-quality-conditions-during-wildfire-events-and-year-round.html | L5: Climate; Climate Change; Environment; Steven Guilbeault; energy | M5: Yes | N5: 5 | O5: Canada | P5: page metadata | Q5: live | R5: 993 | S5: Steven Guilbeault | T5: Climate; Climate Change; Environment; energy
A6: 2024-06 | B6: 45449 | C6: Pre-withdrawal | D6: Canada | E6: Global North | F6: North America | G6: Ministry of Environment | H6: Press release | I6: canada.ca | J6: Canada expands and improves warning system for coastal flooding | K6: https://www.canada.ca/en/environment-climate-change/news/2024/06/canada-expands-and-improves-warning-system-for-coastal-flooding.html | L6: Climate; Climate Change; Environment; Steven Guilbeault | M6: Yes | N6: 4 | O6: Canada | P6: page metadata | Q6: live | R6: 936 | S6: Steven Guilbeault | T6: Climate; Climate Change; Environment
A7: 2024-06 | B7: 45450 | C7: Pre-withdrawal | D7: Canada | E7: Global North | F7: North America | G7: Ministry of Environment | H7: Press release | I7: canada.ca | J7: The Government of Canada invests over $3.3 million in nine grassroots, community projects to curb greenhouse gas emissions and fight climate change | K7: https://www.canada.ca/en/environment-climate-change/news/2024/06/the-government-of-canada-invests-over-33-million-in-nine-grassroots-community-projects-to-curb-greenhouse-gas-emissions-and-fight-climate-change.html | L7: Climate; Climate Change; Environment; carbon; emissions; energy; green; greenhouse gas | M7: Yes | N7: 8 | P7: page metadata | Q7: live | R7: 699 | T7: Climate; Climate Change; Environment; carbon; emissions; energy; green; greenhouse gas
A8: 2024-06 | B8: 45450 | C8: Pre-withdrawal | D8: Canada | E8: Global North | F8: North America | G8: Ministry of Environment | H8: Press release | I8: canada.ca | J8: The Government of Canada invests over $3.3 million in nine grassroots, community projects to curb greenhouse gas emissions and fight climate change | K8: https://www.canada.ca/en/environment-climate-change/news/2024/06/the-government-of-canada-invests-over-33-million-in-nine-grassroots-community-projects-to-curb-greenhouse-gas-emissions-and-fight-climate-change0.html | L8: Climate; Climate Change; Environment; Steven Guilbeault; carbon; climate goals; emissions; energy; greenhouse gas | M8: Yes | N8: 9 | O8: Canada | P8: page metadata | Q8: live | R8: 644 | S8: Steven Guilbeault | T8: Climate; Climate Change; Environment; carbon; climate goals; emissions; energy; greenhouse gas
A9: 2024-06 | B9: 45453 | C9: Pre-withdrawal | D9: Canada | E9: Global North | F9: North America | G9: Ministry of Environment | H9: Press release | I9: canada.ca | J9: Environment and Climate Change Canada to hold media availability regarding Canada’s summer seasonal weather outlook | K9: https://www.canada.ca/en/environment-climate-change/news/2024/06/environment-and-climate-change-canada-to-hold-media-availability-regarding-canadas-summer-seasonal-weather-outlook.html | L9: Climate; Climate Change; Environment | M9: No | N9: 3 | P9: page metadata | Q9: live | R9: 166 | T9: Climate; Climate Change; Environment
A10: 2024-06 | B10: 45454 | C10: Pre-withdrawal | D10: Canada | E10: Global North | F10: North America | G10: Ministry of Environment | H10: Press release | I10: canada.ca | J10: Environment and Climate Change Canada presents summer seasonal outlook and introduces new heat wave attribution system | K10: https://www.canada.ca/en/environment-climate-change/news/2024/06/environment-and-climate-change-canada-presents-summer-seasonal-outlook-and-introduces-new-heat-wave-attribution-system.html | L10: Climate; Climate Change; Environment; Temperature | M10: Yes | N10: 4 | P10: page metadata | Q10: live | R10: 519 | T10: Climate; Climate Change; Environment; Temperature
A11: 2024-06 | B11: 45455 | C11: Pre-withdrawal | D11: Canada | E11: Global North | F11: North America | G11: Ministry of Environment | H11: Policy / regulatory | I11: canada.ca | J11: Minister Guilbeault to hold a media availability on Canada’s plan for nature | K11: https://www.canada.ca/en/environment-climate-change/news/2024/06/minister-guilbeault-to-hold-a-media-availability-on-canadas-plan-for-nature.html | L11: Climate; Climate Change; Environment; Steven Guilbeault | M11: Yes | N11: 4 | O11: Canada | P11: page metadata | Q11: live | R11: 158 | S11: Steven Guilbeault | T11: Climate; Climate Change; Environment
A12: 2024-06 | B12: 45456 | C12: Pre-withdrawal | D12: Canada | E12: Global North | F12: North America | G12: Ministry of Environment | H12: Press release | I12: canada.ca | J12: 1799334 ALBERTA LTD., carrying on business as OSY RENTALS LTD., fined $60,000 for illegally importing and possessing protected wildlife species | K12: https://www.canada.ca/en/environment-climate-change/news/2024/06/1799334-alberta-ltd-carrying-on-business-as-osy-rentals-ltd-fined-60000-for-illegally-importing-and-possessing-protected-wildlife-species.html | L12: Climate; Climate Change; Environment | M12: No | N12: 3 | P12: page metadata | Q12: live | R12: 710 | T12: Climate; Climate Change; Environment
A13: 2024-06 | B13: 45456 | C13: Pre-withdrawal | D13: Canada | E13: Global North | F13: North America | G13: Ministry of Environment | H13: Policy / regulatory | I13: canada.ca | J13: 2030 Nature Strategy and Nature Accountability Bill | K13: https://www.canada.ca/en/environment-climate-change/news/2024/06/2030-nature-strategy-and-nature-accountability-bill.html | L13: Climate; Climate Change; Environment; Transparency; commitments; transition | M13: Yes | N13: 6 | P13: page metadata | Q13: live | R13: 874 | T13: Climate; Climate Change; Environment; Transparency; commitments; transition
A14: 2024-06 | B14: 45456 | C14: Pre-withdrawal | D14: Canada | E14: Global North | F14: North America | G14: Ministry of Environment | H14: Policy / regulatory | I14: canada.ca | J14: National strategy to protect nature in Canada unveiled alongside bill to ensure accountability | K14: https://www.canada.ca/en/environment-climate-change/news/2024/06/national-strategy-to-protect-nature-in-canada-unveiled-alongside-bill-to-ensure-accountability.html | L14: COP; Climate; Climate Change; Environment; Steven Guilbeault; Transparency; commitments | M14: Yes | N14: 7 | O14: Canada | P14: page metadata | Q14: live | R14: 938 | S14: Steven Guilbeault | T14: Climate; Climate Change; Environment; Transparency; commitments | U14: COP
A15: 2024-06 | B15: 45461 | C15: Pre-withdrawal | D15: Canada | E15: Global North | F15: North America | G15: Ministry of Environment | H15: Press release | I15: canada.ca | J15: Environment and Climate Change Canada and Health Canada to hold media availability on current hot weather conditions | K15: https://www.canada.ca/en/environment-climate-change/news/2024/06/environment-and-climate-change-canada-and-health-canada-to-hold-media-availability-on-current-hot-weather-conditions.html | L15: Climate; Climate Change; Environment | M15: No | N15: 3 | P15: page metadata | Q15: live | R15: 208 | T15: Climate; Climate Change; Environment
A16: 2024-06 | B16: 45461 | C16: Pre-withdrawal | D16: Canada | E16: Global North | F16: North America | G16: Ministry of Environment | H16: Press release | I16: canada.ca | J16: Government of Canada takes action to further phase out mercury-containing lamps | K16: https://www.canada.ca/en/environment-climate-change/news/2024/06/government-of-canada-takes-action-to-further-phase-out-mercury-containing-lamps.html | L16: Climate; Climate Change; Environment; Steven Guilbeault; emissions; greenhouse gas; transition | M16: Yes | N16: 7 | O16: Canada | P16: page metadata | Q16: live | R16: 778 | S16: Steven Guilbeault | T16: Climate; Climate Change; Environment; emissions; greenhouse gas; transition
A17: 2024-06 | B17: 45462 | C17: Pre-withdrawal | D17: Canada | E17: Global North | F17: North America | G17: Ministry of Environment | H17: Press release | I17: canada.ca | J17: Emergency order to protect boreal caribou habitat in Quebec | K17: https://www.canada.ca/en/environment-climate-change/news/2024/06/emergency-order-to-protect-boreal-caribou-habitat-in-quebec.html | L17: Climate; Climate Change; Environment; carbon | M17: Yes | N17: 4 | P17: page metadata | Q17: live | R17: 907 | T17: Climate; Climate Change; Environment; carbon
A18: 2024-06 | B18: 45462 | C18: Pre-withdrawal | D18: Canada | E18: Global North | F18: North America | G18: Ministry of Environment | H18: Press release | I18: canada.ca | J18: Following the Government of Quebec’s failure, the federal government begins consultations on an emergency order to protect caribou | K18: https://www.canada.ca/en/environment-climate-change/news/2024/06/following-the-government-of-quebecs-failure-the-federal-government-begins-consultations-on-an-emergency-order-to-protect-caribou.html | L18: Climate; Climate Change; Environment; Steven Guilbeault; Sustainability | M18: Yes | N18: 5 | O18: Canada | P18: page metadata | Q18: live | R18: 895 | S18: Steven Guilbeault | T18: Climate; Climate Change; Environment; Sustainability
A19: 2024-06 | B19: 45462 | C19: Pre-withdrawal | D19: Canada | E19: Global North | F19: North America | G19: Ministry of Environment | H19: Press release | I19: canada.ca | J19: New Inuvialuit-led conservation area in the Yukon will safeguard wildlife, habitat, and Inuvialuit traditional use | K19: https://www.canada.ca/en/environment-climate-change/news/2024/06/new-inuvialuit-led-conservation-area-in-the-yukon-will-safeguard-wildlife-habitat-and-inuvialuit-traditional-use.html | L19: Climate; Climate Change; Environment; Steven Guilbeault | M19: Yes | N19: 4 | O19: Canada | P19: page metadata | Q19: live | R19: 1716 | S19: Steven Guilbeault | T19: Climate; Climate Change; Environment
A20: 2024-06 | B20: 45463 | C20: Pre-withdrawal | D20: Canada | E20: Global North | F20: North America | G20: Ministry of Environment | H20: Press release | I20: canada.ca | J20: Canada is supporting habitat stewardship projects for Monarchs and pollinators in southern Ontario | K20: https://www.canada.ca/en/environment-climate-change/news/2024/06/canada-is-supporting-habitat-stewardship-projects-for-monarchs-and-pollinators-in-southern-ontario.html | L20: Climate; Climate Change; Environment; Steven Guilbeault | M20: Yes | N20: 4 | O20: Canada | P20: page metadata | Q20: live | R20: 769 | S20: Steven Guilbeault | T20: Climate; Climate Change; Environment
A21: 2024-06 | B21: 45463 | C21: Pre-withdrawal | D21: Canada | E21: Global North | F21: North America | G21: Ministry of Environment | H21: Press release | I21: canada.ca | J21: The Government of Canada names two new leads for the Net-Zero Advisory Body | K21: https://www.canada.ca/en/environment-climate-change/news/2024/06/the-government-of-canada-names-two-new-leads-for-the-net-zero-advisory-body.html | L21: Climate; Climate Change; Environment; Steven Guilbeault; Transparency; carbon; climate goals; emissions; energy; net zero emissions; transition | M21: Yes | N21: 11 | O21: Canada | P21: page metadata | Q21: live | R21: 851 | S21: Steven Guilbeault | T21: Climate; Climate Change; Environment; Transparency; carbon; climate goals; emissions; energy; net zero emissions; transition
A22: 2024-06 | B22: 45464 | C22: Pre-withdrawal | D22: Canada | E22: Global North | F22: North America | G22: Ministry of Environment | H22: Policy / regulatory | I22: canada.ca | J22: Government supports bill toward progress on environmental justice | K22: https://www.canada.ca/en/environment-climate-change/news/2024/06/government-supports-bill-toward-progress-on-environmental-justice.html | L22: Climate; Climate Change; Environment; Steven Guilbeault | M22: Yes | N22: 4 | O22: Canada | P22: page metadata | Q22: live | R22: 973 | S22: Steven Guilbeault | T22: Climate; Climate Change; Environment
A23: 2024-06 | B23: 45469 | C23: Pre-withdrawal | D23: Canada | E23: Global North | F23: North America | G23: Ministry of Environment | H23: Policy / regulatory | I23: canada.ca | J23: Co-chairs’ Summary: Meeting of federal-provincial-territorial Ministers responsible for conservation, wildlife, and biodiversity – Federal-provincial-territorial Ministers commit to implementing the Global Biodiversity Framework in Canada | K23: https://www.canada.ca/en/environment-climate-change/news/2024/06/co-chairs-summary-meeting-of-federal-provincial-territorial-ministers-responsible-for-conservation-wildlife-and-biodiversity--federal-provincial-te.html | L23: COP; Climate; Climate Change; Environment | M23: Yes | N23: 4 | P23: page metadata | Q23: live | R23: 822 | T23: Climate; Climate Change; Environment | U23: COP
A24: 2024-06 | B24: 45469 | C24: Pre-withdrawal | D24: Canada | E24: Global North | F24: North America | G24: Ministry of Environment | H24: Press release | I24: canada.ca | J24: Government of Canada and Manitoba to make an announcement on funding for renewable energy in the province | K24: https://www.canada.ca/en/environment-climate-change/news/2024/06/government-of-canada-and-manitoba-to-make-an-announcement-on-funding-for-renewable-energy-in-the-province.html | L24: Climate; Climate Change; Environment; Steven Guilbeault; energy; renewable energy | M24: Yes | N24: 6 | O24: Canada | P24: page metadata | Q24: live | R24: 240 | S24: Steven Guilbeault | T24: Climate; Climate Change; Environment; energy; renewable energy
A25: 2024-06 | B25: 45469 | C25: Pre-withdrawal | D25: Canada | E25: Global North | F25: North America | G25: Ministry of Environment | H25: Press release | I25: canada.ca | J25: Government of Canada announces funding for Indigenous communities to protect species at risk and their habitats | K25: https://www.canada.ca/en/environment-climate-change/news/2024/06/government-of-canada-announces-funding-for-indigenous-communities-to-protect-species-at-risk-and-their-habitats.html | L25: Climate; Climate Change; Environment; Steven Guilbeault | M25: Yes | N25: 4 | O25: Canada | P25: page metadata | Q25: live | R25: 1091 | S25: Steven Guilbeault | T25: Climate; Climate Change; Environment
A26: 2024-06 | B26: 45469 | C26: Pre-withdrawal | D26: Canada | E26: Global North | F26: North America | G26: Ministry of Environment | H26: Press release | I26: canada.ca | J26: List of 27 Aboriginal Fund for Species at Risk projects 2023–2024 | K26: https://www.canada.ca/en/environment-climate-change/news/2024/06/list-of-27-aboriginal-fund-for-species-at-risk-projects-202320240.html | L26: Environment | M26: No | N26: 1 | P26: page metadata | Q26: live | R26: 1552 | T26: Environment
A27: 2024-06 | B27: 45469 | C27: Pre-withdrawal | D27: Canada | E27: Global North | F27: North America | G27: Ministry of Environment | H27: Press release | I27: canada.ca | J27: Minister Guilbeault to join provincial and territorial environment ministers for meetings on conservation, wildlife, and biodiversity | K27: https://www.canada.ca/en/environment-climate-change/news/2024/06/minister-guilbeault-to-join-provincial-and-territorial-environment-ministers-for-meetings-on-conservation-wildlife-and-biodiversity.html | L27: Climate; Climate Change; Environment; Steven Guilbeault | M27: Yes | N27: 4 | O27: Canada | P27: page metadata | Q27: live | R27: 230 | S27: Steven Guilbeault | T27: Climate; Climate Change; Environment
A28: 2024-06 | B28: 45469 | C28: Pre-withdrawal | D28: Canada | E28: Global North | F28: North America | G28: Ministry of Environment | H28: Press release | I28: canada.ca | J28: UPDATE: Minister Guilbeault to participate at the Great Lakes Sustainable Growth Forum | K28: https://www.canada.ca/en/environment-climate-change/news/2024/06/the-government-of-canada-to-make-an-announcement-on-restoring-healthy-ecosystems-in-canadas-great-lakes.html | L28: Climate; Climate Change; Environment; Steven Guilbeault | M28: Yes | N28: 4 | O28: Canada | P28: page metadata | Q28: live | R28: 157 | S28: Steven Guilbeault | T28: Climate; Climate Change; Environment
A29: 2024-06 | B29: 45470 | C29: Pre-withdrawal | D29: Canada | E29: Global North | F29: North America | G29: Ministry of Environment | H29: Press release | I29: canada.ca | J29: Federal and Manitoba Government teaming up to help farms and other organizations switch to renewable energy | K29: https://www.canada.ca/en/environment-climate-change/news/2024/06/federal-and-manitoba-government-teaming-up-to-help-farms-and-other-organizations-switch-to-renewable-energy.html | L29: Climate; Climate Change; Environment; Steven Guilbeault; Sustainable Economy; carbon; climate goals; commitments; emissions; energy; fossil fuel; green; greenhouse gas; net zero emissions; renewable energy | M29: Yes | N29: 15 | O29: Canada | P29: page metadata | Q29: live | R29: 783 | S29: Steven Guilbeault | T29: Climate; Climate Change; Environment; Sustainable Economy; carbon; climate goals; commitments; emissions; energy; fossil fuel; green; greenhouse gas; net zero emissions; renewable energy
A30: 2024-06 | B30: 45470 | C30: Pre-withdrawal | D30: Canada | E30: Global North | F30: North America | G30: Ministry of Environment | H30: Press release | I30: canada.ca | J30: Manitoba’s Merit-Based Program: 32 projects approved under first round | K30: https://www.canada.ca/en/environment-climate-change/news/2024/06/manitobas-merit-based-program-32-projects-approved-under-first-round.html | L30: carbon; emissions; energy; fossil fuel; greenhouse gas; renewable energy; transition | M30: Yes | N30: 7 | P30: page metadata | Q30: live | R30: 866 | T30: carbon; emissions; energy; fossil fuel; greenhouse gas; renewable energy; transition
A31: 2024-06 | B31: 45471 | C31: Pre-withdrawal | D31: Canada | E31: Global North | F31: North America | G31: Ministry of Environment | H31: Press release | I31: canada.ca | J31: The Government of Canada introduces new measures to regulate methane emissions from Canadian landfills | K31: https://www.canada.ca/en/environment-climate-change/news/2024/06/the-government-of-canada-introduces-new-measures-to-regulate-methane-emissions-from-canadian-landfills.html | L31: Climate; Climate Change; Environment; Steven Guilbeault; Temperature; carbon; emissions; greenhouse gas; net zero emissions | M31: Yes | N31: 9 | O31: Canada | P31: page metadata | Q31: live | R31: 574 | S31: Steven Guilbeault | T31: Climate; Climate Change; Environment; Temperature; carbon; emissions; greenhouse gas; net zero emissions

Sheet 2024-07
A1: Month | B1: Date | C1: Period | D1: Country | E1: North/South | F1: Continent | G1: Source Type | H1: Document Type | I1: Site | J1: Title | K1: URL | L1: Matched Keywords | M1: Strong Match | N1: Keyword Count | O1: Minister/Person Country | P1: Date Source | Q1: Fetched Via | R1: Word Count | S1: Event/Person hits | T1: Adjective Indicators hits | U1: Organizations/Alliances hits | V1: Regulatory Bodies hits
A2: 2024-07 | B2: 45477 | C2: Pre-withdrawal | D2: Canada | E2: Global North | F2: North America | G2: Ministry of Environment | H2: Speech / remarks | I2: canada.ca | J2: The Government of Canada is taking steps to address plastic waste and pollution from the textile and apparel sector | K2: https://www.canada.ca/en/environment-climate-change/news/2024/07/the-government-of-canada-is-taking-steps-to-address-plastic-waste-and-pollution-from-the-textile-and-apparel-sector.html | L2: Circular; Circular Economy; Climate; Climate Change; Environment; Steven Guilbeault; energy | M2: Yes | N2: 7 | O2: Canada | P2: page metadata | Q2: live | R2: 630 | S2: Steven Guilbeault | T2: Circular; Circular Economy; Climate; Climate Change; Environment; energy
A3: 2024-07 | B3: 45478 | C3: Pre-withdrawal | D3: Canada | E3: Global North | F3: North America | G3: Ministry of Environment | H3: Press release | I3: canada.ca | J3: Environment and Climate Change Canada to hold media availability on current hot weather conditions in Western Canada | K3: https://www.canada.ca/en/environment-climate-change/news/2024/07/environment-and-climate-change-canada-to-hold-media-availability-on-current-hot-weather-conditions-in-western-canada.html | L3: Climate; Climate Change; Environment | M3: No | N3: 3 | P3: page metadata | Q3: live | R3: 210 | T3: Climate; Climate Change; Environment
A4: 2024-07 | B4: 45478 | C4: Pre-withdrawal | D4: Canada | E4: Global North | F4: North America | G4: Ministry of Environment | H4: Press release | I4: canada.ca | J4: Governments of Canada and Newfoundland and Labrador announce new priority place to conserve species at risk | K4: https://www.canada.ca/en/environment-climate-change/news/2024/07/governments-of-canada-and-newfoundland-and-labrador-announce-new-priority-place-to-conserve-species-at-risk.html | L4: Climate; Climate Change; Environment; Steven Guilbeault | M4: Yes | N4: 4 | O4: Canada | P4: page metadata | Q4: live | R4: 870 | S4: Steven Guilbeault | T4: Climate; Climate Change; Environment
A5: 2024-07 | B5: 45481 | C5: Pre-withdrawal | D5: Canada | E5: Global North | F5: North America | G5: Ministry of Environment | H5: Press release | I5: canada.ca | J5: A Quebec company was fined $12,500 for destroying nests of Bank Swallows, a threatened species | K5: https://www.canada.ca/en/environment-climate-change/news/2024/07/a-quebec-company-was-fined-12500-for-destroying-nests-of-bank-swallows-a-threatened-species.html | L5: Climate; Climate Change; Environment | M5: No | N5: 3 | P5: page metadata | Q5: live | R5: 471 | T5: Climate; Climate Change; Environment
A6: 2024-07 | B6: 45481 | C6: Pre-withdrawal | D6: Canada | E6: Global North | F6: North America | G6: Ministry of Environment | H6: Press release | I6: canada.ca | J6: Environment and Climate Change Canada to hold media availability on results from Rapid Extreme Weather Event Attribution system | K6: https://www.canada.ca/en/environment-climate-change/news/2024/07/environment-and-climate-change-canada-to-hold-media-availability-on-results-from-rapid-extreme-weather-event-attribution-system.html | L6: Climate; Climate Change; Environment | M6: No | N6: 3 | P6: page metadata | Q6: live | R6: 284 | T6: Climate; Climate Change; Environment
A7: 2024-07 | B7: 45482 | C7: Pre-withdrawal | D7: Canada | E7: Global North | F7: North America | G7: Ministry of Environment | H7: Press release | I7: canada.ca | J7: Canada releases first results from rapid extreme weather event attribution system | K7: https://www.canada.ca/en/environment-climate-change/news/2024/07/canada-releases-first-results-from-rapid-extreme-weather-event-attribution-system.html | L7: Climate; Climate Change; Environment; Temperature; emissions; greenhouse gas | M7: Yes | N7: 6 | P7: page metadata | Q7: live | R7: 582 | T7: Climate; Climate Change; Environment; Temperature; emissions; greenhouse gas
A8: 2024-07 | B8: 45483 | C8: Pre-withdrawal | D8: Canada | E8: Global North | F8: North America | G8: Ministry of Environment | H8: Press release | I8: canada.ca | J8: The Government of Canada to make a health announcement | K8: https://www.canada.ca/en/environment-climate-change/news/2024/07/the-government-of-canada-to-make-a-health-announcement.html | L8: Climate; Climate Change; Environment; Steven Guilbeault | M8: Yes | N8: 4 | O8: Canada | P8: page metadata | Q8: live | R8: 161 | S8: Steven Guilbeault | T8: Climate; Climate Change; Environment
A9: 2024-07 | B9: 45484 | C9: Pre-withdrawal | D9: Canada | E9: Global North | F9: North America | G9: Ministry of Environment | H9: Policy / regulatory | I9: canada.ca | J9: Environment and Climate Change Canada Enforcement lays 5 charges for contraventions of subsection 36(3) of the Fisheries Act | K9: https://www.canada.ca/en/environment-climate-change/news/2024/07/environment-and-climate-change-canada-enforcement-lays-5-charges-for-contraventions-of-subsection-363-of-the-fisheries-act.html | L9: Climate; Climate Change; Environment | M9: No | N9: 3 | P9: page metadata | Q9: live | R9: 426 | T9: Climate; Climate Change; Environment
A10: 2024-07 | B10: 45484 | C10: Pre-withdrawal | D10: Canada | E10: Global North | F10: North America | G10: Ministry of Environment | H10: Press release | I10: canada.ca | J10: Supporting Canada’s health workers by improving health workforce research, planning and data | K10: https://www.canada.ca/en/environment-climate-change/news/2024/07/supporting-canadas-health-workers-by-improving-health-workforce-research-planning-and-data.html | L10: Climate; Climate Change; Environment; Steven Guilbeault; transition | M10: Yes | N10: 5 | O10: Canada | P10: page metadata | Q10: live | R10: 1354 | S10: Steven Guilbeault | T10: Climate; Climate Change; Environment; transition
A11: 2024-07 | B11: 45485 | C11: Pre-withdrawal | D11: Canada | E11: Global North | F11: North America | G11: Ministry of Environment | H11: Press release | I11: canada.ca | J11: How Canada’s pollution pricing system works | K11: https://www.canada.ca/en/environment-climate-change/news/2024/07/how-canadas-pollution-pricing-system-works.html | L11: Climate; Climate Change; Environment; carbon; emissions; energy; fossil fuel; greenhouse gas; transition | M11: Yes | N11: 9 | P11: page metadata | Q11: live | R11: 1956 | T11: Climate; Climate Change; Environment; carbon; emissions; energy; fossil fuel; greenhouse gas; transition
A12: 2024-07 | B12: 45485 | C12: Pre-withdrawal | D12: Canada | E12: Global North | F12: North America | G12: Ministry of Environment | H12: Press release | I12: canada.ca | J12: Minister Guilbeault in London, Ontario, to highlight Canada Carbon Rebates for Canadians and small businesses, clean re-investment into Ontario industry | K12: https://www.canada.ca/en/environment-climate-change/news/2024/07/minister-guilbeault-in-london-ontario-to-highlight-canada-carbon-rebates-for-canadians-and-small-businesses-clean-re-investment-into-ontario-industry.html | L12: Climate; Climate Change; Environment; Steven Guilbeault; carbon; energy | M12: Yes | N12: 6 | O12: Canada | P12: page metadata | Q12: live | R12: 279 | S12: Steven Guilbeault | T12: Climate; Climate Change; Environment; carbon; energy
A13: 2024-07 | B13: 45488 | C13: Pre-withdrawal | D13: Canada | E13: Global North | F13: North America | G13: Ministry of Environment | H13: Press release | I13: canada.ca | J13: Government of Canada publishes updated Draft State of Per- and Polyfluoroalkyl Substances (PFAS) Report and revised Risk Management Scope | K13: https://www.canada.ca/en/environment-climate-change/news/2024/07/government-of-canada-publishes-updated-draft-state-of-per--and-polyfluoroalkyl-substances-pfas-report-and-revised-risk-management-scope.html | L13: Environment; carbon | M13: No | N13: 2 | P13: page metadata | Q13: live | R13: 1014 | T13: Environment; carbon
A14: 2024-07 | B14: 45488 | C14: Pre-withdrawal | D14: Canada | E14: Global North | F14: North America | G14: Ministry of Environment | H14: Press release | I14: canada.ca | J14: Government of Canada updates efforts to protect the environment and communities by addressing “forever chemicals” | K14: https://www.canada.ca/en/environment-climate-change/news/2024/07/government-of-canada-updates-efforts-to-protect-the-environment-and-communities-by-addressing-forever-chemicals.html | L14: Climate; Climate Change; Environment; Steven Guilbeault | M14: Yes | N14: 4 | O14: Canada | P14: page metadata | Q14: live | R14: 1393 | S14: Steven Guilbeault | T14: Climate; Climate Change; Environment
A15: 2024-07 | B15: 45488 | C15: Pre-withdrawal | D15: Canada | E15: Global North | F15: North America | G15: Ministry of Environment | H15: Press release | I15: canada.ca | J15: Pollution pricing at work: re-investing $2.2 million into new low-carbon cement in Ontario | K15: https://www.canada.ca/en/environment-climate-change/news/2024/07/pollution-pricing-at-work-re-investing-22-million-into-new-low-carbon-cement-in-ontario.html | L15: Circular; Circular Economy; Climate; Climate Change; Environment; Steven Guilbeault; Sustainable Economy; carbon; emissions; energy; greenhouse gas; net zero emissions; renewable energy; transition | M15: Yes | N15: 14 | O15: Canada | P15: page metadata | Q15: live | R15: 919 | S15: Steven Guilbeault | T15: Circular; Circular Economy; Climate; Climate Change; Environment; Sustainable Economy; carbon; emissions; energy; greenhouse gas; net zero emissions; renewable energy; transition
A16: 2024-07 | B16: 45488 | C16: Pre-withdrawal | D16: Canada | E16: Global North | F16: North America | G16: Ministry of Environment | H16: Press release | I16: canada.ca | J16: Supporting Canadians and fighting climate change with July Canada Carbon Rebate and small business tax credit | K16: https://www.canada.ca/en/environment-climate-change/news/2024/07/supporting-canadians-and-fighting-climate-change-with-july-canada-carbon-rebate-and-small-business-tax-credit.html | L16: Climate; Climate Change; Environment; Steven Guilbeault; carbon; emissions; energy | M16: Yes | N16: 7 | O16: Canada | P16: page metadata | Q16: live | R16: 928 | S16: Steven Guilbeault | T16: Climate; Climate Change; Environment; carbon; emissions; energy
A17: 2024-07 | B17: 45489 | C17: Pre-withdrawal | D17: Canada | E17: Global North | F17: North America | G17: Ministry of Environment | H17: Press release | I17: canada.ca | J17: The Government of Canada to make an announcement supporting clean and affordable homes | K17: https://www.canada.ca/en/environment-climate-change/news/2024/07/the-government-of-canada-to-make-an-announcement-supporting-clean-and-affordable-homes.html | L17: Climate; Climate Change; Environment; Steven Guilbeault; energy | M17: Yes | N17: 5 | O17: Canada | P17: page metadata | Q17: live | R17: 154 | S17: Steven Guilbeault | T17: Climate; Climate Change; Environment; energy
A18: 2024-07 | B18: 45490 | C18: Pre-withdrawal | D18: Canada | E18: Global North | F18: North America | G18: Ministry of Environment | H18: Policy / regulatory | I18: canada.ca | J18: Helping Quebec residents save money on their energy bills: introducing the Canada Green Buildings Strategy | K18: https://www.canada.ca/en/environment-climate-change/news/2024/07/helping-quebec-residents-save-money-on-their-energy-bills-introducing-the-canada-green-buildings-strategy.html | L18: Climate; Climate Change; Environment; Steven Guilbeault; Sustainable Economy; carbon; climate goals; commitments; emissions; energy; fossil fuel; green; greenhouse gas; net zero emissions; transition | M18: Yes | N18: 15 | O18: Canada | P18: page metadata | Q18: live | R18: 1717 | S18: Steven Guilbeault | T18: Climate; Climate Change; Environment; Sustainable Economy; carbon; climate goals; commitments; emissions; energy; fossil fuel; green; greenhouse gas; net zero emissions; transition
A19: 2024-07 | B19: 45490 | C19: Pre-withdrawal | D19: Canada | E19: Global North | F19: North America | G19: Ministry of Environment | H19: Press release | I19: canada.ca | J19: The Government of Canada to make an announcement in British Columbia supporting the protection of nature to fight climate change | K19: https://www.canada.ca/en/environment-climate-change/news/2024/07/the-government-of-canada-to-make-an-announcement-in-british-columbia-supporting-the-protection-of-nature-to-fight-climate-change.html | L19: Climate; Climate Change; Environment; Steven Guilbeault | M19: Yes | N19: 4 | O19: Canada | P19: page metadata | Q19: live | R19: 174 | S19: Steven Guilbeault | T19: Climate; Climate Change; Environment
A20: 2024-07 | B20: 45490 | C20: Pre-withdrawal | D20: Canada | E20: Global North | F20: North America | G20: Ministry of Environment | H20: Press release | I20: canada.ca | J20: The Government of Canada to make an announcement in Manitoba supporting the protection of nature to fight climate change | K20: https://www.canada.ca/en/environment-climate-change/news/2024/07/the-government-of-canada-to-make-an-announcement-in-manitoba-supporting-the-protection-of-nature-to-fight-climate-change.html | L20: Climate; Climate Change; Environment; Steven Guilbeault | M20: Yes | N20: 4 | O20: Canada | P20: page metadata | Q20: live | R20: 192 | S20: Steven Guilbeault | T20: Climate; Climate Change; Environment
A21: 2024-07 | B21: 45491 | C21: Pre-withdrawal | D21: Canada | E21: Global North | F21: North America | G21: Ministry of Environment | H21: Press release | I21: canada.ca | J21: Protecting nature in British Columbia and across Canada to help fight climate change and protect biodiversity | K21: https://www.canada.ca/en/environment-climate-change/news/2024/07/protecting-nature-in-british-columbia-and-across-canada-to-help-fight-climate-change-and-protect-biodiversity.html | L21: Climate; Climate Change; Environment; Steven Guilbeault; carbon; climate goals; commitments; emissions; greenhouse gas | M21: Yes | N21: 9 | O21: Canada | P21: page metadata | Q21: live | R21: 1530 | S21: Steven Guilbeault | T21: Climate; Climate Change; Environment; carbon; climate goals; commitments; emissions; greenhouse gas
A22: 2024-07 | B22: 45491 | C22: Pre-withdrawal | D22: Canada | E22: Global North | F22: North America | G22: Ministry of Environment | H22: Press release | I22: canada.ca | J22: Protecting nature in Manitoba to help fight climate change and protect biodiversity | K22: https://www.canada.ca/en/environment-climate-change/news/2024/07/protecting-nature-in-manitoba-to-help-fight-climate-change-and-protect-biodiversity.html | L22: Climate; Climate Change; Environment; Steven Guilbeault; carbon; climate goals; emissions; greenhouse gas | M22: Yes | N22: 8 | O22: Canada | P22: page metadata | Q22: live | R22: 1157 | S22: Steven Guilbeault | T22: Climate; Climate Change; Environment; carbon; climate goals; emissions; greenhouse gas
A23: 2024-07 | B23: 45491 | C23: Pre-withdrawal | D23: Canada | E23: Global North | F23: North America | G23: Ministry of Environment | H23: Press release | I23: canada.ca | J23: The Government of Canada invests in nature-based solutions to help fight climate change and protect biodiversity across the country | K23: https://www.canada.ca/en/environment-climate-change/news/2024/07/the-government-of-canada-invests-in-nature-based-solutions-to-help-fight-climate-change-and-protect-biodiversity-across-the-country.html | L23: Climate; Climate Change; Environment; Steven Guilbeault; carbon; emissions; greenhouse gas | M23: Yes | N23: 7 | O23: Canada | P23: page metadata | Q23: live | R23: 892 | S23: Steven Guilbeault | T23: Climate; Climate Change; Environment; carbon; emissions; greenhouse gas
A24: 2024-07 | B24: 45491 | C24: Pre-withdrawal | D24: Canada | E24: Global North | F24: North America | G24: Ministry of Environment | H24: Press release | I24: canada.ca | J24: The Government of Canada to make an announcement on the Canada Child Benefit | K24: https://www.canada.ca/en/environment-climate-change/news/2024/07/the-government-of-canada-to-make-an-announcement-on-the-canada-child-benefit.html | L24: Climate; Climate Change; Environment; Steven Guilbeault | M24: Yes | N24: 4 | O24: Canada | P24: page metadata | Q24: live | R24: 165 | S24: Steven Guilbeault | T24: Climate; Climate Change; Environment
A25: 2024-07 | B25: 45492 | C25: Pre-withdrawal | D25: Canada | E25: Global North | F25: North America | G25: Ministry of Environment | H25: Press release | I25: canada.ca | J25: Canada Child Benefit increases again to keep up with the cost of living | K25: https://www.canada.ca/en/environment-climate-change/news/2024/07/canada-child-benefit-increases-again-to-keep-up-with-the-cost-of-living.html | L25: Climate; Climate Change; Environment; Steven Guilbeault | M25: Yes | N25: 4 | O25: Canada | P25: page metadata | Q25: live | R25: 1031 | S25: Steven Guilbeault | T25: Climate; Climate Change; Environment
A26: 2024-07 | B26: 45495 | C26: Pre-withdrawal | D26: Canada | E26: Global North | F26: North America | G26: Ministry of Environment | H26: Press release | I26: canada.ca | J26: Canadian National Railway Company fined $8 million for environmental offences in relation to two 2015 train derailments | K26: https://www.canada.ca/en/environment-climate-change/news/2024/07/canadian-national-railway-company-fined-8-million-for-environmental-offences-in-relation-to-two-2015-train-derailments.html | L26: Climate; Climate Change; Environment | M26: No | N26: 3 | P26: page metadata | Q26: live | R26: 632 | T26: Climate; Climate Change; Environment
A27: 2024-07 | B27: 45502 | C27: Pre-withdrawal | D27: Canada | E27: Global North | F27: North America | G27: Ministry of Environment | H27: Press release | I27: canada.ca | J27: The Government of Canada to announce an investment to protect the waters of Lake Winnipeg | K27: https://www.canada.ca/en/environment-climate-change/news/2024/07/the-government-of-canada-to-announce-an-investment-to-protect-the-waters-of-lake-winnipeg.html | L27: Climate; Climate Change; Environment | M27: No | N27: 3 | P27: page metadata | Q27: live | R27: 162 | T27: Climate; Climate Change; Environment
A28: 2024-07 | B28: 45503 | C28: Pre-withdrawal | D28: Canada | E28: Global North | F28: North America | G28: Ministry of Environment | H28: Press release | I28: canada.ca | J28: Canada invests in 17 new projects to help protect Lake Winnipeg | K28: https://www.canada.ca/en/environment-climate-change/news/2024/07/canada-invests-in-17-new-projects-to-help-protect-lake-winnipeg.html | L28: Climate; Climate Change; Environment; Steven Guilbeault | M28: Yes | N28: 4 | O28: Canada | P28: page metadata | Q28: live | R28: 706 | S28: Steven Guilbeault | T28: Climate; Climate Change; Environment

Sheet 2024-08
A1: Month | B1: Date | C1: Period | D1: Country | E1: North/South | F1: Continent | G1: Source Type | H1: Document Type | I1: Site | J1: Title | K1: URL | L1: Matched Keywords | M1: Strong Match | N1: Keyword Count | O1: Minister/Person Country | P1: Date Source | Q1: Fetched Via | R1: Word Count | S1: Event/Person hits | T1: Adjective Indicators hits | U1: Organizations/Alliances hits | V1: Regulatory Bodies hits
A2: 2024-08 | B2: 45506 | C2: Pre-withdrawal | D2: Canada | E2: Global North | F2: North America | G2: Ministry of Environment | H2: Press release | I2: canada.ca | J2: Bos Smoked Fish Inc. ordered to pay a $25,000 fine for illegally importing protected European Eel meat | K2: https://www.canada.ca/en/environment-climate-change/news/2024/08/bos-smoked-fish-inc-ordered-to-pay-a-25000-fine-for-illegally-importing-protected-european-eel-meat.html | L2: Climate; Climate Change; Environment; International Union for Conservation of Nature | M2: Yes | N2: 4 | P2: page metadata | Q2: live | R2: 662 | T2: Climate; Climate Change; Environment | U2: International Union for Conservation of Nature
A3: 2024-08 | B3: 45510 | C3: Pre-withdrawal | D3: Canada | E3: Global North | F3: North America | G3: Ministry of Environment | H3: Policy / regulatory | I3: canada.ca | J3: Federal government extends consultation period for emergency order to protect caribou | K3: https://www.canada.ca/en/environment-climate-change/news/2024/08/federal-government-extends-consultation-period-for-emergency-order-to-protect-caribou.html | L3: Climate; Climate Change; Environment; Steven Guilbeault | M3: Yes | N3: 4 | O3: Canada | P3: page metadata | Q3: live | R3: 248 | S3: Steven Guilbeault | T3: Climate; Climate Change; Environment
A4: 2024-08 | B4: 45510 | C4: Pre-withdrawal | D4: Canada | E4: Global North | F4: North America | G4: Ministry of Environment | H4: Press release | I4: canada.ca | J4: The Government of Canada to make a funding announcement to increase conserved areas in southern Ontario | K4: https://www.canada.ca/en/environment-climate-change/news/2024/08/the-government-of-canada-to-make-a-funding-announcement-to-increase-conserved-areas-in-southern-ontario.html | L4: Climate; Climate Change; Environment; Julie Dabrusin; energy | M4: Yes | N4: 5 | O4: Canada | P4: page metadata | Q4: live | R4: 222 | S4: Julie Dabrusin | T4: Climate; Climate Change; Environment; energy
A5: 2024-08 | B5: 45511 | C5: Pre-withdrawal | D5: Canada | E5: Global North | F5: North America | G5: Ministry of Environment | H5: Press release | I5: canada.ca | J5: Canada invests over $12.5 million to increase conserved areas primarily in southern Ontario | K5: https://www.canada.ca/en/environment-climate-change/news/2024/08/canada-invests-over-125-million-to-increase-conserved-areas-primarily-in-southern-ontario.html | L5: Climate; Climate Change; Environment; Julie Dabrusin; Steven Guilbeault; Sustainability; energy | M5: Yes | N5: 7 | O5: Canada | P5: page metadata | Q5: live | R5: 783 | S5: Julie Dabrusin; Steven Guilbeault | T5: Climate; Climate Change; Environment; Sustainability; energy
A6: 2024-08 | B6: 45511 | C6: Pre-withdrawal | D6: Canada | E6: Global North | F6: North America | G6: Ministry of Environment | H6: Press release | I6: canada.ca | J6: Environment and Climate Change Canada to hold media availability on upcoming potential heavy rainfall for parts of Eastern Canada | K6: https://www.canada.ca/en/environment-climate-change/news/2024/08/environment-and-climate-change-canada-to-hold-media-availability-on-upcoming-potential-heavy-rainfall-for-parts-of-eastern-canada.html | L6: Climate; Climate Change; Environment | M6: No | N6: 3 | P6: page metadata | Q6: live | R6: 247 | T6: Climate; Climate Change; Environment
A7: 2024-08 | B7: 45511 | C7: Pre-withdrawal | D7: Canada | E7: Global North | F7: North America | G7: Ministry of Environment | H7: Press release | I7: canada.ca | J7: Federal Government announces support for community-led health study in Athabasca oil sands region | K7: https://www.canada.ca/en/environment-climate-change/news/2024/08/federal-government-announces-support-for-community-led-health-study-in-athabasca-oil-sands-region.html | L7: Climate; Climate Change; Environment; Steven Guilbeault; commitments | M7: Yes | N7: 5 | O7: Canada | P7: page metadata | Q7: live | R7: 904 | S7: Steven Guilbeault | T7: Climate; Climate Change; Environment; commitments
A8: 2024-08 | B8: 45512 | C8: Pre-withdrawal | D8: Canada | E8: Global North | F8: North America | G8: Ministry of Environment | H8: Press release | I8: canada.ca | J8: First Nations and the Government of Canada continue to strengthen partnership on climate action | K8: https://www.canada.ca/en/environment-climate-change/news/2024/08/first-nations-and-the-government-of-canada-continue-to-strengthen-partnership-on-climate-action.html | L8: Climate; Climate Change; Environment; Steven Guilbeault; Transparency; energy; transition | M8: Yes | N8: 7 | O8: Canada | P8: page metadata | Q8: live | R8: 1099 | S8: Steven Guilbeault | T8: Climate; Climate Change; Environment; Transparency; energy; transition
A9: 2024-08 | B9: 45516 | C9: Pre-withdrawal | D9: Canada | E9: Global North | F9: North America | G9: Ministry of Environment | H9: Press release | I9: canada.ca | J9: Science shows climate change made summer heat waves much more likely | K9: https://www.canada.ca/en/environment-climate-change/news/2024/08/science-shows-climate-change-made-summer-heat-waves-much-more-likely.html | L9: Climate; Climate Change; Environment; Temperature; emissions; greenhouse gas | M9: Yes | N9: 6 | P9: page metadata | Q9: live | R9: 606 | T9: Climate; Climate Change; Environment; Temperature; emissions; greenhouse gas
A10: 2024-08 | B10: 45516 | C10: Pre-withdrawal | D10: Canada | E10: Global North | F10: North America | G10: Ministry of Environment | H10: Press release | I10: canada.ca | J10: The Government of Canada to make an announcement on funding for training skilled workers to install heat pumps and offer facility tour | K10: https://www.canada.ca/en/environment-climate-change/news/2024/08/the-government-of-canada-to-make-an-announcement-on-funding-for-training-skilled-workers-to-install-heat-pumps-and-offer-facility-tour.html | L10: Climate; Climate Change; Environment; Julie Dabrusin; Steven Guilbeault | M10: Yes | N10: 5 | O10: Canada | P10: page metadata | Q10: live | R10: 200 | S10: Julie Dabrusin; Steven Guilbeault | T10: Climate; Climate Change; Environment
A11: 2024-08 | B11: 45517 | C11: Pre-withdrawal | D11: Canada | E11: Global North | F11: North America | G11: Ministry of Environment | H11: Press release | I11: canada.ca | J11: Government of Canada invests in heat pump training for skilled workers in a cleaner economy across the country | K11: https://www.canada.ca/en/environment-climate-change/news/2024/08/government-of-canada-invests-in-heat-pump-training-for-skilled-workers-in-a-cleaner-economy-across-the-country.html | L11: Climate; Climate Change; Environment; Julie Dabrusin; Steven Guilbeault; Sustainable Economy; carbon; emissions; energy; green; greenhouse gas; transition | M11: Yes | N11: 12 | O11: Canada | P11: page metadata | Q11: live | R11: 1259 | S11: Julie Dabrusin; Steven Guilbeault | T11: Climate; Climate Change; Environment; Sustainable Economy; carbon; emissions; energy; green; greenhouse gas; transition
A12: 2024-08 | B12: 45520 | C12: Pre-withdrawal | D12: Canada | E12: Global North | F12: North America | G12: Ministry of Environment | H12: Press release | I12: canada.ca | J12: 2253457 Ontario Inc. fined $100,000 for unlawful deposit of diesel fuel in Etobicoke Creek | K12: https://www.canada.ca/en/environment-climate-change/news/2024/08/2253457-ontario-inc-fined-100000-for-unlawful-deposit-of-diesel-fuel-in-etobicoke-creek.html | L12: Climate; Climate Change; Environment | M12: No | N12: 3 | P12: page metadata | Q12: live | R12: 556 | T12: Climate; Climate Change; Environment
A13: 2024-08 | B13: 45520 | C13: Pre-withdrawal | D13: Canada | E13: Global North | F13: North America | G13: Ministry of Environment | H13: Press release | I13: canada.ca | J13: Environment and Climate Change Canada to hold media availability on expected meteorological impacts of Hurricane Ernesto | K13: https://www.canada.ca/en/environment-climate-change/news/2024/08/environment-and-climate-change-canada-to-hold-media-availability-on-expected-meteorological-impacts-of-hurricane-ernesto.html | L13: Climate; Climate Change; Environment | M13: No | N13: 3 | P13: page metadata | Q13: live | R13: 183 | T13: Climate; Climate Change; Environment
A14: 2024-08 | B14: 45523 | C14: Pre-withdrawal | D14: Canada | E14: Global North | F14: North America | G14: Ministry of Environment | H14: Press release | I14: canada.ca | J14: Preparing for the UN’s next nature conference: Minister Guilbeault and Minister Muhamad from Colombia to provide update ahead of COP16 | K14: https://www.canada.ca/en/environment-climate-change/news/2024/08/preparing-for-the-uns-next-nature-conference-minister-guilbeault-and-minister-muhamad-from-colombia-to-provide-update-ahead-of-cop16.html | L14: COP; Climate; Climate Change; Environment; Steven Guilbeault | M14: Yes | N14: 5 | O14: Canada | P14: page metadata | Q14: live | R14: 252 | S14: Steven Guilbeault | T14: Climate; Climate Change; Environment | U14: COP
A15: 2024-08 | B15: 45525 | C15: Pre-withdrawal | D15: Canada | E15: Global North | F15: North America | G15: Ministry of Environment | H15: Press release | I15: canada.ca | J15: Canadian and Colombian Environment Ministers Meet to Share International Leadership Ambition on Nature and Biodiversity | K15: https://www.canada.ca/en/environment-climate-change/news/2024/08/canadian-and-colombian-environment-ministers-meet-to-share-international-leadership-ambition-on-nature-and-biodiversity.html | L15: COP; Climate; Climate Change; Environment; Steven Guilbeault; Transparency; commitments | M15: Yes | N15: 7 | O15: Canada | P15: page metadata | Q15: live | R15: 1062 | S15: Steven Guilbeault | T15: Climate; Climate Change; Environment; Transparency; commitments | U15: COP
A16: 2024-08 | B16: 45525 | C16: Pre-withdrawal | D16: Canada | E16: Global North | F16: North America | G16: Ministry of Environment | H16: Press release | I16: canada.ca | J16: Minister Guilbeault to announce support for expansion of biosphere conservation areas in Quebec, including Mont-Saint-Hilaire, and across Canada | K16: https://www.canada.ca/en/environment-climate-change/news/2024/08/minister-guilbeault-to-announce-support-for-expansion-of-biosphere-conservation-areas-in-quebec-including-mont-saint-hilaire-and-across-canada.html | L16: Climate; Climate Change; Environment; Steven Guilbeault | M16: Yes | N16: 4 | O16: Canada | P16: page metadata | Q16: live | R16: 158 | S16: Steven Guilbeault | T16: Climate; Climate Change; Environment
A17: 2024-08 | B17: 45526 | C17: Pre-withdrawal | D17: Canada | E17: Global North | F17: North America | G17: Ministry of Environment | H17: Press release | I17: canada.ca | J17: Canada invests over $11.7 million to increase biodiversity conservation in biosphere regions in Quebec and across Canada | K17: https://www.canada.ca/en/environment-climate-change/news/2024/08/canada-invests-over-117-million-to-increase-biodiversity-conservation-in-biosphere-regions-in-quebec-and-across-canada.html | L17: Climate; Climate Change; Environment; Steven Guilbeault | M17: Yes | N17: 4 | O17: Canada | P17: page metadata | Q17: live | R17: 305 | S17: Steven Guilbeault | T17: Climate; Climate Change; Environment
